Workbook
Name _00: #REF!
Name _1: #REF!
Name _2: #REF!
Name ddddddddddddddddd: #REF!
Name MM: #REF!
Name MM: #REF!
Name MM개발계획10월: #REF!
Name MM개발계획10월: #REF!
Name MM개발계획11월: #REF!
Name MM개발계획11월: #REF!
Name MM개발계획12월: #REF!
Name MM개발계획12월: #REF!
Name MM개발계획12월2005: #REF!
Name MM개발계획12월2005: #REF!
Name MM개발계획1월: #REF!
Name MM개발계획1월: #REF!
Name MM개발계획2월: #REF!
Name MM개발계획2월: #REF!
Name MM개발계획3월: #REF!
Name MM개발계획3월: #REF!
Name MM개발계획4월: #REF!
Name MM개발계획4월: #REF!
Name MM개발계획5월: #REF!
Name MM개발계획5월: #REF!
Name MM개발계획6월: #REF!
Name MM개발계획6월: #REF!
Name MM개발계획7월: #REF!
Name MM개발계획7월: #REF!
Name MM개발계획8월: #REF!
Name MM개발계획8월: #REF!
Name MM개발계획9월: #REF!

Sheet _com.sap.ip.bi.xl.hiddensheet

Sheet List
B2: No. | C2: Source System | D2: Interface ID | E2: 변경 IF-ID | F2: IN/OUT | G2: 맵핑정의 ID | H2: 맵핑정의 항목 | I2: 사용처 | J2: Entity 분류 | K2: 작업유형 | L2: I/F정의서 | M2: 적용순서 | N2: I/F Table | O2: STG Table(표준화) | P2: Import Program | Q2: 비고 | S2: 쿠도개발 | V2: Aplan 구분 | W2: Source System | X2: 작업유형 | Y2: Delta/Full Data | Z2: FILE | AA2: API/File | AB2: 예상건수 | AC2: 비고 | AD2: 모듈 | AE2: 기존IF ID | AF2: 코멘트 | AG2: 유형 | AH2: 공수(M/D) | AI2: Batch Cycle | AJ2: Batch Cycle Detail | AK2: Source/Target Table Name
B3: 1 | C3: SAP | D3: SDI4012 | E3: SDI8361 | F3: INBOUND | G3: CP-03 | H3: 조직도 | I3: 공통 | J3: M | K3: 유지 | L3: Y | M3: 1 | N3: ALIFCI_OGCH_MSTR | O3: ALCDCM_OGCH_MSTR | P3: SP_STGCM_OGCH_MSTR | S3: 45967 | V3: 공통 | W3: SAP | X3: 유지 | Y3: Delta | AA3: API | AD3: SD | AE3: SDI4012 CP-03.조직도 | AF3: 확장 | AG3: 유지 | AH3: 1 | AI3: W | AJ3: Random | AK3: ZSD_SEND_ORG_01
B4: 2 | C4: SAP | D4: SDI4004 | E4: SDI8362 | F4: INBOUND | G4: CP-01 | H4: 자재마스터(영업조직: CP) | I4: 공통 | J4: M | K4: 유지 | L4: Y | M4: 1 | N4: ALIFCI_MTRL_MSTR_CP | O4: ALCDCM_MTRL_MSTR ALCDCM_MTRL_MSTR_CP | P4: SP_STGCM_MTRL_MSTR_CP | V4: 공통 | W4: SAP | X4: 유지 | Y4: Delta | AA4: API | AC4: 영업조직/Item 별 속성정보 | AD4: SD | AE4: SDI4004 CP-01.자재마스터 | AF4: 필드추가 | AG4: 변경 | AH4: 3 | AI4: W,D | AJ4: 10Min | AK4: ZSD_SEND_MATERIAL_01
B5: =+B4+1 -> 3 | C5: SAP | D5: PPI2015 | E5: PPI2058 | F5: INBOUND | G5: SP-02 | H5: 자재마스터(플랜트: SP) | I5: 공통 | J5: M | K5: 유지 | L5: Y | M5: 1 | N5: ALIFCI_MTRL_MSTR_SP | O5: ALCDCM_MTRL_MSTR_SP | P5: SP_STGCM_MTRL_MSTR_SP | V5: 공통 | W5: SAP | X5: 유지 | Y5: Delta | AA5: API | AD5: PP | AE5: PPI2015 SP-02.자재 마스터 | AF5: 필드추가 | AG5: 변경 | AH5: 3 | AI5: W,D | AJ5: 15Min | AK5: ZPP_IF_MAT_SEND_SP
B6: =+B5+1 -> 4 | C6: SAP | D6: SDI4009 | E6: SDI8363 | F6: INBOUND | G6: CP-10 | H6: 자재 단가 | I6: 공통 | J6: M | K6: 유지 | L6: Y | M6: 1 | N6: ALIFCI_MTRL_UTPR | O6: ALCDCM_MTRL_UTPR | P6: SP_STGCM_MTRL_UTPR | V6: 공통 | W6: SAP | X6: 유지 | Y6: Delta | AA6: API | AC6: 판가 정보 | AD6: SD | AE6: SDI4009 CP-10.자재 단가 | AF6: 확장 | AG6: 유지 | AH6: 1 | AI6: W,D | AJ6: 10Min | AK6: ZSD_SEND_CHANNEL_PRICE
B7: =+B6+1 -> 5 | C7: NPD | D7: PPI2027 | E7: PPI2059 | F7: INBOUND | G7: CP-25 | H7: NPD 자재 목록 | I7: 공통 | J7: M | K7: 유지 | L7: Y | M7: 2 | N7: ALIFCI_DVLP_MTRL | O7: ALCDCM_DVLP_MTRL | P7: SP_STGCM_DVLP_MTRL | V7: 공통 | W7: NPD | X7: 유지 | Y7: Full | AA7: API | AC7: 현행화 주기 나 대상 검토 필요, 현재 업데이트가 되고 있지 않음 | AD7: NPD | AE7: PPI2027 CP-25.NPD 자재 목록 | AF7: 필드 추가(NPD 소비자가 72P) | AG7: 변경 | AH7: 3 | AI7: W,D | AJ7: Daily | AK7: ZPL_IF_DEVHEAD_SINGLE
B8: =+B7+1 -> 6 | C8: SAP | D8: SDI4029 | E8: SDI8364 | F8: INBOUND | G8: CP-07 | H8: 제품 허가 정보 | I8: 공통 | J8: M | K8: 유지 | L8: Y | M8: 2 | N8: ALIFCI_MTRL_WARR | O8: ALCDCM_MTRL_WARR | P8: SP_STGCM_MTRL_WARR | Q8: 국가별 제품사용허가 정보 | V8: 공통 | W8: SAP | X8: 유지 | Y8: Full | AA8: API | AC8: BOD 및 SKU IN/OUT 에서 사용함 | AD8: SD | AE8: SDI4029 CP-07.제품 허가 정보 | AF8: 티움넷->SAP 허가 관리 대상 로직 확인 필요 | AG8: 변경(상) | AH8: 5 | AI8: W,D | AJ8: Daily | AK8: ZSD_SEND_CONFIRM_MAT_O9
B9: =+B8+1 -> 7 | C9: SAP | D9: PPI2025 | E9: PPI2060 | F9: INBOUND | G9: SP-15 | H9: 단종 품의 완료 상태 | I9: 공통 | J9: M | K9: 유지 | L9: Y | M9: 2 | N9: ALIFCI_BEDI_CNSN | O9: ALCDCM_BEDI_CNSN | P9: SP_STGCM_BEDI_CNSN | V9: 공통 | W9: SAP | X9: 신규 | Y9: Real Time | AA9: API | AC9: SAP에서 압축 품의 후 상태 수신 | AD9: PP | AE9: 신규 | AF9: 1) Aplan -> SAP: 자재, 생산단종월, 판매단종월 인터페이스 2) SAP에서 압축 품의 (Aplan에서 품의하지 않음) 3) SAP -> Aplan: 압축품의일(월), 압축대상분류 인터페이스 | AG9: 신규 | AH9: 5 | AI9: 15Min | AJ9: Random | AK9: TBD
B10: =+B9+1 -> 8 | C10: BW | D10: BII0229 | E10: BII0246 | F10: INBOUND | G10: CP-23 | H10: SKU 현황 | I10: 공통 | J10: M | K10: 유지 | L10: Y | M10: 2 | N10: ALIFCI_MTRL_PS | O10: ALCDCM_MTRL_PS | P10: SP_STGCM_MTRL_PS | V10: 공통 | W10: BW | X10: 유지 | Y10: Full | Z10: File | AA10: File | AB10: 6.5k | AD10: BW | AE10: BII0229 CP-23.SKU 현황 | AG10: 유지 | AH10: 1 | AI10: W,D | AJ10: Daily | AK10: ZBI_SEND_FILE_TO_O9
B11: =+B10+1 -> 9 | C11: NPD | D11: PPI2026 | E11: PPI2061 | F11: INBOUND | G11: CP-24 | H11: SKU In 일정 | I11: 공통 | J11: M | K11: 유지 | L11: Y | M11: 2 | N11: ALIFCI_MTRL_LNCH_SCH | O11: ALCDCM_MTRL_LNCH_SCH | P11: SP_STGCM_MTRL_LNCH_SCH | V11: 공통 | W11: NPD | X11: 유지 | Y11: Full | AA11: API | AD11: NPD | AE11: PPI2026 CP-24.SKU In 일정 | AF11: 필드 추가(NPD 생산회의 상태 68P) | AG11: 변경 | AH11: 3 | AI11: W,D | AJ11: Daily | AK11: ZPL_IF_MT_SINGLE
B12: =+B11+1 -> 10 | C12: SAP | D12: PPI2017 | E12: PPI2062 | F12: INBOUND | G12: SP-19 | H12: 자재마스터 대체단위 인터페이스 매핑구조 | I12: 공통 | J12: M | K12: 유지 | L12: Y | M12: 1 | N12: ALIFCI_MTRL_UNIT_CNVT | O12: ALCDCM_MTRL_UNIT_CNVT | P12: SP_STGCM_MTRL_UNIT_CNVT | V12: 공통 | W12: SAP | X12: 유지 | Y12: Full | AD12: PP | AE12: PPI2017 SP-19.자재마스터 대체단위 인터페이스 매핑구조 | AF12: 필드 추가 | AG12: 변경 | AH12: 3
B13: =+B12+1 -> 11 | C13: SAP | D13: PPI2011 | E13: PPI2063 | F13: INBOUND | G13: SP-13 | H13: 자재마스터 원가정보 | I13: 공통 | J13: M | K13: 유지 | L13: Y | M13: 2 | N13: ALIFCI_MTRL_PRPR | O13: ALCDCM_MTRL_PRPR | P13: SP_STGCM_MTRL_PRPR | V13: 공통 | W13: SAP | X13: 유지 | Y13: Delta | AA13: API | AC13: 해외 정보 확인 필요 | AD13: PP | AE13: PPI2011 SP-13.자재마스터 원가정보 | AG13: 유지 | AH13: 1 | AI13: D | AJ13: Daily | AK13: ZPP_IF_STD_PRICE_SEND_SP
B14: =+B13+1 -> 12 | C14: BW | D14: BII0224 | E14: BII0247 | F14: INBOUND | G14: CP-12 | H14: 재고 | I14: 공통 | J14: A | K14: 유지 | L14: Y | M14: 1 | N14: ALIFCI_INVN | O14: ALCDCA_INVN | P14: SP_STGCA_INVN | V14: 공통 | W14: BW | X14: 유지 | Y14: Full | Z14: File | AA14: File | AB14: 364k | AD14: BW | AE14: BII0224 CP-12.재고 | AG14: 유지 | AH14: 1 | AI14: D | AJ14: Daily | AK14: ZBI_SEND_FILE_TO_O9
A15: 대표다이나믹 | B15: =+B14+1 -> 13 | C15: SAP | D15: SDI4018 | E15: SDI8365 | F15: INBOUND | G15: CP-40 | H15: 재고(계획용) | I15: 공통 | J15: A | K15: 수정 | L15: Y | M15: 1 | N15: ALIFCI_INVN_PLAN | O15: ALCDCA_INVN_PLAN | P15: SP_STGCA_INVN_PLAN | Q15: 취소==> 시간차이로 다시 수정후 사용결정(11/04)이봉기=> 기존 그대로 사용하고, 주문생성후 dn미부여는 추가 인터페이스하여 활용(11/17일). | Y15: Full | Z15: File | AA15: File | AB15: 345k
B16: =+B15+1 -> 14 | C16: SAP | D16: SDI4005 | E16: SDI8366 | F16: INBOUND | G16: CP-02 | H16: 거래처마스터 | I16: DP | J16: M | K16: 유지 | L16: Y | M16: 1 | N16: ALIFCI_PRTN_MSTR | O16: ALCDCM_PRTN_MSTR | P16: SP_STGCM_PRTN_MSTR | Q16: 거래처 그룹 기준정보 필요.(데이터 존재여부) | V16: DP | W16: SAP | X16: 유지 | Y16: Delta | AA16: API | AD16: SD | AE16: SDI4005 CP-02.거래처마스터 | AG16: 유지 | AH16: 1 | AI16: W | AJ16: 15Min | AK16: ZSD_SEND_CUSTOMER_01
B17: =+B16+1 -> 15 | C17: BW | D17: BII0230 | E17: BII0248 | F17: INBOUND | G17: CP-39 | H17: SKU 목표 | I17: DP | J17: A | K17: 유지 | L17: Y | M17: 2 | N17: ALIFCI_YRLY_SAL_PLAN | O17: ALCDCA_YRLY_SAL_PLAN | P17: SP_STGCA_YRLY_SAL_PLAN | Q17: 년월+SKU 단위 판매목표수량 | V17: DP | W17: BW | X17: 유지 | Y17: Full | Z17: File | AA17: File | AB17: 3k | AD17: BW | AE17: BII0230 CP-39.SKU 목표 | AG17: 유지 | AH17: 1 | AI17: W,D | AJ17: Daily | AK17: ZBI_SEND_FILE_TO_O9
B18: =+B17+1 -> 16 | C18: BW | D18: BII0232 | E18: BII0249 | F18: INBOUND | G18: CP-42 | H18: 기준환율 | I18: DP | J18: A | K18: 유지 | L18: Y | M18: 2 | N18: ALIFCI_STND_EXRT | O18: ALCDCA_STND_EXRT | P18: SP_STGCA_STND_EXRT | Q18: 환율일자 추가가 필요하다고 판단됨 | V18: DP | W18: BW | X18: 유지 | Y18: Full | Z18: File | AA18: File | AB18: 1k | AC18: 유지(값의 정합성 확인 필요) 영업 조직별 기준환율이 I/F 되어야 함 | AD18: BW | AE18: BII0232 CP-42.기준환율 | AG18: 유지 | AH18: 1 | AI18: W,D | AJ18: Daily | AK18: ZBI_SEND_FILE_TO_O9
A19: 대표다이나믹 | B19: =+B18+1 -> 17 | C19: SAP | D19: SDI4030 | E19: SDI8367 | F19: INBOUND | G19: CP-32 | H19: 수출 진행 모니터링 | I19: DP | J19: A | K19: 유지 | L19: Y | M19: 2 | N19: ALIFCI_EXPO_PRGR_MONI | O19: ALCDCA_EXPO_PRGR_MONI | P19: SP_STGCA_EXPO_PRGR_MONI | V19: DP | W19: SAP | X19: 유지 | Y19: Full | AA19: API | AD19: SD | AE19: SDI4030 CP-32.수출 진행 모니터링 | AG19: 유지 | AH19: 1 | AI19: W,D | AJ19: Daily | AK19: ZSD_SEND_EXPORT_O9
B20: =+B19+1 -> 18 | C20: BW | D20: BII0234 | E20: BII0250 | F20: INBOUND | G20: CP-49 | H20: 거래처 재고 | I20: DP | J20: A | K20: 유지 | L20: Y | M20: 3 | N20: ALIFCI_PRTN_INVN | O20: ALCDCA_PRTN_INVN | P20: SP_STGCA_PRTN_INVN | V20: DP | W20: BW | X20: 유지 | Y20: Full | Z20: File | AA20: File | AB20: 1k | AD20: BW | AE20: BII0234 CP-49.거래처 재고 | AG20: 유지 | AH20: 1 | AI20: W,D | AJ20: Daily | AK20: ZBI_SEND_FILE_TO_O9
B21: =+B20+1 -> 19 | C21: BW | D21: BII0226 | E21: BII0251 | F21: INBOUND | G21: CP-19 | H21: 기타 수요(잡출) | I21: DP | J21: A | K21: 수정 | L21: Y | M21: 3 | N21: ALIFCI_OTH_DMD | O21: ALCDCA_OTH_DMD | P21: SP_STGCA_OTH_DMD | V21: DP | W21: BW | X21: 수정 | Y21: Full | Z21: File | AA21: File | AB21: 4.7k | AC21: Layout 변경(PG → Sold-To-Party 로 변경 | AD21: BW | AE21: BII0226 CP-19.기타 수요(잡출) | AF21: 거래처 단위 로직 변경 | AG21: 변경 | AH21: 3 | AI21: Weekly,Daily | AJ21: Daily | AK21: ZBI_SEND_FILE_TO_O9
B22: =+B21+1 -> 20 | C22: SAP | D22: PPI2003 | E22: PPI2064 | F22: INBOUND | G22: SP-01 | H22: BOM Master | I22: SP | J22: M | K22: 유지 | L22: Y | M22: 1 | N22: ALIFCI_BOM_MSTR | O22: ALCDCM_BOM_MSTR | P22: SP_STGCM_BOM_MSTR | V22: SP | W22: SAP | X22: 유지 | Y22: Delta | AA22: API | AD22: PP | AE22: PPI2003 SP-01.BOM | AF22: 신규 플랜트 로직 수정 필요 | AG22: 변경 | AH22: 3 | AI22: D | AJ22: Daily | AK22: ZPP_IF_BOM_SEND_SP
B23: =+B22+1 -> 21 | C23: SAP | D23: PPI2006 | E23: PPI2065 | F23: INBOUND | G23: SP-05 | H23: 작업장 마스터 | I23: SP | J23: M | K23: 유지 | L23: Y | M23: 1 | N23: ALIFCI_MFG_WKNS | O23: ALCDCM_MFG_WKNS | P23: SP_STGCM_MFG_WKNS | V23: SP | W23: SAP | X23: 유지 | Y23: Delta | AA23: API | AC23: (작업장 기준 Grouping 해서 Resource 로 정의 | AD23: PP | AE23: PPI2006 SP-05.작업장 마스터 | AG23: 유지 | AH23: 1 | AI23: W | AJ23: Random | AK23: ZPP_IF_WORKCENTER_SEND_SP
A24: 대표다이나믹 | B24: =+B23+1 -> 22 | C24: SAP | D24: PPI2009 | E24: PPI2066 | F24: INBOUND | G24: SP-10 | H24: 생산 오더 | I24: SP | J24: A | K24: 유지 | L24: Y | M24: 1 | N24: ALIFCI_MFG_ORD | O24: ALCDCA_MFG_ORD | P24: SP_STGCA_MFG_ORD | V24: SP | W24: SAP | X24: 유지 | Y24: Delta | AA24: API | AC24: 국내 포함 전체(해외)Plant 반영 필요 | AD24: PP | AE24: PPI2009 SP-10.생산 오더 | AG24: 변경 | AH24: 3 | AI24: W,D | AJ24: Daily | AK24: ZPP_IF_PROD_ORDER_SEND_SP
A25: 대표다이나믹 | B25: =+B24+1 -> 23 | C25: SAP | D25: PPI2010 | E25: PPI2067 | F25: INBOUND | G25: SP-11 | H25: 구매오더 | I25: SP | J25: A | K25: 유지 | L25: Y | M25: 1 | N25: ALIFCI_PUR_ORD | O25: ALCDCA_PUR_ORD | P25: SP_STGCA_PUR_ORD | V25: SP | W25: SAP | X25: 유지 | Y25: Delta | AA25: API | AC25: ODM 포함 전체 구매오더로 반영되어야 하고 확인 필요 | AD25: PP | AE25: PPI2010 SP-11.구매오더 | AG25: 유지 | AH25: 1 | AI25: W,D | AJ25: Daily | AK25: ZPP_IF_PURCH_ORDER_SEND_SP
B26: =+B25+1 -> 24 | C26: SAP | D26: PPI2004 | E26: PPI2068 | F26: INBOUND | G26: SP-03 | H26: 구매정보 (ODM 원부자재) | I26: SP | J26: M | K26: 유지 | L26: Y | M26: 2 | N26: ALIFCI_MTRL_PUR | O26: ALCDCM_MTRL_PUR | P26: SP_STGCM_MTRL_PUR | V26: SP | W26: SAP | X26: 유지 | Y26: Delta | AA26: API | AC26: ODM Network 구성 및 포장재 구매처 정의 (Category 컬럼-> 구매 또는 외주가공 정의 가능) | AD26: PP | AE26: PPI2004 SP-03.구매정보(ODM 외주 원부자재) | AG26: 유지 | AH26: 1 | AI26: W,D | AJ26: Daily | AK26: ZPP_IF_INFOREC_SEND_SP
B27: =+B26+1 -> 25 | C27: SAP | D27: PPI2005 | E27: PPI2069 | F27: INBOUND | G27: SP-04 | H27: 협력사 마스터 | I27: SP | J27: M | K27: 유지 | L27: Y | M27: 2 | N27: ALIFCI_SBCN_MSTR | O27: ALCDCM_SBCN_MSTR | P27: SP_STGCM_SBCN_MSTR | V27: SP | W27: SAP | X27: 유지 | Y27: Delta | AA27: API | AD27: PP | AE27: PPI2005 SP-04.협력사 마스터 | AG27: 유지 | AH27: 1 | AI27: W | AJ27: Daily | AK27: ZPP_IF_VENDOR_SEND_SP
B28: =+B27+1 -> 26 | C28: SAP | D28: PPI2016 | E28: PPI2070 | F28: INBOUND | G28: SP-14 | H28: 가용화 입고 실적 | I28: SP | J28: A | K28: 유지 | L28: Y | M28: 1 | N28: ALIFCI_AVAB_WRHS_PRFR | O28: ALCDCA_AVAB_WRHS_PRFR | P28: SP_STGCA_AVAB_WRHS_PRFR | V28: SP | W28: SAP | X28: 유지 | Y28: Delta | AA28: API | AC28: 엔진 Input은 아니나 활용 측면에서 검토 필요 | AD28: PP | AE28: PPI2016 SP-14.가용화 입고 실적 | AG28: 유지 | AH28: 1 | AI28: 2/Day | AJ28: 2/day( 11AM , 03PM) | AK28: ZPP_IF_AVAIL_STOCK_SEND_SP
A29: 대표다이나믹 | B29: =+B28+1 -> 27 | C29: SAP | D29: SDI4026 | E29: SDI8368 | F29: INBOUND | G29: CP-37 | H29: SOP 잔량 정보 | I29: SP | J29: A | K29: 유지 | L29: Y | M29: 1 | N29: ALIFCI_LOAD_RMN_QTY | O29: ALCDCA_LOAD_RMN_QTY | P29: SP_STGCA_LOAD_RMN_QTY | V29: SP | W29: SAP | X29: 유지 | Y29: Full | AA29: API | AC29: 선적잔량 | AD29: SC | AE29: SDI4026 CP-37.SOP 잔량 정보 | AF29: 해외요청량 프로세스 Aplan 개발 범위에 따라 공수 변동 | AG29: 유지 | AH29: 1 | AI29: W,D | AJ29: Sunday | AK29: ZSC_PIR_O9_SAP_002
B30: =+B29+1 -> 28 | C30: SAP | D30: PPI2007 | E30: PPI2071 | F30: INBOUND | G30: SP-08 | H30: 반제품 포장재 MD04 재고 | I30: SP | J30: A | K30: 유지 | L30: Y | M30: 1 | N30: ALIFCI_SMPR_INVN | O30: ALCDCA_SMPR_INVN | P30: SP_STGCA_SMPR_INVN | V30: SP | W30: SAP | X30: 유지 | Y30: Full | AA30: API | AC30: 반제품 재고 수량 + QA 수량 | AD30: PP | AE30: PPI2007 SP-08.반제품 포장재 MD04 재고 | AG30: 유지 | AH30: 1 | AI30: 2/Day | AJ30: Daily | AK30: ZPP_IF_MD04STOCK_SEND_SP
B31: =+B30+1 -> 29 | C31: IAM | D31: LEGI3532 | E31: LEGI3532 | F31: INBOUND | G31: CP-04 | H31: Role 권한 승인 정보 | I31: SYS | J31: M | K31: 유지 | L31: Y | M31: 2 | N31: ALIFCI_AUTH_ROLE | O31: ALCDCM_AUTH_ROLE | P31: SP_STGCM_AUTH_ROLE | V31: System | W31: IAM | X31: 유지 | Y31: - | AA31: API | AD31: IAM | AE31: LEGI3532 CP-04.Role 권한 승인 정보 | AF31: IAM 박소영님/레이아웃 재정의 | AG31: 변경(상) | AH31: 5 | AI31: 2/Day | AJ31: 11:30:00 AM / 04:30 PM | AK31: EX_IF_ROLE
B32: =+B31+1 -> 30 | C32: IAM | D32: LEGI3531 | E32: LEGI3531 | F32: INBOUND | G32: CP-04 | H32: 계정 승인 정보 | I32: SYS | J32: M | K32: 유지 | L32: Y | M32: 1 | N32: ALIFCI_USER_ACCT | O32: ALCDCM_USER_ACCT | P32: SP_STGCM_USER_ACCT | V32: System | W32: IAM | X32: 유지 | Y32: Delta | AA32: API | AD32: IAM | AE32: LEGI3531 CP-04. 계정 승인 정보 | AF32: IAM 박소영님/레이아웃 재정의 | AG32: 변경(상) | AH32: 5 | AI32: 2/Day | AJ32: 11:30:00 AM / 04:30 PM | AK32: EX_IF_RES_USER
B33: =+B32+1 -> 31 | C33: SAP | D33: SDI4011 | E33: SDI8369 | F33: INBOUND | G33: CP-34 | H33: CP 코드 마스터 | I33: SYS | J33: M | K33: 유지 | L33: Y | M33: 1 | N33: ALIFCI_CP_CD_MSTR | O33: ALCDCM_CP_CD_MSTR | P33: SP_STGCM_CP_CD_MSTR | Q33: SAP 공통코드 | S33: 45965 | V33: DP | W33: SAP | X33: 신규 | AD33: SD | AE33: SDI4011 CP-34.CP 코드 마스터 | AF33: 왜 신규 인터페이스인지 확인 필요 | AG33: 신규 | AH33: 5
B34: =+B33+1 -> 32 | C34: SAP | D34: SDI8354 | E34: SDI8354 | F34: INBOUND | G34: SP-41 | H34: SP-41. 저장위치리스트 | I34: 공통 | J34: M | K34: 신규 | L34: Y | N34: ALIFCI_INVN_SLOC | O34: ALCDCM_INVN_SLOC | P34: SP_STGCM_INVN_SLOC | Q34: SRC 시스템 다름 | R34: 20251020추가 | V34: SP | W34: SAP | X34: 신규
B35: =+B34+1 -> 33 | C35: SAP | D35: PPI2018 | E35: PPI2072 | F35: INBOUND | G35: SP-20 | H35: 공장달력 인터페이스 | I35: SP | J35: A | K35: 수정 | L35: Y | N35: ALIFCI_PLNT_CLD | O35: ALCDCA_PLNT_CLD | P35: SP_STGCA_PLNT_CLD | R35: 20251020추가 | V35: SP | W35: SAP | X35: 유지 | AD35: PP | AE35: PPI2018 SP-20.공장달력 인터페이스 | AF35: 공장달력 인터페이스 누락되어 추가 | AG35: 유지 | AH35: 1
A36: 보류 | B36: =+B35+1 -> 34 | C36: CDP | D36: TBD | F36: INBOUND | G36: DP-50 | H36: 거래처 협업 유통사 판매 재고 | I36: DP | J36: A | K36: 신규 | L36: Y | N36: ALIFCI_PRTN_DSTR_INVN | O36: ALCDCA_PRTN_DSTR_INVN | P36: SP_STGCA_PRTN_DSTR_INVN | Q36: 글루 사용 I/F | R36: 20251020추가 | V36: DP | W36: CDP | X36: 신규 | AC36: 재고, 판매 | AD36: CDP | AE36: 신규 | AF36: 신규 (거래처 협업 유통사 데이터, 84P) 글루 I/F만 허용 | AG36: 신규 | AH36: 5
A37: 보류 | B37: =+B36+1 -> 35 | C37: CDP | D37: TBD | F37: INBOUND | G37: DP-51 | H37: 거래처 협업 유통사 판매 재고(월) | I37: DP | J37: A | K37: 신규 | L37: Y | N37: ALIFCI_PRTN_DSTR_MTH_INVN | O37: ALCDCA_PRTN_DSTR_MTH_INVN | P37: SP_STGCA_PRTN_DSTR_MTH_INVN | Q37: 글루 사용 I/F | R37: 20251020추가 | V37: DP | W37: CDP | X37: 신규 | AC37: 재고, 판매 (월) | AD37: CDP | AE37: 신규 | AF37: 신규 (거래처 협업 유통사 데이터, 84P) 글루 I/F만 허용 | AG37: 신규 | AH37: 5
A38: 보류 | B38: =+B37+1 -> 36 | C38: CDP | D38: TBD | F38: INBOUND | G38: SP-42 | H38: 재고 Aging 상태 | I38: SP | J38: A | K38: 신규 | L38: Y | N38: ALIFCI_INVN_AG_ST | O38: ALCDCA_INVN_AG_ST | P38: SP_STGCA_INVN_AG_ST | Q38: 글루 사용 I/F | R38: 20251020추가 | V38: SP | W38: CDP | X38: 신규 | AC38: SAP, EWM, 아폴로, 3PL 데이터를 CDP에서 통합하여 연계 | AD38: CDP | AE38: 신규 | AF38: 신규 (재고 Aging, 52P) 글루 I/F만 허용 | AG38: 신규 | AH38: 5
A39: 보류 | B39: =+B38+1 -> 37 | C39: CDP | D39: TBD | F39: INBOUND | G39: DP-52 | H39: 엔진상품 리스트 | I39: SP | J39: M | K39: 신규 | L39: Y | N39: ALIFCI_ENGN_PRD | O39: ALCDCM_ENGN_PRD | P39: SP_STGCM_ENGN_PRD | Q39: 글루 사용 I/F | R39: 20251020추가 | V39: SP | W39: CDP | X39: 신규 | AD39: CDP | AE39: 신규 | AF39: 글루 I/F만 허용 | AG39: 신규 | AH39: 5
B40: =+B39+1 -> 38 | C40: BW | D40: BII0237 | E40: BII0237 | F40: INBOUND | G40: DP-42-1 | H40: DP-42-1. 자재정보추가_BW | I40: 공통 | J40: M | K40: 신규 | L40: Y | N40: ALIFCI_MTRL_XTRA_ATTR1 | O40: ALCDCM_MTRL_MSTR(업데이트 Only) | P40: SP_STGCM_MTRL_MSTR_XTRA1 | R40: 20251020추가 | V40: 공통 | W40: BW | X40: 신규 | Z40: File | AD40: BW | AE40: 신규 | AG40: 신규
B41: =+B40+1 -> 39 | C41: BW | D41: BII0238 | E41: BII0238 | F41: INBOUND | G41: DP-42-2 | H41: DP-42-2. 자재정보추가_BW | I41: 공통 | J41: M | K41: 신규 | L41: Y | N41: ALIFCI_MTRL_XTRA_ATTR2 | O41: ALCDCM_MTRL_MSTR_CP(업데이트 Only) | P41: SP_STGCM_MTRL_MSTR_XTRA2 | R41: 20251020추가 | V41: 공통 | W41: BW | X41: 신규 | Z41: File | AD41: BW | AE41: 신규
B42: =+B41+1 -> 40 | C42: BW | D42: BII0239 | E42: BII0239 | F42: INBOUND | G42: DP-42-3 | H42: DP-42-3. 자재정보추가_BW | I42: 공통 | J42: M | K42: 신규 | L42: Y | N42: ALIFCI_MTRL_XTRA_ATTR3 | O42: ALCDCM_MTRL_MSTR_CP_YRMN_HIST | P42: SP_STGCM_MTRL_MSTR_XTRA3 | R42: 20251020추가 | V42: 공통 | W42: BW | X42: 신규 | Z42: File | AD42: BW | AE42: 신규
B43: =+B42+1 -> 41 | C43: BW | D43: BII0240 | E43: BII0240 | F43: INBOUND | G43: DP-43-1 | H43: DP-43-1. 거래처정보추가_BW(유통경로) | I43: 공통 | J43: M | K43: 신규 | L43: Y | N43: ALIFCI_PRTN_XTRA_ATTR1 | O43: ALCDCM_PRTN_MSTR(업데이트 ONLY) | P43: SP_STGCM_PRTN_XTRA_ATTR1 | Q43: SBW17 | R43: 20251020추가 | V43: 공통 | W43: BW | X43: 신규 | Z43: File | AD43: BW | AE43: 신규
B44: =+B43+1 -> 42 | C44: BW | D44: BII0241 | E44: BII0241 | F44: INBOUND | G44: DP-43-2 | H44: DP-43-2. 거래처정보추가_BW(영업조직 회사정보) | I44: 공통 | J44: M | K44: 신규 | L44: Y | N44: ALIFCI_PRTN_XTRA_ATTR2 | O44: ALCDCM_SORG_CMPY | P44: SP_STGCM_PRTN_XTRA_ATTR2 | Q44: SBW18 | R44: 20251020추가 | V44: 공통 | W44: BW | X44: 신규 | Z44: File | AD44: BW | AE44: 신규
A45: 대표다이나믹 | B45: =+B44+1 -> 43 | C45: BW | D45: BII0242 | E45: BII0242 | F45: INBOUND | G45: DP-44 | H45: DP-44. 마감계획_BW | I45: 공통 | J45: A | K45: 신규 | L45: Y | N45: ALIFCI_DDLN_PLAN | O45: ALCDCA_DDLN_PLAN | P45: SP_STGCA_DDLN_PLAN | Q45: 수정완료(12/3)SBW19 | R45: 20251020추가 | V45: 공통 | W45: BW | X45: 신규 | Z45: File | AD45: BW | AE45: 신규
A46: 대표다이나믹 | B46: =+B45+1 -> 44 | C46: BW | D46: BII0243 | E46: BII0243 | F46: INBOUND | G46: DP-46 | H46: DP-46. 판매실적_거래처&SKU | I46: 공통 | J46: A | K46: 신규 | L46: Y | N46: ALIFCI_SAL_PRFR | O46: ALCDCA_SAL_PRFR | P46: SP_STGCA_SAL_PRFR | Q46: 수정완료(12/3)-SBW20 | R46: 20251020추가 | V46: 공통 | W46: BW | X46: 신규 | Z46: File | AD46: BW | AE46: 신규
A47: 대표다이나믹 | B47: =+B46+1 -> 45 | C47: BW | D47: BII0244 | E47: BII0244 | F47: INBOUND | G47: DP-48 | H47: DP-48. 주문실적_거래처&SKU | I47: 공통 | J47: A | K47: 신규 | L47: Y | N47: ALIFCI_ORD_LACK | O47: ALCDCA_ORD_LACK | P47: SP_STGCA_ORD_LACK | Q47: 수정완료(12/3)-SBW21 | R47: 20251020추가 | V47: 공통 | W47: BW | X47: 신규 | Z47: File | AD47: BW | AE47: 신규
A48: 대표다이나믹 | B48: =+B47+1 -> 46 | C48: BW | D48: BII0245 | E48: BII0245 | F48: INBOUND | G48: DP-49 | H48: DP-49. 목표&예상이익 | I48: 공통 | J48: A | K48: 신규 | L48: Y | N48: ALIFCI_GOAL_EXPC_PRFT | O48: ALCDCA_GOAL_EXPC_PRFT | P48: SP_STGCA_GOAL_EXPC_PRFT | Q48: 수정완료(12/3) | R48: 20251020추가 | V48: 공통 | W48: BW | X48: 신규 | Z48: File | AD48: BW | AE48: 신규
B49: =+B48+1 -> 47 | C49: SAP | D49: SDI8353 | E49: SDI8353 | F49: INBOUND | G49: DP-53 | H49: DP-53. 신제품추정단가 | I49: DP | J49: M | K49: 신규 | L49: Y | N49: ALIFCI_NEW_PRD_ESTI_UTPR | O49: ALCDCM_NEW_PRD_ESTI_UTPR | P49: SP_STGCM_NEW_PRD_ESTI_UTPR | R49: 20251106추가
A50: 대표다이나믹 | B50: =+B49+1 -> 48 | C50: SAP | D50: PPI2055 | E50: PPI2055 | F50: INBOUND | G50: SP-43 | H50: SP-43. 라우팅관리(SAP) | I50: SP | J50: M | K50: 신규 | L50: Y | N50: ALIFCI_MFRU_MSTR1 | O50: ALCDCM_MFRU_MSTR1 | P50: SP_STGCM_MFRU_MSTR1 | R50: 20251106추가
A51: 대표다이나믹 | B51: =+B50+1 -> 49 | C51: SAP | D51: PPI2056 | E51: PPI2056 | F51: INBOUND | G51: SP-44 | H51: SP-44. 라우팅관리(SAP)2 | I51: SP | J51: M | K51: 신규 | L51: Y | N51: ALIFCI_MFRU_MSTR2 | O51: ALCDCM_MFRU_MSTR2 | P51: SP_STGCM_MFRU_MSTR2 | R51: 20251106추가
B52: =+B51+1 -> 50 | C52: SAP | D52: SDI8352 | E52: SDI8352 | F52: INBOUND | G52: SP-45 | H52: SP-45. 영업저장위치관리 | I52: SP | J52: M | K52: 신규 | L52: Y | N52: ALIFCI_SALES_SLOC | O52: ALCDCM_SALES_SLOC | P52: SP_STGCM_SALES_SLOC | R52: 20251106추가
B53: =+B52+1 -> 51 | C53: SAP | D53: PPI2057 | E53: PPI2057 | F53: INBOUND | G53: DP-55 | H53: DP-55. SAP압축품의 정보 | I53: DP | J53: M | K53: 신규 | L53: Y | N53: ALIFCI_SAP_BEDI_CNSN | O53: ALCDCM_SAP_BEDI_CNSN | P53: SP_STGCM_SAP_BEDI_CNSN | R53: 20251106추가
B54: =+B53+1 -> 52 | C54: SAP | F54: INBOUND | G54: SP-46 | H54: SP-46. SAP재고에이징데이터(중국) | I54: SP | J54: A | K54: 신규 | L54: Y | N54: ALIFCI_SAP_AG_INVN_CHIN | O54: ALCDCA_SAP_AG_INVN_CHIN | P54: SP_STGCA_SAP_AG_INVN_CHIN | R54: 20251126추가
B55: =+B54+1 -> 53 | C55: BW | D55: BII0252 | E55: BII0252 | F55: INBOUND | G55: DP-57 | H55: DP-57. BW 코드별 네이밍 마스터 | I55: DP | J55: M | K55: 신규 | L55: Y | N55: ALIFCI_BW_CD_MSTR | O55: ALCDCM_BW_CD_MSTR | P55: SP_STGCM_BW_CD_MSTR | R55: 20251203추가
A56: 대표다이나믹 | B56: =+B55+1 -> 54 | C56: SAP | D56: SDI8358 | E56: SDI8358 | F56: INBOUND | G56: SP-47 | H56: 오픈SO(계획용) | I56: SP | J56: A | K56: 신규 | L56: Y | N56: ALIFCI_OPEN_SAL_ORD | O56: ALCDCA_OPEN_SAL_ORD | P56: SP_STGCA_OPEN_SAL_ORD | Q56: 20251205 ERP팀추가
A57: 대표다이나믹 | B57: =+B56+1 -> 55 | C57: SAP | D57: SDI8359 | E57: SDI8359 | F57: INBOUND | G57: SP-48 | H57: 판매처별 위탁재고 | I57: SP | J57: A | K57: 신규 | L57: Y | N57: ALIFCI_PRTN_TS_INVN | O57: ALICDCA_PRTN_TS_INVN | P57: SP_STGCA_PRTN_TS_INVN | Q57: 20251205 ERP팀추가
A62: 삭제 | B62: 14 | C62: SAP | F62: INBOUND | G62: SP-18 | H62: 플랜트 저장위치 매핑 마스터 | I62: 공통 | J62: M | K62: 삭제 | L62: Y | M62: 1 | N62: ALIFCI_INVN_SLOC | O62: ALCDCM_INVN_SLOC | P62: 20251202삭제 | Q62: 저장위치리스트(SP-41)로 대체. 25.11.19삭제
A63: 삭제 | B63: 16 | C63: BW | F63: INBOUND | H63: 거래처 / GPS 목표채널 Mapping 정보 | I63: DP | J63: M | K63: 삭제 | L63: Y | M63: 1 | P63: 20251202삭제 | Q63: 거래처 추가 칼럼에 GPS채널 존재 25.11.19 삭제
A64: 삭제 | B64: 17 | C64: BW | D64: BII0227 | F64: INBOUND | G64: CP-20 | H64: 주문 실적/결품 수량 | I64: DP | J64: A | K64: 삭제 | L64: Y | M64: 2 | N64: ALIFCI_ORD_LACK | O64: ALCDCA_ORD_LACK | P64: 20251202삭제 | V64: DP | W64: BW | X64: 수정 | Y64: Full | AA64: File | AB64: 110k | AC64: Layout 변경(PG → Sold-To-Party 로 변경 | AD64: BW | AE64: BII0227 CP-20.주문 실적/결품 수량 | AF64: 거래처 단위 로직 변경 | AG64: 변경 | AH64: 3 | AI64: W,D | AJ64: Daily | AK64: ZBI_SEND_FILE_TO_O9
A65: 삭제 | B65: 18 | C65: BW | D65: BII0228 | F65: INBOUND | G65: CP-21 | H65: 판매실적 | I65: DP | J65: A | K65: 삭제 | L65: Y | M65: 1 | N65: ALIFCI_SAL_PRFR | O65: ALCDCA_SAL_PRFR | P65: 20251202삭제 | V65: DP | W65: BW | X65: 수정 | Y65: Full | AA65: File | AB65: 201k | AC65: Layout 변경(PG → Sold-To-Party 로 변경 | AD65: BW | AE65: BII0228 CP-21.판매 실적 | AF65: 거래처 단위 로직 변경 | AG65: 변경 | AH65: 3 | AI65: W,D | AJ65: Daily | AK65: ZBI_SEND_FILE_TO_O9
A66: 삭제 | B66: 27 | C66: SAP | D66: LEGI2972 | F66: INBOUND | G66: SP-06 | H66: ROS | I66: SP | J66: M | K66: 삭제 | L66: Y | M66: 1 | N66: ALIFCI_ROS_MSTR | O66: ALCDCM_ROS_MSTR | P66: 20251202삭제 | Q66: ROUTING으로 대체.25.11.18 | V66: SP | W66: SAP | X66: 신규 | Y66: Full | AA66: API | AC66: 해외사업장 확장으로 인해서 원천을 SAP 로 변경, MES 한국 Plant만 존재함 | AD66: PP | AE66: 신규-LEGI2972 SP-06.ROS | AG66: 신규 | AH66: 5 | AI66: 15Min | AJ66: 목(Thu)/토(Sat) | AK66: MWRKTI_ROS_PACK_PRFR_SND
A67: 삭제 | B67: 35 | C67: 구매포털 | D67: LEGI3534 | F67: INBOUND | G67: CP-36 | H67: 협력사 원부자재 재고 | I67: SP | J67: A | K67: 삭제 | L67: Y | M67: 2 | N67: ALIFCI_SBCN_MTRL_INVN | O67: ALCDCA_SBCN_MTRL_INVN | P67: 20251202삭제 | Q67: 20251113_제외처리_이봉기 | V67: SP | W67: 구매포털 | X67: 유지 | Y67: Full | AA67: API | AD67: 구매포털 | AE67: LEGI3534 CP-36.협력사 원부자재 재고 | AG67: 유지 | AH67: 1 | AI67: W,D | AJ67: Daily | AK67: -
A68: 삭제 | B68: =+B33+1 -> 32 | C68: SAP | D68: TBD | F68: INBOUND | G68: CP-40 | H68: Lot ID별 재고정보 | I68: SP | K68: 삭제 | P68: 20251202삭제 | Q68: 신규추가_2025.10.20 (확인필요) 삭제(251119) | V68: 공통 | W68: SAP | X68: 신규 | Y68: Full | AA68: File | AC68: 재고(계획용) | AD68: SD | AE68: SDI4018 CP-40.재고(계획용) | AF68: DN, GI 상태 고려한 기준 변경 | AG68: 변경(상) | AH68: 5 | AI68: D | AJ68: Daily | AK68: TBD
A69: 삭제 | B69: =+B68+1 -> 33 | C69: SAP | D69: TBD | F69: INBOUND | G69: CP-40 | H69: 판매실적(계획용) | I69: SP | K69: 삭제 | P69: 20251202삭제 | Q69: 신규추가_2025.10.20 (확인필요) 삭제(251119) 삭제재확인(251126) | V69: 공통 | W69: SAP | X69: 신규 | Y69: Full | AA69: File | AC69: 판매실적(계획용) | AD69: SD | AE69: SDI4018 CP-40.재고(계획용) | AF69: DN, GI 상태 고려한 기준 변경 | AG69: 변경(상) | AH69: 5 | AI69: D | AJ69: Daily | AK69: TBD
A70: 삭제 | B70: =+B69+1 -> 34 | C70: SAP | D70: TBD | F70: INBOUND | G70: CP-06 | H70: 플랜트 저장위치 마스터 | I70: SP | K70: 삭제 | P70: 20251202삭제 | Q70: 신규추가_2025.10.20 | V70: SP | W70: SAP | X70: 신규 | Y70: Delta | AA70: API | AC70: BIM Inbound 추가 | AD70: PP | AE70: 신규 -SDI4013 CP-06.PG별 영업 저장위치 매핑 마스터 | AF70: PG BIM에서 관리하기 위해 플랜트/저장위치 마스터 필요 | AG70: 신규 | AH70: 5 | AI70: W | AJ70: Daily | AK70: TBD
A71: 삭제 | B71: =+B34+1 -> 33 | C71: BW | D71: TBD | F71: INBOUND | G71: ?? | H71: GPS 목표채널 기준정보 | I71: DP | K71: 삭제 | P71: 20251202삭제 | Q71: 신규추가_2025.10.20 | V71: DP | W71: BW | X71: 신규 | Y71: Delta | AA71: API | AC71: 그룹거래처 채널- GPS 목표채널 Mapping 정보 BW 에서 신규 I/F 필요 | AD71: BW | AE71: 신규 | AG71: 신규 | AH71: 5 | AI71: W | AJ71: 15Min | AK71: TBD
A72: 삭제 | B72: =+B44+1 -> 43 | C72: BW | D72: TBD | F72: INBOUND | G72: DP-43-3 | H72: DP-43-3. 거래처정보추가_BW | I72: 삭제 | K72: 삭제 | L72: Y | P72: 20251202삭제 | Q72: 신규추가_2025.10.20 ,삭제 11/14 | V72: 공통 | W72: BW | X72: 신규 | AD72: BW | AE72: 신규
A73: 삭제 | B73: =+B72+1 -> 44 | C73: BW | D73: TBD | F73: INBOUND | G73: DP-43-4 | H73: DP-43-4. 거래처정보추가_BW | I73: 삭제 | K73: 삭제 | L73: Y | P73: 20251202삭제 | Q73: 신규추가_2025.10.20, 삭제 11/14 | V73: 공통 | W73: BW | X73: 신규 | AD73: BW | AE73: 신규
A74: 삭제 | B74: =+B73+1 -> 45 | C74: BW | D74: TBD | F74: INBOUND | G74: DP-43-5 | H74: DP-43-5. 거래처정보추가_BW | I74: 삭제 | K74: 삭제 | L74: Y | P74: 20251202삭제 | Q74: 신규추가_2025.10.20, 삭제 11/14 | V74: 공통 | W74: BW | X74: 신규 | AD74: BW | AE74: 신규
A75: 삭제 | B75: =+B48+1 -> 47 | C75: SAP | D75: TBD | F75: INBOUND | G75: DP-45 | H75: DP-45. 판매실적_SKU | I75: 공통 | K75: 삭제 | P75: 20251202삭제 | Q75: 신규추가_2025.11.06 판매실적 거래처/SKU만 사용하고 이 건은 삭제 협의됨. 25/11/12
A76: 삭제 | B76: =+B37+1 -> 36 | C76: CDP | D76: TBD | F76: INBOUND | G76: DP-50-1 | H76: 유통사 오더 수량 | I76: DP | K76: 신규 | P76: 20251202삭제 | Q76: 신규추가_2025.10.20=> 취소 업로드 기능 개발취소됨(손혜원님 확인) | V76: DP | W76: CDP | X76: 신규 | AC76: 유통사 오더 수량(발수) | AD76: CDP | AE76: 신규 | AG76: 신규 | AH76: 5
A77: 삭제 | B77: =+B53+1 -> 52 | C77: SAP | D77: TBD | F77: INBOUND | G77: DP-56 | H77: DP-56. 수출포장모듈 | I77: SP | K77: 신규 | L77: Y | P77: 20251202삭제 | Q77: 신규추가_2025.11.06 자재대체단위 항목으로 대체됨 SAP ZPP02230에서 데이터 확인함(11/26일) STG I/F된 데이터확인필요
D80: BII0246 | E80: BII0246

Sheet 개요
B2: I/F 연관시스템 | C2: 시스템 관리팀 | D2: 시스템 담당자
B3: SAP
B4: NPD
B5: AP-ON
B6: BW
B7: 구매포털
B8: IAM
B9: MES
B10: CDP
B12: Inbound Interface Data 처리 Logic
B13: 1. Purge Old i/f data(인터페이스 항목 별로 보존기간이 지난 data이고 i/f data 상태가 처리 또는 에러상태)
B14: 2. Backup (신규 인터페이스 데이터를 일자별로 백업테이블로 저장)
B15: 3. 신규 i/f Group id 채번
... B141: CP-132.판매계획 프로모션 정보

Sheet Inbound
B2: No | C2: Interface ID | D2: In/Out | E2: 항목 | F2: Aplan 구분 | G2: Source System | H2: 작업유형 | I2: Delta/Full Data | J2: API/File | K2: 비고 | L2: Batch Cycle | M2: Batch Cycle Detail | N2: Source/Target Table Name
B3: 1 | C3: TBD | D3: IN | E3: 조직도 | F3: 공통 | G3: SAP | H3: 유지 | I3: Delta | J3: API | L3: W | M3: Random | N3: ZSD_SEND_ORG_01
B4: 2 | C4: TBD | D4: IN | E4: 자재마스터(영업조직:CP) | F4: 공통 | G4: SAP | H4: 유지 | I4: Delta | J4: API | K4: 영업조직/Item 별 속성정보 | L4: W,D | M4: 10Min | N4: ZSD_SEND_MATERIAL_01
B5: 3 | C5: TBD | D5: IN | E5: 자재 마스터(플랜트:SP) | F5: 공통 | G5: SAP | H5: 유지 | I5: Delta | J5: API | L5: W,D | M5: 15Min | N5: ZPP_IF_MAT_SEND_SP
B6: 4 | C6: TBD | D6: IN | E6: 자재 단가 | F6: 공통 | G6: SAP | H6: 유지 | I6: Delta | J6: API | K6: 판가 정보 | L6: W,D | M6: 10Min | N6: ZSD_SEND_CHANNEL_PRICE
B7: 5 | C7: TBD | D7: IN | E7: NPD 자재 목록 | F7: 공통 | G7: NPD | H7: 유지 | I7: Full | J7: API | K7: 현행화 주기 나 대상 검토 필요, 현재 업데이트가 되고 있지 않음 | L7: W,D | M7: Daily | N7: ZPL_IF_DEVHEAD_SINGLE
B8: 6 | C8: TBD | D8: IN | E8: 제품 허가 정보 | F8: 공통 | G8: SAP | H8: 유지 | I8: Full | J8: API | K8: BOD 및 SKU IN/OUT 에서 사용함 | L8: W,D | M8: Daily | N8: ZSD_SEND_CONFIRM_MAT_O9
B9: 7 | C9: TBD | D9: IN | E9: 단종 품의 완료 상태 | F9: 공통 | G9: AP-ON | H9: 신규 | I9: Real Time | J9: API | K9: AP-ON I/F (압축 품의 정보 전송 필요 BI -> AP-ON) (변경BI 압축 품의 진행 여부 확인 필요) | L9: 15Min | M9: Random | N9: TBD
B10: 8 | C10: TBD | D10: IN | E10: SKU 현황 | F10: 공통 | G10: BW | H10: 유지 | I10: Full | J10: File | L10: W,D | M10: Daily | N10: ZBI_SEND_FILE_TO_O9
B11: 9 | C11: TBD | D11: IN | E11: SKU In 일정 | F11: 공통 | G11: NPD | H11: 유지 | I11: Full | J11: API | L11: W,D | M11: Daily | N11: ZPL_IF_MT_SINGLE
B12: 10 | C12: TBD | D12: IN | E12: UOM Conversion Rule | F12: 공통 | G12: SAP | H12: 유지 | I12: Full
B13: 11 | C13: TBD | D13: IN | E13: 자재마스터 원가정보 | F13: 공통 | G13: SAP | H13: 유지 | I13: Delta | J13: API | K13: 해외 정보 확인 필요 | L13: D | M13: Daily | N13: ZPP_IF_STD_PRICE_SEND_SP
B14: 12 | C14: TBD | D14: IN | E14: 재고 | F14: 공통 | G14: BW | H14: 유지 | I14: Full | J14: File | L14: D | M14: Daily | N14: ZBI_SEND_FILE_TO_O9
B15: 13 | C15: TBD | D15: IN | E15: Lot ID별 재고정보 | F15: 공통 | G15: TBD | H15: 신규 | I15: Full | J15: File | K15: 재고(계획용) | L15: D | M15: Daily | N15: TBD
B16: 14 | C16: TBD | D16: IN | E16: 플랜트 저장위치 매핑 마스터 | F16: SP | G16: SAP | H16: 신규 | I16: Delta | J16: API | K16: BIM Inbound 삭제 , BIM Outbound 추가 | L16: W | M16: Daily | N16: TBD
B17: 15 | C17: TBD | D17: IN | E17: 거래처마스터 | F17: DP | G17: SAP | H17: 유지 | I17: Delta | J17: API | L17: W | M17: 15Min | N17: ZSD_SEND_CUSTOMER_01
B18: 16 | C18: TBD | D18: IN | E18: 채널- GPS 목표채널 Mapping 정보 | F18: DP | G18: BW | H18: 신규 | I18: Delta | J18: API | K18: 그룹거래처 채널- GPS 목표채널 Mapping 정보 BW 에서 신규 I/F 필요 | L18: W | M18: 15Min | N18: TBD
B19: 17 | C19: TBD | D19: IN | E19: 주문 실적/결품 수량 | F19: DP | G19: BW | H19: 수정 | I19: Full | J19: File | K19: Layout 변경(PG → Sold-To-Party 로 변경 | L19: W,D | M19: Daily | N19: ZBI_SEND_FILE_TO_O9
B20: 18 | C20: TBD | D20: IN | E20: 판매 실적 | F20: DP | G20: BW | H20: 수정 | I20: Full | J20: File | K20: Layout 변경(PG → Sold-To-Party 로 변경 | L20: W,D | M20: Daily | N20: ZBI_SEND_FILE_TO_O9
B21: 19 | C21: TBD | D21: IN | E21: SKU 목표 | F21: DP | G21: BW | H21: 유지 | I21: Full | J21: File | L21: W,D | M21: Daily | N21: ZBI_SEND_FILE_TO_O9
B22: 20 | C22: TBD | D22: IN | E22: 기준환율 | F22: DP | G22: BW | H22: 유지 | I22: Full | J22: File | K22: 유지(값의 정합성 확인 필요) 영업 조직별 기준환율이 I/F 되어야 함 | L22: W,D | M22: Daily | N22: ZBI_SEND_FILE_TO_O9
B23: 21 | C23: TBD | D23: IN | E23: 수출 진행 모니터링 | F23: DP | G23: SAP | H23: 유지 | I23: Full | J23: API | L23: W,D | M23: Daily | N23: ZSD_SEND_EXPORT_O9
B24: 22 | C24: TBD | D24: IN | E24: 거래처 재고 | F24: DP | G24: BW | H24: 유지 | I24: Full | J24: File | L24: W,D | M24: Daily | N24: ZBI_SEND_FILE_TO_O9
B25: 23 | C25: TBD | D25: IN | E25: 기타 수요(잡출) | F25: DP | G25: BW | H25: 수정 | I25: Full | J25: File | K25: Layout 변경(PG → Sold-To-Party 로 변경 | L25: Weekly,Daily | M25: Daily | N25: ZBI_SEND_FILE_TO_O9
B26: 24 | C26: TBD | D26: IN | E26: BOM | F26: SP | G26: SAP | H26: 유지 | I26: Delta | J26: API | L26: D | M26: Daily | N26: ZPP_IF_BOM_SEND_SP
B27: 25 | C27: TBD | D27: IN | E27: BOM On-demand | F27: SP | G27: SAP | H27: 유지 | I27: - | J27: API | L27: 15Min | M27: On-Demand | N27: ZPP_IF_SP_GET_BOM
B28: 26 | C28: TBD | D28: IN | E28: 작업장 마스터 | F28: SP | G28: SAP | H28: 유지 | I28: Delta | J28: API | K28: (작업장 기준 Grouping 해서 Resource 로 정의 | L28: W | M28: Random | N28: ZPP_IF_WORKCENTER_SEND_SP
B29: 27 | C29: TBD | D29: IN | E29: ROS | F29: SP | G29: SAP | H29: 신규 | I29: Full | J29: API | K29: 해외사업장 확장으로 인해서 원천을 SAP 로 변경, MES 한국 Plant만 존재함 | L29: 15Min | M29: 목(Thu)/토(Sat) | N29: MWRKTI_ROS_PACK_PRFR_SND
B30: 28 | C30: TBD | D30: IN | E30: ROS On-demand | F30: SP | G30: SAP | H30: 신규 | I30: - | J30: API | K30: 해외사업장 확장으로 인해서 원천을 SAP 로 변경, MES 한국 Plant만 존재함 | L30: - | M30: On-Demand | N30: MWRKTI_ROS_PACK_PRFR_SND
B31: 29 | C31: TBD | D31: IN | E31: 생산 오더 | F31: SP | G31: SAP | H31: 유지 | I31: Delta | J31: API | K31: 국내 포함 전체(해외)Plant 반영 필요 | L31: W,D | M31: Daily | N31: ZPP_IF_PROD_ORDER_SEND_SP
B32: 30 | C32: TBD | D32: IN | E32: 생산 오더 On-demand | F32: SP | G32: SAP | H32: 유지 | I32: - | J32: API | L32: 15Min | M32: On-Demand | N32: ZPP_IF_SP_GET_PROD_ORDER
B33: 31 | C33: TBD | D33: IN | E33: 구매오더 | F33: SP | G33: SAP | H33: 유지 | I33: Delta | J33: API | K33: ODM 포함 전체 구매오더로 반영되어야 하고 확인 필요 | L33: W,D | M33: Daily | N33: ZPP_IF_PURCH_ORDER_SEND_SP
B34: 32 | C34: TBD | D34: IN | E34: 구매정보(ODM 외주 원부자재) | F34: SP | G34: SAP | H34: 유지 | I34: Delta | J34: API | K34: ODM Network 구성 및 포장재 구매처 정의 (Category 컬럼-> 구매 또는 외주가공 정의 가능) | L34: W,D | M34: Daily | N34: ZPP_IF_INFOREC_SEND_SP
B35: 33 | C35: TBD | D35: IN | E35: 협력사 마스터 | F35: SP | G35: SAP | H35: 유지 | I35: Delta | J35: API | L35: W | M35: Daily | N35: ZPP_IF_VENDOR_SEND_SP
B36: 34 | C36: TBD | D36: IN | E36: 가용화 입고 실적 | F36: SP | G36: SAP | H36: 유지 | I36: Delta | J36: API | K36: 엔진 Input은 아니나 활용 측면에서 검토 필요 | L36: 2/Day | M36: 2/day( 11AM , 03PM) | N36: ZPP_IF_AVAIL_STOCK_SEND_SP
B37: 35 | C37: TBD | D37: IN | E37: 협력사 원부자재 재고 | F37: SP | G37: 구매포털 | H37: 유지 | I37: Full | J37: API | L37: W,D | M37: Daily | N37: -
B38: 36 | C38: TBD | D38: IN | E38: SOP 잔량 정보 | F38: SP | G38: SAP | H38: 유지 | I38: Full | J38: API | K38: 선적잔량 | L38: W,D | M38: Sunday | N38: ZSC_PIR_O9_SAP_002
B39: 37 | C39: TBD | D39: IN | E39: 반제품 포장재 MD04 재고 | F39: SP | G39: SAP | H39: 유지 | I39: Full | J39: API | K39: 반제품 재고 수량 + QA 수량 | L39: 2/Day | M39: Daily | N39: ZPP_IF_MD04STOCK_SEND_SP
B40: 38 | C40: TBD | D40: IN | E40: Role 권한 승인 정보 | F40: System | G40: IAM | H40: 유지 | I40: - | J40: API | L40: 2/Day | M40: 11:30:00 AM / 04:30 PM | N40: EX_IF_ROLE
B41: 39 | C41: TBD | D41: IN | E41: 계정 승인 정보 | F41: System | G41: IAM | H41: 유지 | I41: Delta | J41: API | L41: 2/Day | M41: 11:30:00 AM / 04:30 PM | N41: EX_IF_RES_USER
B42: 40 | C42: TBD | D42: IN | E42: CP 코드 마스터 | H42: 신규
C46: 유지 | D46: 30
C47: 수정 | D47: 3
C48: 신규 | D48: 7

Sheet 조직도
A1: Top
B2: 매핑정의서 - 조직도 | J2: Source System | K2: SAP | O2: 문서작성일 | P2: 2025.09.25
J3: Target System | K3: APLAN | O3: 버전 | P3: 0.1
B4: 매핑정의
B5: Source Table : ? | I5: Target Table : ALIFCI_OGCH_MSTR | R5: Set Value | S5: 변환규칙 | Z5: CDP 자재 마스터 테이블 명세서 (D_PRD_MSTR)
B6: RFC | C6: ZSD_SEND_ORG_BM_01 | I6: Web SVC | J6: PreProd : https://myamorepacificpreprod.o9solutions.com/ Prod : https://myamorepacific.o9solutions.com/
B7: SEQ | C7: Field | D7: PK | E7: Type | F7: Size | G7: Desc | H7: Desc(ENG) | I7: SEQ | J7: Field | K7: PK | L7: Type | M7: Size | N7: Desc | O7: Desc(ENG) | P7: Req No | Q7: Res No | Z7: 컬럼명 | AA7: 데이터타입 | AB7: 한글명 | AC7: 영문명
B8: 1 | C8: I_LEGACY | E8: CHAR | F8: 5 | G8: LEGACY SYSTEM 명 | H8: Legacy System Name | I8: 1 | Z8: PRD_CD | AA8: VARCHAR(12) | AB8: 상품코드 | AC8: Product Code.
B9: 2 | C9: BUKRS | D9: Y | E9: CHAR | F9: 4 | G9: 회사코드 | H9: Company code | I9: 2 | J9: Company | L9: NVARCHAR2 | M9: 1000 | N9: 회사코드 | O9: Company code | Z9: PRD_NM | AA9: VARCHAR(100) | AB9: 상품명 | AC9: Product Name.
B10: 3 | C10: VKORG | D10: Y | E10: CHAR | F10: 4 | G10: 영업조직 | H10: Sales organization | I10: 3 | J10: SalesOrg | L10: NVARCHAR2 | M10: 1000 | N10: 영업조직 | O10: Sales organization | Z10: PRD_ENGL_NM | AA10: VARCHAR(200) | AB10: 상품영어명 | AC10: Product English Name.
B11: 4 | C11: SUBSC | D11: Y | E11: CHAR | F11: 4 | G11: 하위영업경로 | H11: Sub -business path | I11: 4 | J11: Channel | L11: NVARCHAR2 | M11: 1000 | N11: 하위영업경로 | O11: Sub -business path | Z11: ENGL_PRD_NM | AA11: VARCHAR(100) | AB11: 영어상품명(비표준) | AC11: English Product Name (Non-Standard).
B12: 5 | C12: LAND1 | E12: CHAR | F12: 3 | G12: 국가 | H12: nation | I12: 5 | J12: Country | L12: NVARCHAR2 | M12: 1000 | N12: 국가 | O12: nation | Z12: BRND_CD | AA12: VARCHAR(5) | AB12: 브랜드코드 | AC12: Brand Code.
B13: 6 | C13: BUSUN | D13: Y | E13: CHAR | F13: 4 | G13: BU | H13: BU | I13: 6 | J13: BU | L13: NVARCHAR2 | M13: 1000 | N13: BU(사업부) | O13: BU | Z13: BRND_DTL_CD | AA13: VARCHAR(6) | AB13: 브랜드상세코드 | AC13: Brand Detail Code.
B14: 7 | C14: ZMODE | E14: CHAR | F14: 1 | G14: 'I' (Insert) , 'U'(Update), 'D'(Delete) | H14: 'I' (INSERT), 'U' (update), 'D' (Delete) | I14: 7 | J14: CUD | L14: NVARCHAR2 | M14: 1000 | N14: 'I' (Insert) , 'U'(Update), 'D'(Delete) | O14: 'I' (INSERT), 'U' (update), 'D' (Delete) | Z14: RPRS_PRD_CD | AA14: VARCHAR(12) | AB14: 대표상품코드 | AC14: Representative Product Code.
B15: 8 | C15: TFLG | E15: CHAR | F15: 1 | G15: 이관 Flag | H15: Transfer flag | I15: 8 | J15: TransFlag | L15: NVARCHAR2 | M15: 1000 | N15: 이관 Flag | O15: Transfer flag | Z15: RPRS_PRD_NM | AA15: VARCHAR(100) | AB15: 대표상품명 | AC15: Product Name.
B16: 9 | C16: .INCLUDE | E16: STRU | F16: 0 | G16: Cr/Ch log | H16: Cr/ch log | I16: 9 | Z16: RPRS_PRD_ENGL_NM | AA16: VARCHAR(100) | AB16: 대표상품영어명 | AC16: Representative Product English Name.
B17: 10 | C17: ERDAT | E17: DATS | F17: 8 | G17: 레코드 생성일 | H17: Record creation date | I17: 10 | J17: IF_DATE | L17: DATE | N17: 인터페이스 일자 | O17: Interface date | Z17: RPLC_PRD_CD | AA17: VARCHAR(12) | AB17: 대체상품코드 | AC17: Alternative Product Code.
B18: 11 | C18: ERZET | E18: TIMS | F18: 6 | G18: 입력 시간 | H18: Input time | I18: 11 | J18: IF_STATUS | L18: VARCHAR2 | M18: 30 | N18: 인터페이스 처리 상태 | O18: Interface Status | Z18: PRD_MKT_CAT_CD | AA18: VARCHAR(2) | AB18: 상품마케팅분류코드 | AC18: Product Marketing Classification Code.
B19: 12 | C19: ERNAM | E19: CHAR | F19: 12 | G19: 오브젝트 생성자 이름 | H19: Object constructor name | I19: 12 | J19: IF_PROCESS_DATE | L19: DATE | N19: 인터페이스 처리 일자 | O19: Interface Process date | Z19: SET_PRD_YN | AA19: VARCHAR(1) | AB19: 세트상품여부 | AC19: Set product or not.
B20: 13 | C20: AEDAT | E20: DATS | F20: 8 | G20: 변경일 | H20: Change date | I20: 13 | J20: IF_GRP_ID | L20: NUMBER | N20: 인터페이스 그룹 id(처리 시) | O20: Interface group id | Z20: SET_DSMN_YN | AA20: VARCHAR(1) | AB20: 세트해체여부 | AC20: Set disassembly.
B21: 14 | C21: AEZET | E21: TIMS | F21: 6 | G21: 최종변경시간 | H21: Final change time | I21: 14 | Z21: CNSM_UTPR_AMT | AA21: NUMBER(20,3) | AB21: 소비자단가금액 | AC21: Consumer Unit Price.
B22: 15 | C22: AENAM | E22: CHAR | F22: 12 | G22: 오브젝트 변경자 이름 | H22: Object Changer Name | I22: 15 | Z22: PRD_CPT | AA22: NUMBER(38,0) | AB22: 상품용량 | AC22: Product Capacity.
B23: 16 | I23: 16 | Z23: PRD_CPT_UNIT_CD | AA23: VARCHAR(3) | AB23: 상품용량단위코드 | AC23: Product Unit Code.
B24: 17 | I24: 17 | Z24: PRD_USE_CD | AA24: VARCHAR(3) | AB24: 상품용도코드 | AC24: Product Use Code.
B25: 18 | I25: 18 | Z25: PRD_CAT_CD | AA25: VARCHAR(10) | AB25: 상품분류코드 | AC25: Product Classification Code.
B26: 19 | I26: 19 | Z26: MAIN_FUNC_CD | AA26: VARCHAR(4) | AB26: 주요기능코드 | AC26: Main Function Code.
B27: 20 | I27: 20 | Z27: USER_TP_CD | AA27: VARCHAR(1) | AB27: 사용자유형코드 | AC27: User Type Code.
B28: 21 | I28: 21 | Z28: FRSH_CSMT_YN | AA28: VARCHAR(1) | AB28: 신선화장품여부 | AC28: Fresh Cosmetics.
B29: 22 | I29: 22 | Z29: PRD_CL_CD | AA29: VARCHAR(2) | AB29: 상품구분코드 | AC29: Product Classification Code.
B30: 23 | I30: 23 | Z30: SLS_TP_CD | AA30: VARCHAR(3) | AB30: 영업유형코드 | AC30: Sales Type Code.
B31: 24 | I31: 24 | Z31: SAP_PRD_LN_CD | AA31: VARCHAR(4) | AB31: SAP상품라인코드 | AC31: SAP Product Line Code.
B32: 25 | I32: 25 | Z32: PRD_CLR_CD | AA32: VARCHAR(4) | AB32: 상품색상코드 | AC32: Product Color Code.
B33: 26 | I33: 26 | Z33: NEW_PRD_CL_CD | AA33: VARCHAR(3) | AB33: 신상품구분코드 | AC33: New Product Code.
B34: 27 | I34: 27 | Z34: STRO_PRD_YN | AA34: VARCHAR(1) | AB34: 강한상품여부 | AC34: Strong product or not.
... B38: 31 | I38: 31 | Z38: BRND_LN_CD | AA38: VARCHAR(4) | AB38: 브랜드라인코드 | AC38: Brand Line Code.
Z39: MFG_PLNT_CD | AA39: VARCHAR(4) | AB39: 생산플랜트코드 | AC39: Production Plant Code.
Z40: NITM_APLY_YN | AA40: VARCHAR(1) | AB40: 품목수적용여부 | AC40: Item Application.
B41: 변환규칙정의 | Z41: FST_MFG_DT | AA41: VARCHAR(10) | AB41: 최초생산일자 | AC41: Initial Production Date.
B42: 변환규칙 | D42: 내용 | Z42: LST_MFG_DT | AA42: VARCHAR(10) | AB42: 최종생산일자 | AC42: Final production date.
B43: R1 | Z43: PRD_BRCD_CD | AA43: VARCHAR(15) | AB43: 상품바코드코드 | AC43: Product barcode code.
B44: R2 | Z44: REG_APPL_CL_CD | AA44: VARCHAR(10) | AB44: 등록어플리케이션구분코드 | AC44: Registration Application Type Code.
Z45: CP_PRD_YN | AA45: VARCHAR(1) | AB45: 자사상품여부 | AC45: Is it a company product?.
B46: 기타정보 | Z46: INSD_MGNT_AMT | AA46: NUMBER(20,3) | AB46: 내부관리금액 | AC46: Internal Management Amount.
B47: 이벤트 발생조건 (DB Trigger) | Z47: WKPL_CL_CD | AA47: VARCHAR(10) | AB47: 사업장구분코드 | AC47: Business Site Classification Code.
B48: 연계데이터 추출조건 | Z48: ASRC_PRD_MKT_CAT_CD | AA48: VARCHAR(2) | AB48: 소스상품마케팅분류코드 | AC48: Source Product Marketing Classification Code.
B49: 데이터 반영방법 | Z49: ASRC_PRD_CAT_CD | AA49: VARCHAR(10) | AB49: 소스상품분류코드 | AC49: Source Product Classification Code.
B50: 기타 | Z50: PRD_TP_CD | AA50: VARCHAR(4) | AB50: 상품유형코드 | AC50: Product Type Code.

Sheet 자재마스터(영업조직)
A1: Top
B2: 매핑정의서 - 자재마스터(Sales ORG.) Item Master CP | J2: Source System | K2: SAP | O2: 문서작성일 | P2: 2025.09.25
J3: Target System | K3: APLAN | O3: 버전 | P3: 0.1
B4: 매핑정의
B5: Source Table : ? | I5: Target Table : ALIFCI_MTRL_MSTR_CP | R5: Set Value | S5: 변환 규칙
B6: RFC | C6: ZSD_SEND_MATERIAL_01 | I6: Web SVC | J6: PreProd : https://myamorepacificpreprod.o9solutions.com/ Prod : https://myamorepacific.o9solutions.com/
B7: SEQ | C7: Field | D7: PK | E7: Type | F7: Size | G7: Desc | H7: Desc(ENG) | I7: SEQ | J7: Field | K7: PK | L7: Type | M7: Size | N7: Desc | O7: Desc(ENG) | P7: Req No | Q7: Res No
B8: 1 | C8: MATNR | D8: Y | E8: CHAR | F8: 18 | G8: 자재코드 | H8: Material code | I8: 1 | J8: Item | K8: Y | L8: nvarchar2 | M8: 1000 | N8: 자재코드 | O8: Material code
B9: 2 | C9: VKORG | D9: Y | E9: CHAR | F9: 4 | G9: 판매조직 | H9: Sales organization | I9: 2 | J9: SalesOrg | K9: Y | L9: nvarchar2 | M9: 1000 | N9: 판매조직 | O9: Sales organization
B10: 3 | C10: MAKTX_KO | E10: CHAR | F10: 40 | G10: 자재내역(KO) | H10: Material details (KO) | I10: 3 | J10: ItemDescKR | L10: nvarchar2 | M10: 1000 | N10: 자재내역(KO) | O10: Material details (KO) | T10: 자재공통칼럼
B11: 4 | C11: MTART | E11: CHAR | F11: 4 | G11: 자재유형 | H11: Material | I11: 4 | J11: ItemType | L11: nvarchar2 | M11: 1000 | N11: 자재유형 | O11: Material | T11: 자재공통칼럼
B12: 5 | C12: BISMT | E12: CHAR | F12: 18 | G12: 이전상품코드 | H12: Previous product code | I12: 5 | J12: OldItem | L12: nvarchar2 | M12: 1000 | N12: 이전상품코드 | O12: Previous product code
B13: 6 | C13: LABOR | E13: CHAR | F13: 3 | G13: 상품개발담당자 | H13: Product operation manager | I13: 6 | J13: ProdOpPerson | L13: nvarchar2 | M13: 1000 | N13: 상품개발담당자 | O13: Product operation manager | T13: 자재공통칼럼
B14: 7 | C14: BRAND | E14: CHAR | F14: 9 | G14: 브랜드코드 | H14: Brand code | I14: 7 | J14: Brand | L14: nvarchar2 | M14: 1000 | N14: 브랜드코드 | O14: Brand code | T14: 자재공통칼럼
B15: 8 | C15: BCTXT_KO | E15: CHAR | F15: 20 | G15: 브랜드명(KO) | H15: Brand name (KO) | I15: 8 | J15: BrandDescKR | L15: nvarchar2 | M15: 1000 | N15: 브랜드명(KO) | O15: Brand name (KO) | T15: 자재공통칼럼
B16: 9 | C16: MEINS | E16: CHAR | F16: 3 | G16: 기본단위 | H16: Basic unit | I16: 9 | J16: UOM | L16: nvarchar2 | M16: 1000 | N16: 기본단위 | O16: Basic unit | T16: 자재공통칼럼
B17: 10 | C17: DISPO | E17: CHAR | F17: 3 | G17: MRP관리자 | H17: MRP manager | I17: 10 | J17: MRPPerson | L17: nvarchar2 | M17: 1000 | N17: MRP관리자 | O17: MRP manager
B18: 11 | C18: MVGR1 | E18: CHAR | F18: 3 | G18: 제품용도 | H18: Product use | I18: 11 | J18: MVGR1 | L18: nvarchar2 | M18: 1000 | N18: 제품용도 | O18: Product use
B19: 12 | C19: MVGR2 | E19: CHAR | F19: 3 | G19: 제품등급 | H19: Product grade | I19: 12 | J19: MVGR2 | L19: nvarchar2 | M19: 1000 | N19: 제품등급 | O19: Product grade
B20: 13 | C20: MVGR4 | E20: CHAR | F20: 3 | G20: 자재클래스1 | H20: Material Class 1 | I20: 13 | J20: ItemClass1 | L20: nvarchar2 | M20: 1000 | N20: 자재클래스1 | O20: Material Class 1 | T20: 자재공통칼럼
B21: 14 | C21: MVGR5 | E21: CHAR | F21: 3 | G21: 자재클래스2 | H21: Material Class 2 | I21: 14 | J21: ItemClass2 | L21: nvarchar2 | M21: 1000 | N21: 자재클래스2 | O21: Material Class 2 | T21: 자재공통칼럼
B22: 15 | C22: PRODH | E22: CHAR | F22: 18 | G22: 제품계층구조 | H22: Product hierarchy | I22: 15 | J22: ProdHrcy | L22: nvarchar2 | M22: 1000 | N22: 제품계층구조 | O22: Product hierarchy | T22: 자재공통칼럼
B23: 16 | C23: MATNR2 | E23: CHAR | F23: 18 | G23: 대체자재 | H23: Alternative materials | I23: 16 | J23: ReplaceItem | L23: nvarchar2 | M23: 1000 | N23: 대체자재 | O23: Alternative materials
B24: 17 | C24: ADNEW | E24: CHAR | F24: 3 | G24: NEW/AD | H24: New/AD | I24: 17 | J24: ADNEW | L24: nvarchar2 | M24: 1000 | N24: NEW/AD | O24: New/AD
B25: 18 | C25: SETID | E25: CHAR | F25: 3 | G25: SET구분 | H25: SET classification | I25: 18 | J25: SETID | L25: nvarchar2 | M25: 1000 | N25: SET구분 | O25: SET classification
B26: 19 | C26: MATOP | E26: CHAR | F26: 3 | G26: 상품운영담당 | H26: Product operation manager | I26: 19 | J26: ProdOp | L26: nvarchar2 | M26: 1000 | N26: 상품운영담당 | O26: Product operation manager
B27: 20 | C27: SETDI | E27: CHAR | F27: 1 | G27: 세트해체여부 | H27: Whether to dismantle the set | I27: 20 | J27: SETDI | L27: nvarchar2 | M27: 1000 | N27: 세트해체여부 | O27: Whether to dismantle the set
B28: 21 | C28: MANFT | E28: CHAR | F28: 4 | G28: 제조장 | H28: Manufacture | I28: 21 | J28: Plant | L28: nvarchar2 | M28: 1000 | N28: 제조장 | O28: Manufacture
B29: 22 | C29: LPRDD | E29: CHAR | F29: 8 | G29: 최종생산일 | H29: Final production date | I29: 22 | J29: LastProdDate | L29: nvarchar2 | M29: 1000 | N29: 최종생산일 | O29: Final production date
B30: 23 | C30: FPRDD | E30: CHAR | F30: 8 | G30: 최초생산일 | H30: Initial production date | I30: 23 | J30: FirstProdDate | L30: nvarchar2 | M30: 1000 | N30: 최초생산일 | O30: Initial production date
B31: 24 | C31: MAKTX_EN | E31: CHAR | F31: 40 | G31: 자재내역(EN) | H31: Material details (EN) | I31: 24 | J31: ItemDescEN | L31: nvarchar2 | M31: 1000 | N31: 자재내역(EN) | O31: Material details (EN) | T31: 자재공통칼럼
B32: 25 | C32: MAKTX_ZH | E32: CHAR | F32: 40 | G32: 자재내역(ZH) | H32: Material details (ZH) | I32: 25 | J32: ItemDescZH | L32: nvarchar2 | M32: 1000 | N32: 자재내역(ZH) | O32: Material details (ZH) | T32: 자재공통칼럼
B33: 26 | C33: BCTXT_EN | E33: CHAR | F33: 20 | G33: 브랜드명(EN) | H33: Brand name (EN) | I33: 26 | J33: BrandDescEN | L33: nvarchar2 | M33: 1000 | N33: 브랜드명(EN) | O33: Brand name (EN) | T33: 자재공통칼럼
B34: 27 | C34: BCTXT_ZH | E34: CHAR | F34: 20 | G34: 브랜드명(ZH) | H34: Brand name (ZH) | I34: 27 | J34: BrandDescZH | L34: nvarchar2 | M34: 1000 | N34: 브랜드명(ZH) | O34: Brand name (ZH) | T34: 자재공통칼럼
B35: 28 | C35: MANFT2 | E35: CHAR | F35: 10 | G35: 제조장2 | H35: Manufacturer 2 | I35: 28 | J35: SCMU | L35: nvarchar2 | M35: 1000 | N35: 제조장2 | O35: Manufacturer 2
B36: 29 | C36: SETYN | E36: CHAR | F36: 1 | G36: SET 여부(Y/N) | H36: Whether set (Y/N) | I36: 29 | J36: SetYN | L36: nvarchar2 | M36: 1000 | N36: SET 여부(Y/N) | O36: Whether set (Y/N) | T36: 자재공통칼럼
B37: 30 | C37: MATKL | E37: CHAR | F37: 9 | G37: 자재그룹 | H37: Material group | I37: 30 | J37: ItemGroup | L37: nvarchar2 | M37: 1000 | N37: 자재그룹 | O37: Material group | T37: 자재공통칼럼
B38: 31 | C38: ZZBRANG | E38: CHAR | F38: 10 | G38: 브랜드그룹 | H38: Brand group | I38: 31 | J38: BrandGroup | L38: nvarchar2 | M38: 1000 | N38: 브랜드그룹 | O38: Brand group | T38: 자재공통칼럼
B39: 32 | C39: ZZRPPRD | E39: CHAR | G39: 대표상품 | I39: 32 | J39: Head_PRDT | L39: nvarchar2 | M39: 1000 | N39: 대표상품 | T39: 신규추가.25.09.25 | U39: 자재공통칼럼
B40: 33 | C40: ZZSCGRP | E40: CHAR | G40: 소싱그룹 | I40: 33 | J40: SRC_GRP | L40: nvarchar2 | M40: 1000 | N40: 소싱그룹 | T40: 신규추가.25.09.25
B41: 34 | C41: ZZBLINE | E41: CHAR | G41: 제형명 | I41: 34 | J41: PRDT_FORM_NM | L41: nvarchar2 | M41: 1000 | N41: 제형명 | T41: 신규추가.25.09.25
B42: 35 | C42: ZZRPFUT | E42: CHAR | G42: 주기능 | I42: 35 | J42: MAINFUNC | L42: nvarchar2 | M42: 1000 | N42: 주기능 | T42: 신규추가.25.09.25 | U42: 자재공통칼럼
B43: 36 | C43: ZZADFU1 | E43: CHAR | G43: 부기능1 | I43: 36 | J43: SUBFUNC1 | L43: nvarchar2 | M43: 1000 | N43: 부기능1 | T43: 신규추가.25.09.25 | U43: 자재공통칼럼
B44: 37 | C44: ZZADFU2 | E44: CHAR | G44: 부기능2 | I44: 37 | J44: SUBFUNC2 | L44: nvarchar2 | M44: 1000 | N44: 부기능2 | T44: 신규추가.25.09.25 | U44: 자재공통칼럼
B45: 38 | C45: ZZADNEW | E45: CHAR | G45: 신제품 분류 | I45: 38 | J45: NEW_PRDT_CD | L45: nvarchar2 | M45: 1000 | N45: 신제품분류 | T45: 신규추가.25.09.25
B46: 39 | C46: MHDRZ | E46: CHAR | G46: 물류보관기간 (제조일로부터) | I46: 39 | J46: DIST_KEEP_DAYS | L46: nvarchar2 | M46: 1000 | N46: 물류보관기간 (제조일로부터) | T46: 신규추가.25.09.25
B47: 40 | C47: MHDHB | E47: CHAR | G47: 사용기한(제조일로부터) | I47: 40 | J47: SHELFLIFE_DAYS | L47: nvarchar2 | M47: 1000 | N47: 사용기한(제조일로부터) | T47: 신규추가.25.09.25
B48: 41 | C48: ZZFSDAT | E48: CHAR | G48: 최초판매실적발생일 | I48: 41 | J48: FST_SALE_DATE | L48: nvarchar2 | M48: 1000 | N48: 최초판매실적발생일 | T48: 신규추가.25.09.25
B49: 42 | C49: ZZLSDAT | E49: CHAR | G49: 최종판매실적발생일 | I49: 42 | J49: LST_SALE_DATE | L49: nvarchar2 | M49: 1000 | N49: 최종판매실적발생일 | T49: 신규추가.25.09.25
B50: 43 | C50: MVGR3 | E50: CHAR | G50: 제품허용그룹 | I50: 43 | J50: PRDT_PERMIT_GRP | L50: nvarchar2 | M50: 1000 | N50: 제품허용그룹 | T50: 신규추가.25.09.25
B51: =+B50+1 -> 44 | C51: ZZRLINE | E51: CHAR | G51: 제품별 라인명 | I51: 44 | J51: PRDT_LINE_NM | L51: nvarchar2 | M51: 1000 | N51: 제품별 라인명 | T51: 신규추가.25.09.25 | U51: 자재공통칼럼
B52: =+B51+1 -> 45 | C52: UMREZ_BOX | E52: CHAR | G52: 박스단위 포장모듈 | H52: Quantity per Box | I52: =+I51+1 -> 45 | J52: QTY_PER_BOX | L52: nvarchar2 | M52: 1000 | N52: 박스단위 포장모듈 | O52: Quantity per Box | T52: 신규추가.25.10.20 | U52: 자재공통칼럼
B53: =+B52+1 -> 46 | C53: UMREZ_TA | E53: CHAR | G53: 타단위 포장모듈 | H53: Quantity per TA | I53: =+I52+1 -> 46 | J53: QTY_PER_TA | L53: nvarchar2 | M53: 1000 | N53: 타단위 포장모듈 | O53: Quantity per TA | T53: 신규추가.25.10.20 | U53: 자재공통칼럼
B54: =+B53+1 -> 47 | C54: UMREZ_PAL | E54: CHAR | G54: 팔레트단위 포장모듈 | H54: Quantity per PLT | I54: =+I53+1 -> 47 | J54: QTY_PER_PLT | L54: nvarchar2 | M54: 1000 | N54: 팔레트단위 포장모듈 | O54: Quantity per PLT | T54: 신규추가.25.10.20 | U54: 자재공통칼럼
B55: =+B54+1 -> 48 | C55: EAN11 | E55: CHAR | G55: EAN/UPC | H55: EAN/UPC | I55: =+I54+1 -> 48 | J55: EAN_UPC | L55: nvarchar2 | M55: 1000 | N55: EAN/UPC | O55: EAN/UPC | T55: 신규추가.25.10.20 | U55: 자재공통칼럼
B56: =+B55+1 -> 49 | C56: ZZCPIAP | E56: CHAR | G56: 카테고리 | I56: =+I55+1 -> 49 | J56: ITEM_CATEGORY | L56: nvarchar2 | M56: 1000 | N56: 카테고리 | T56: 신규추가.25.10.22 | U56: 자재공통칼럼
B57: =+B56+1 -> 50 | C57: MAKTX_BISMT_KO | F57: 40 | G57: 기존자재코드 내역(한국어) | I57: =+I56+1 -> 50 | J57: OLDITEM_NM | L57: nvarchar2 | M57: 1000 | N57: 기존품목명(한국어) | T57: 신규추가.25.11.17 | U57: 자재공통칼럼-BK추가
B58: =+B57+1 -> 51 | C58: MAKTX_BISMT_EN | F58: 40 | G58: 기존자재코드 내역(영어) | I58: =+I57+1 -> 51 | J58: OLDITEM_NM_EN | L58: nvarchar2 | M58: 1000 | N58: 기존품목명(영어)
B59: =+B58+1 -> 52 | C59: MAKTX_BISMT_ZH | F59: 40 | G59: 기존자재코드 내역(중국어) | I59: =+I58+1 -> 52 | J59: OLDITEM_NM_ZH | L59: nvarchar2 | M59: 1000 | N59: 기존품목명(중국어)
B60: =+B59+1 -> 53 | C60: RPTXT | F60: 40 | G60: 대표제품명 | I60: =+I59+1 -> 53 | J60: Head_PRDT_NM | L60: nvarchar2 | M60: 1000 | N60: 대표상품 | T60: 신규추가.25.12.01 | U60: 자재공통칼럼-BK추가
J62: IF_DATE | L62: DATE | N62: 인터페이스 일자 | O62: Interface date
J63: IF_STATUS | L63: VARCHAR2 | M63: 30 | N63: 인터페이스 처리 상태 | O63: Interface Status
J64: IF_PROCESS_DATE | L64: DATE | N64: 인터페이스 처리 일자 | O64: Interface Process date
J65: IF_GRP_ID | L65: NUMBER | N65: 인터페이스 그룹 id(처리 시) | O65: Interface group id
B67: 변환규칙정의
B68: 변환규칙 | D68: 49
B69: R1
B70: R2
B72: 기타정보
B73: 이벤트 발생조건 (DB Trigger)
B74: 연계데이터 추출조건
B75: 데이터 반영방법
B76: 기타 | D76: ITEM_TYPE, 제품계층구조의 코드/코드명 필요
H98: * SQL의 성능을 고려하여 STG의 자재마스터 cp,sp에도 자재명, 브랜드명 등 공통코드를 포함.

Sheet 자재마스터(플랜트)
A1: Top
B2: 매핑정의서 - 자재마스터(Plant) Item Master SP | J2: Source System | K2: SAP | O2: 문서작성일 | P2: 2025.09.25
J3: Target System | K3: APLAN | O3: 버전 | P3: 0.1
B4: 매핑정의
B5: Source Table : ? | I5: Target Table : ALIFCI_MTRL_MSTR_CP | R5: Set Value | S5: 변환 규칙 | Z5: CDP 자재 마스터 테이블 명세서 (D_PRD_MSTR)
B6: RFC | C6: ZPP_IF_MAT_SEND_BM_SP | I6: Web SVC | J6: PreProd : https://myamorepacificpreprod.o9solutions.com/ Prod : https://myamorepacific.o9solutions.com/
B7: SEQ | C7: Field | D7: PK | E7: Type | F7: Size | G7: Desc | H7: Desc(ENG) | I7: SEQ | J7: Field | K7: PK | L7: Type | M7: Size | N7: Desc | O7: Desc(ENG) | P7: Req No | Q7: Res No | Z7: 컬럼명 | AA7: 데이터타입 | AB7: 한글명 | AC7: 영문명
B8: 1 | C8: MATNR | D8: Y | E8: CHAR | F8: 18 | G8: 자재코드 | H8: Material code | I8: 1 | J8: Item | K8: Y | L8: nvarchar | M8: 1000 | N8: 자재코드 | O8: Material code | Z8: PRD_CD | AA8: VARCHAR(12) | AB8: 상품코드 | AC8: Product Code.
B9: 2 | C9: WERKS | D9: Y | E9: CHAR | F9: 4 | G9: Plant | H9: Plant | I9: 2 | J9: Plant | K9: Y | L9: nvarchar | M9: 1000 | N9: 플랜트 | O9: Plant | Z9: PRD_NM | AA9: VARCHAR(100) | AB9: 상품명 | AC9: Product Name.
B10: 3 | C10: BESKZ | E10: CHAR | F10: 1 | G10: 조달유형 | H10: Procurement | I10: 3 | J10: ProcType | L10: nvarchar | M10: 1000 | N10: 조달유형 | O10: Procurement | Z10: PRD_ENGL_NM | AA10: VARCHAR(200) | AB10: 상품영어명 | AC10: Product English Name.
B11: 4 | C11: SOBSL | E11: CHAR | F11: 2 | G11: 특별조달유형 | H11: Special procurement type | I11: 4 | J11: SpecProcType | L11: nvarchar | M11: 1000 | N11: 특별조달유형 | O11: Special procurement type | Z11: ENGL_PRD_NM | AA11: VARCHAR(100) | AB11: 영어상품명(비표준) | AC11: English Product Name (Non-Standard).
B12: 5 | C12: ODM | E12: CHAR | F12: 1 | G12: ODM/OEM flag | H12: ODM/OEM Flag | I12: 5 | J12: ODM | L12: nvarchar | M12: 1000 | N12: ODM | O12: ODM/OEM Flag | Z12: BRND_CD | AA12: VARCHAR(5) | AB12: 브랜드코드 | AC12: Brand Code.
B13: 6 | C13: PROVG | E13: CHAR | F13: 2 | G13: 주요판매경로 | H13: Main | I13: 6 | J13: ExportFlag | L13: nvarchar | M13: 1000 | N13: 수출 여부 | O13: Main | Z13: BRND_DTL_CD | AA13: VARCHAR(6) | AB13: 브랜드상세코드 | AC13: Brand Detail Code.
B14: 7 | C14: ZZMANFT | E14: CHAR | F14: 4 | G14: 소싱플랜트 | H14: Sourcing plant | I14: 7 | J14: SourcingPlant | L14: nvarchar | M14: 1000 | N14: 소싱플랜트 | O14: Sourcing plant | Z14: RPRS_PRD_CD | AA14: VARCHAR(12) | AB14: 대표상품코드 | AC14: Representative Product Code.
B15: 8 | C15: LGFSB | E15: CHAR | F15: 4 | G15: EP 저장위치 | H15: EP storage location | I15: 8 | J15: ReceivingPlant | L15: nvarchar | M15: 1000 | N15: 입고저장위치 | O15: EP storage location | Z15: RPRS_PRD_NM | AA15: VARCHAR(100) | AB15: 대표상품명 | AC15: Product Name.
B16: 9 | C16: LGPRO | E16: CHAR | F16: 4 | G16: 생산 저장위치 | H16: Production storage location | I16: 9 | J16: ProductionLocation | L16: nvarchar | M16: 1000 | N16: 생산저장위치 | O16: Production storage location | Z16: RPRS_PRD_ENGL_NM | AA16: VARCHAR(100) | AB16: 대표상품영어명 | AC16: Representative Product English Name.
B17: 10 | C17: MEINS | E17: CHAR | F17: 3 | G17: 기본단위 | H17: Basic unit | I17: 10 | J17: UOM | L17: nvarchar | M17: 1000 | N17: UOM | O17: Basic unit | T17: 자재공통칼럼 | Z17: RPLC_PRD_CD | AA17: VARCHAR(12) | AB17: 대체상품코드 | AC17: Alternative Product Code.
B18: 11 | C18: BSTMI | E18: QUAN | F18: 13.3 | G18: Minimum Lot Size | H18: Minimum lot size | I18: 11 | J18: MOQ | L18: nvarchar | M18: 1000 | N18: 최소로트크기 | O18: Minimum lot size | Z18: PRD_MKT_CAT_CD | AA18: VARCHAR(2) | AB18: 상품마케팅분류코드 | AC18: Product Marketing Classification Code.
B19: 12 | C19: EKGRP | E19: CHAR | F19: 3 | G19: Purchasing Group | H19: Purchasing Group | I19: 12 | J19: PurchacingGroup | L19: nvarchar | M19: 1000 | N19: 구매그룹 | O19: Purchasing Group | Z19: SET_PRD_YN | AA19: VARCHAR(1) | AB19: 세트상품여부 | AC19: Set product or not.
B20: 13 | C20: MTART | E20: CHAR | F20: 4 | G20: Material Type | H20: Material type | I20: 13 | J20: ItemType | L20: nvarchar | M20: 1000 | N20: Material Type | O20: Material type | T20: 자재공통칼럼 | Z20: SET_DSMN_YN | AA20: VARCHAR(1) | AB20: 세트해체여부 | AC20: Set disassembly.
B21: 14 | C21: MAKTX | E21: CHAR | F21: 40 | G21: Material Description (Short Text) | H21: Material Description (Short Text) | I21: 14 | J21: ItemDesc | L21: nvarchar | M21: 1000 | N21: Material Description (Short Text) | O21: Material Description (Short Text) | T21: 자재공통칼럼 | Z21: CNSM_UTPR_AMT | AA21: NUMBER(20,3) | AB21: 소비자단가금액 | AC21: Consumer Unit Price.
B22: 15 | C22: MAKTX EN | E22: CHAR | F22: 40 | G22: Material Description (Short Text-EN) | H22: Material Description (Short Text -en) | I22: 15 | J22: ItemDescEN | L22: nvarchar | M22: 1000 | N22: Material Description (Short Text-EN) | O22: Material Description (Short Text -en) | T22: 자재공통칼럼 | Z22: PRD_CPT | AA22: NUMBER(38,0) | AB22: 상품용량 | AC22: Product Capacity.
B23: 16 | C23: MAKTX KO | E23: CHAR | F23: 40 | G23: Material Description (Short Text-KO) | H23: Material Description (Short Text-KO) | I23: 16 | J23: ItemDescKR | L23: nvarchar | M23: 1000 | N23: Material Description (Short Text-KO) | O23: Material Description (Short Text-KO) | T23: 자재공통칼럼 | Z23: PRD_CPT_UNIT_CD | AA23: VARCHAR(3) | AB23: 상품용량단위코드 | AC23: Product Unit Code.
B24: 17 | C24: MAKTX ZH | E24: CHAR | F24: 40 | G24: Material Description (Short Text-ZH) | H24: Material Description (Short Text-ZH) | I24: 17 | J24: ItemDescZH | L24: nvarchar | M24: 1000 | N24: Material Description (Short Text-ZH) | O24: Material Description (Short Text-ZH) | T24: 자재공통칼럼 | Z24: PRD_USE_CD | AA24: VARCHAR(3) | AB24: 상품용도코드 | AC24: Product Use Code.
B25: 18 | C25: ADNEW | E25: CHAR | F25: 3 | G25: AD or New | H25: AD or New | I25: 18 | J25: ADNEW | L25: nvarchar | M25: 1000 | N25: AD or New | O25: AD or New | Z25: PRD_CAT_CD | AA25: VARCHAR(10) | AB25: 상품분류코드 | AC25: Product Classification Code.
B26: 19 | C26: SETID | E26: CHAR | F26: 3 | G26: SET Indicator | H26: Set indicator | I26: 19 | J26: SETID | L26: nvarchar | M26: 1000 | N26: SET Indicator | O26: Set indicator | Z26: MAIN_FUNC_CD | AA26: VARCHAR(4) | AB26: 주요기능코드 | AC26: Main Function Code.
B27: 20 | C27: SETYN | E27: CHAR | F27: 1 | G27: SET (Y/N) | H27: Set (Y/N) | I27: 20 | J27: SetYN | L27: nvarchar | M27: 1000 | N27: SET (Y/N) | O27: Set (Y/N) | T27: 자재공통칼럼 | Z27: USER_TP_CD | AA27: VARCHAR(1) | AB27: 사용자유형코드 | AC27: User Type Code.
B28: 21 | C28: DISPO | E28: CHAR | F28: 3 | G28: MRP Controller (Materials Planner) | H28: MRP Controller (Materials Planner) | I28: 21 | J28: MRPPerson | L28: nvarchar | M28: 1000 | N28: MRP Controller (Materials Planner) | O28: MRP Controller (Materials Planner) | Z28: FRSH_CSMT_YN | AA28: VARCHAR(1) | AB28: 신선화장품여부 | AC28: Fresh Cosmetics.
B29: 22 | C29: LABOR | E29: CHAR | F29: 3 | G29: Laboratory/design office | H29: Laboratory/Design Office | I29: 22 | J29: ProdOpPerson | L29: nvarchar | M29: 1000 | N29: Laboratory/design office | O29: Laboratory/Design Office | Z29: PRD_CL_CD | AA29: VARCHAR(2) | AB29: 상품구분코드 | AC29: Product Classification Code.
B30: 23 | C30: MATKL | E30: CHAR | F30: 9 | G30: Material Group | H30: Material Group | I30: 23 | J30: ItemGroup | L30: nvarchar | M30: 1000 | N30: Material Group | O30: Material Group | T30: 자재공통칼럼 | Z30: SLS_TP_CD | AA30: VARCHAR(3) | AB30: 영업유형코드 | AC30: Sales Type Code.
B31: 24 | C31: BRAND | E31: CHAR | F31: 10 | G31: Brand Code | H31: Brand code | I31: 24 | J31: Brand | L31: nvarchar | M31: 1000 | N31: Brand Code | O31: Brand code | T31: 자재공통칼럼 | Z31: SAP_PRD_LN_CD | AA31: VARCHAR(4) | AB31: SAP상품라인코드 | AC31: SAP Product Line Code.
B32: 25 | C32: BCTXT | E32: CHAR | F32: 40 | G32: Description | H32: Description | I32: 25 | J32: BrandDescKR | L32: nvarchar | M32: 1000 | N32: Description | O32: Description | T32: 자재공통칼럼 | Z32: PRD_CLR_CD | AA32: VARCHAR(4) | AB32: 상품색상코드 | AC32: Product Color Code.
B33: 26 | C33: MVGR1 | E33: CHAR | F33: 3 | G33: Material Usage | H33: Material usage | I33: 26 | J33: MVGR1 | L33: nvarchar | M33: 1000 | N33: Material Usage | O33: Material usage | Z33: NEW_PRD_CL_CD | AA33: VARCHAR(3) | AB33: 신상품구분코드 | AC33: New Product Code.
B34: 27 | C34: MVGR2 | E34: CHAR | F34: 3 | G34: Material Grade | H34: Material Grade | I34: 27 | J34: MVGR2 | L34: nvarchar | M34: 1000 | N34: Material Grade | O34: Material Grade | Z34: STRO_PRD_YN | AA34: VARCHAR(1) | AB34: 강한상품여부 | AC34: Strong product or not.
B35: 28 | C35: PRODH | E35: CHAR | F35: 18 | G35: Product hierarchy | H35: Product Hierarchy | I35: 28 | J35: ProdHrcy | L35: nvarchar | M35: 1000 | N35: Product hierarchy | O35: Product Hierarchy | Z35: INNO_PRD_YN | AA35: VARCHAR(1) | AB35: 혁신상품여부 | AC35: Innovative Product Status.
B36: 29 | C36: BISMT | E36: CHAR | F36: 18 | G36: Old material number | H36: Old Material Number | I36: 29 | J36: OldItem | L36: nvarchar | M36: 1000 | N36: Old material number | O36: Old Material Number | Z36: CUSH_PRD_YN | AA36: VARCHAR(1) | AB36: 쿠션상품여부 | AC36: Cushion product status.
B37: 30 | C37: DISMM | E37: CHAR | F37: 2 | G37: MRP유형 | H37: MRP type | I37: 30 | J37: MRPType | L37: nvarchar | M37: 1000 | N37: MRP유형 | O37: MRP type | Z37: PRD_GRD_CD | AA37: VARCHAR(3) | AB37: 상품등급코드 | AC37: Product Grade Code.
B38: 31 | C38: VKORG | E38: CHAR | F38: 4 | G38: 영업조직 | H38: Sales organization | I38: 31 | J38: SalesOrg | L38: nvarchar | M38: 1000 | N38: 영업조직 | O38: Sales organization | Z38: BRND_LN_CD | AA38: VARCHAR(4) | AB38: 브랜드라인코드 | AC38: Brand Line Code.
B39: 32 | C39: LVORM | E39: CHAR | F39: 1 | G39: 삭제지시자 | H39: Delete Flag | I39: 32 | J39: DeleteFlag | L39: NVARCHAR | M39: 1000 | N39: 삭제지시자 | O39: Delete Flag
B40: 33 | C40: CUD_CI | E40: CHAR | F40: 1 | G40: CUD 구분 | H40: CUD classification | I40: 33 | J40: CUD | L40: NVARCHAR | M40: 1000 | N40: D : 삭제 | O40: CUD classification
B41: 34 | C41: BRANG | E41: char | F41: 10 | G41: Brand Group | H41: Brand group | I41: 34 | J41: BrandGroup | L41: nvarchar | M41: 1000 | N41: Brand Group | O41: Brand group | T41: 자재공통칼럼
B42: 35 | C42: ZZQIDATE | E42: CHAR | F42: 3 | G42: 플랜트별 품질검사일수(일) | H42: 플랜트별 품질검사일수(일) | I42: 35 | J42: QA_DAYS | L42: NVARCHAR | M42: 1000 | N42: 품질검사일자 | T42: 신규추가.25.10.20
B43: 36 | C43: ZZFPRDD | E43: CHAR | F43: 8 | G43: 최초생산일자 | I43: 36 | J43: FirstProdDate | N43: 최초생산일자
B44: 37 | C44: ZZLPRDD | E44: CHAR | F44: 8 | G44: 최종생산일자 | I44: 37 | J44: LastProdDate | N44: 최종생산일자
C46: ZZSCGRP | E46: CHAR | G46: 소싱그룹 | J46: SRC_GRP | L46: nvarchar2 | M46: 1000 | N46: 소싱그룹 | T46: 20251215 추가
J49: IF_DATE | L49: DATE | N49: 인터페이스 일자 | O49: Interface date
J50: IF_STATUS | L50: VARCHAR2 | M50: 30 | N50: 인터페이스 처리 상태 | O50: Interface Status
J51: IF_PROCESS_DATE | L51: DATE | N51: 인터페이스 처리 일자 | O51: Interface Process date
J52: IF_ERROR | L52: VARCHAR2 | M52: 1000 | N52: 인터페이스 에러 | Z52: MFG_PLNT_CD | AA52: VARCHAR(4) | AB52: 생산플랜트코드 | AC52: Production Plant Code.
Z53: NITM_APLY_YN | AA53: VARCHAR(1) | AB53: 품목수적용여부 | AC53: Item Application.
B54: 변환규칙정의 | Z54: FST_MFG_DT | AA54: VARCHAR(10) | AB54: 최초생산일자 | AC54: Initial Production Date.
B55: 변환규칙 | D55: 내용 | Z55: LST_MFG_DT | AA55: VARCHAR(10) | AB55: 최종생산일자 | AC55: Final production date.
B56: R1 | Z56: PRD_BRCD_CD | AA56: VARCHAR(15) | AB56: 상품바코드코드 | AC56: Product barcode code.
B57: R2 | Z57: REG_APPL_CL_CD | AA57: VARCHAR(10) | AB57: 등록어플리케이션구분코드 | AC57: Registration Application Type Code.
Z58: CP_PRD_YN | AA58: VARCHAR(1) | AB58: 자사상품여부 | AC58: Is it a company product?.
B59: 기타정보 | Z59: INSD_MGNT_AMT | AA59: NUMBER(20,3) | AB59: 내부관리금액 | AC59: Internal Management Amount.
B60: 이벤트 발생조건 (DB Trigger) | Z60: WKPL_CL_CD | AA60: VARCHAR(10) | AB60: 사업장구분코드 | AC60: Business Site Classification Code.
B61: 연계데이터 추출조건 | Z61: ASRC_PRD_MKT_CAT_CD | AA61: VARCHAR(2) | AB61: 소스상품마케팅분류코드 | AC61: Source Product Marketing Classification Code.
B62: 데이터 반영방법 | Z62: ASRC_PRD_CAT_CD | AA62: VARCHAR(10) | AB62: 소스상품분류코드 | AC62: Source Product Classification Code.
B63: 기타 | Z63: PRD_TP_CD | AA63: VARCHAR(4) | AB63: 상품유형코드 | AC63: Product Type Code.
C66: 코드 및 코드명 ex) FG: 제품
C67: 자재구분의 계층구조
C68: 각 레벨 별 코드 및 코드명 필요
C69: 코드 및 코드명

Sheet 자재단가(판가)
A1: Top
B2: 매핑정의서 - 자재단가(판가) | J2: Source System | K2: SAP | O2: 문서작성일 | P2: 2025.09.25
J3: Target System | K3: APLAN | O3: 버전 | P3: 0.1
B4: 매핑정의
B5: Source Table : ? | I5: Target Table : ? | R5: Set Value | S5: 변환 규칙 | Z5: CDP 자재 마스터 테이블 명세서 (D_PRD_MSTR)
B6: RFC | C6: ZSD_SEND_CHANNEL_PRICE | I6: Web SVC | J6: PreProd : https://myamorepacificpreprod.o9solutions.com/ Prod : https://myamorepacific.o9solutions.com/
B7: SEQ | C7: Field | D7: PK | E7: Type | F7: Size | G7: Desc | H7: Desc(ENG) | I7: SEQ | J7: Field | K7: PK | L7: Type | M7: Size | N7: Desc | O7: Desc(ENG) | P7: Req No | Q7: Res No | Z7: 컬럼명 | AA7: 데이터타입 | AB7: 한글명 | AC7: 영문명
B8: 1 | C8: I_LEGACY | D8: Y | E8: VARCHAR2 | F8: 10 | G8: Legacy system | H8: Legacy System | I8: 1 | K8: Y | Z8: PRD_CD | AA8: VARCHAR(12) | AB8: 상품코드 | AC8: Product Code.
B9: 2 | C9: KNUMH | D9: Y | E9: VARCHAR2 | F9: 10 | G9: 조건 번호 | H9: Condition number | I9: 2 | J9: ConditionNo | K9: Y | L9: NVARCHAR | M9: 1000 | N9: 조건 번호 | O9: Condition number | Z9: PRD_NM | AA9: VARCHAR(100) | AB9: 상품명 | AC9: Product Name.
B10: 3 | C10: KSCHL | D10: Y | E10: VARCHAR2 | F10: 12 | G10: 조건 유형 | H10: Condition | I10: 3 | J10: ConditionType | K10: Y | L10: NVARCHAR | M10: 1000 | N10: 조건 유형 | O10: Condition | Z10: PRD_ENGL_NM | AA10: VARCHAR(200) | AB10: 상품영어명 | AC10: Product English Name.
B11: 4 | C11: VKORG | D11: Y | E11: VARCHAR2 | F11: 12 | G11: 판매 조직 | H11: Sales organization | I11: 4 | J11: SalesOrg | K11: Y | L11: NVARCHAR | M11: 1000 | N11: 판매 조직 | O11: Sales organization | Z11: ENGL_PRD_NM | AA11: VARCHAR(100) | AB11: 영어상품명(비표준) | AC11: English Product Name (Non-Standard).
B12: 5 | C12: WAERK | D12: Y | E12: VARCHAR2 | F12: 15 | G12: 통화 | H12: Currency | I12: 5 | J12: Currency | K12: Y | L12: NVARCHAR | M12: 1000 | N12: 통화 | O12: Currency | Z12: BRND_CD | AA12: VARCHAR(5) | AB12: 브랜드코드 | AC12: Brand Code.
B13: 6 | C13: MATNR | D13: Y | E13: VARCHAR2 | F13: 54 | G13: 자재 번호 | H13: Material number | I13: 6 | J13: Item | K13: Y | L13: NVARCHAR | M13: 1000 | N13: 자재 번호 | O13: Material number | Z13: BRND_DTL_CD | AA13: VARCHAR(6) | AB13: 브랜드상세코드 | AC13: Brand Detail Code.
B14: 7 | C14: PLTYP | E14: VARCHAR2 | F14: 6 | G14: 가격리스트유형 | H14: Price list type | I14: 7 | J14: PriceListType | L14: NVARCHAR | M14: 1000 | N14: 가격리스트유형 | O14: Price list type | Z14: RPRS_PRD_CD | AA14: VARCHAR(12) | AB14: 대표상품코드 | AC14: Representative Product Code.
B15: 8 | C15: DATBI | E15: VARCHAR2 | F15: 24 | G15: 종료일 | H15: End date | I15: 8 | J15: EffEndDate | L15: NVARCHAR | M15: 1000 | N15: 종료일 | O15: End date | Z15: RPRS_PRD_NM | AA15: VARCHAR(100) | AB15: 대표상품명 | AC15: Product Name.
B16: 9 | C16: DATAB | E16: VARCHAR2 | F16: 24 | G16: 시작일 | H16: start date | I16: 9 | J16: EffStartDate | L16: NVARCHAR | M16: 1000 | N16: 시작일 | O16: start date | Z16: RPRS_PRD_ENGL_NM | AA16: VARCHAR(100) | AB16: 대표상품영어명 | AC16: Representative Product English Name.
B17: 10 | C17: KBETR | E17: NUMBER | F17: 11.2 | G17: 상품대(부가세제외) | H17: Product price (excluding additional tax) | I17: 10 | J17: KBETR | L17: NVARCHAR | M17: 1000 | N17: 상품대(부가세제외) | O17: Product price (excluding additional tax) | Z17: RPLC_PRD_CD | AA17: VARCHAR(12) | AB17: 대체상품코드 | AC17: Alternative Product Code.
B18: 11 | C18: KBETR_INV | E18: NUMBER | F18: 11.2 | G18: 출하가(부가세포함) | H18: Shipping price (additional cell box) | I18: 11 | J18: KBETR_INV | L18: NVARCHAR | M18: 1000 | N18: 출하가(부가세포함) | O18: Shipping price (additional cell box) | Z18: PRD_MKT_CAT_CD | AA18: VARCHAR(2) | AB18: 상품마케팅분류코드 | AC18: Product Marketing Classification Code.
B19: 12 | C19: KBETR_VAT | E19: NUMBER | F19: 11.2 | G19: 부가세 | H19: VAT | I19: 12 | J19: KBETR_VAT | L19: NVARCHAR | M19: 1000 | N19: 부가세 | O19: VAT | Z19: SET_PRD_YN | AA19: VARCHAR(1) | AB19: 세트상품여부 | AC19: Set product or not.
B20: 13 | C20: SPETAX | E20: NUMBER | F20: 11.2 | G20: 특소세(개별소비세+교육세+농어촌특별세) | H20: Special tax (individual consumption tax+education tax+special farming and fishing village) | I20: 13 | J20: SPETAX | L20: NVARCHAR | M20: 1000 | N20: 특소세(개별소비세+교육세+농어촌특별세) | O20: Special tax (individual consumption tax+education tax+special farming and fishing village) | Z20: SET_DSMN_YN | AA20: VARCHAR(1) | AB20: 세트해체여부 | AC20: Set disassembly.
B21: 14 | C21: CONTAX | E21: NUMBER | F21: 11.2 | G21: 개별소비세 | H21: Individual consumption tax | I21: 14 | J21: CONTAX | L21: NVARCHAR | M21: 1000 | N21: 개별소비세 | O21: Individual consumption tax | Z21: CNSM_UTPR_AMT | AA21: NUMBER(20,3) | AB21: 소비자단가금액 | AC21: Consumer Unit Price.
B22: 15 | C22: EDUTAX | E22: NUMBER | F22: 11.2 | G22: 교육세 | H22: Education tax | I22: 15 | J22: EDUTAX | L22: NVARCHAR | M22: 1000 | N22: 교육세 | O22: Education tax | Z22: PRD_CPT | AA22: NUMBER(38,0) | AB22: 상품용량 | AC22: Product Capacity.
B23: 16 | C23: RURTAX | E23: NUMBER | F23: 11.2 | G23: 농어촌특별세 | H23: Special tax | I23: 16 | J23: RURTAX | L23: NVARCHAR | M23: 1000 | N23: 농어촌특별세 | O23: Special tax | Z23: PRD_CPT_UNIT_CD | AA23: VARCHAR(3) | AB23: 상품용량단위코드 | AC23: Product Unit Code.
B24: 17 | C24: LOEVM_KO | E24: VARCHAR2 | F24: 2 | G24: 삭제지시자 | H24: Deleter | I24: 17 | J24: DeleteFlag | L24: NVARCHAR | M24: 1000 | N24: 삭제지시자 | O24: Deleter | Z24: PRD_USE_CD | AA24: VARCHAR(3) | AB24: 상품용도코드 | AC24: Product Use Code.
B25: 18 | C25: GUBUN | E25: VARCHAR2 | F25: 2 | G25: 구분 | H25: division | I25: 18 | J25: Type | L25: NVARCHAR | M25: 1000 | N25: 구분 | O25: division | Z25: PRD_CAT_CD | AA25: VARCHAR(10) | AB25: 상품분류코드 | AC25: Product Classification Code.
B26: 19 | C26: TYPE | E26: CHAR | F26: 1 | G26: 전송결과 S,E | H26: Transmission Result S, E | I26: 19 | Z26: MAIN_FUNC_CD | AA26: VARCHAR(4) | AB26: 주요기능코드 | AC26: Main Function Code.
B27: 20 | C27: MESSAGE | E27: CHAR | F27: 220 | G27: 전송결과 메시지 | H27: Transmission result message | I27: 20 | Z27: USER_TP_CD | AA27: VARCHAR(1) | AB27: 사용자유형코드 | AC27: User Type Code.
B28: 21 | I28: 21 | Z28: FRSH_CSMT_YN | AA28: VARCHAR(1) | AB28: 신선화장품여부 | AC28: Fresh Cosmetics.
B29: 22 | I29: 22 | Z29: PRD_CL_CD | AA29: VARCHAR(2) | AB29: 상품구분코드 | AC29: Product Classification Code.
B30: 23 | I30: 23 | Z30: SLS_TP_CD | AA30: VARCHAR(3) | AB30: 영업유형코드 | AC30: Sales Type Code.
B31: 24 | I31: 24 | Z31: SAP_PRD_LN_CD | AA31: VARCHAR(4) | AB31: SAP상품라인코드 | AC31: SAP Product Line Code.
B32: 25 | I32: 25 | Z32: PRD_CLR_CD | AA32: VARCHAR(4) | AB32: 상품색상코드 | AC32: Product Color Code.
B33: 26 | I33: 26 | Z33: NEW_PRD_CL_CD | AA33: VARCHAR(3) | AB33: 신상품구분코드 | AC33: New Product Code.
B34: 27 | I34: 27 | Z34: STRO_PRD_YN | AA34: VARCHAR(1) | AB34: 강한상품여부 | AC34: Strong product or not.
B35: 28 | I35: 28 | Z35: INNO_PRD_YN | AA35: VARCHAR(1) | AB35: 혁신상품여부 | AC35: Innovative Product Status.
B36: 29 | I36: 29 | Z36: CUSH_PRD_YN | AA36: VARCHAR(1) | AB36: 쿠션상품여부 | AC36: Cushion product status.
B37: 30 | I37: 30 | Z37: PRD_GRD_CD | AA37: VARCHAR(3) | AB37: 상품등급코드 | AC37: Product Grade Code.
B38: 31 | I38: 31 | Z38: BRND_LN_CD | AA38: VARCHAR(4) | AB38: 브랜드라인코드 | AC38: Brand Line Code.
Z39: MFG_PLNT_CD | AA39: VARCHAR(4) | AB39: 생산플랜트코드 | AC39: Production Plant Code.
Z40: NITM_APLY_YN | AA40: VARCHAR(1) | AB40: 품목수적용여부 | AC40: Item Application.
B41: 변환규칙정의 | Z41: FST_MFG_DT | AA41: VARCHAR(10) | AB41: 최초생산일자 | AC41: Initial Production Date.
B42: 변환규칙 | D42: 내용 | Z42: LST_MFG_DT | AA42: VARCHAR(10) | AB42: 최종생산일자 | AC42: Final production date.
B43: R1 | Z43: PRD_BRCD_CD | AA43: VARCHAR(15) | AB43: 상품바코드코드 | AC43: Product barcode code.
B44: R2 | Z44: REG_APPL_CL_CD | AA44: VARCHAR(10) | AB44: 등록어플리케이션구분코드 | AC44: Registration Application Type Code.
Z45: CP_PRD_YN | AA45: VARCHAR(1) | AB45: 자사상품여부 | AC45: Is it a company product?.
B46: 기타정보 | Z46: INSD_MGNT_AMT | AA46: NUMBER(20,3) | AB46: 내부관리금액 | AC46: Internal Management Amount.
B47: 이벤트 발생조건 (DB Trigger) | Z47: WKPL_CL_CD | AA47: VARCHAR(10) | AB47: 사업장구분코드 | AC47: Business Site Classification Code.
B48: 연계데이터 추출조건 | Z48: ASRC_PRD_MKT_CAT_CD | AA48: VARCHAR(2) | AB48: 소스상품마케팅분류코드 | AC48: Source Product Marketing Classification Code.
B49: 데이터 반영방법 | Z49: ASRC_PRD_CAT_CD | AA49: VARCHAR(10) | AB49: 소스상품분류코드 | AC49: Source Product Classification Code.
B50: 기타 | Z50: PRD_TP_CD | AA50: VARCHAR(4) | AB50: 상품유형코드 | AC50: Product Type Code.

Sheet NPD자재목록
A1: Top
B2: 매핑정의서 - NPD자재목록(NPD material list) | J2: Source System | K2: NPD | O2: 문서작성일 | P2: 2025.09.25
J3: Target System | K3: APLAN | O3: 버전 | P3: 0.1
B4: 매핑정의
B5: Source Table : ? | I5: Target Table : ? | R5: Set Value | S5: 변환 규칙 | Z5: CDP 자재 마스터 테이블 명세서 (D_PRD_MSTR)
B6: RFC | I6: Web SVC | J6: PreProd : https://myamorepacificpreprod.o9solutions.com/ Prod : https://myamorepacific.o9solutions.com/
B7: SEQ | C7: Field | D7: PK | E7: Type | F7: Size | G7: Desc | H7: Desc(ENG) | I7: SEQ | J7: Field | K7: PK | L7: Type | M7: Size | N7: Desc | O7: Desc(ENG) | P7: Req No | Q7: Res No | Z7: 컬럼명 | AA7: 데이터타입 | AB7: 한글명 | AC7: 영문명
B8: 1 | C8: I_TERMS_F | D8: Y | E8: CHAR | F8: 8 | G8: 시작일 FROM | H8: From Date | I8: 1 | J8: FROM | K8: Y | L8: NVARCHAR | M8: 1000 | N8: From Date("20221001") | O8: From Date | Z8: PRD_CD | AA8: VARCHAR(12) | AB8: 상품코드 | AC8: Product Code.
B9: 2 | C9: I_TERMS_T | D9: Y | E9: CHAR | F9: 8 | G9: 종료일 TO | H9: To Date | I9: 2 | J9: TO | K9: Y | L9: NVARCHAR | M9: 1000 | N9: To Date | O9: To Date | Z9: PRD_NM | AA9: VARCHAR(100) | AB9: 상품명 | AC9: Product Name.
B10: 3 | C10: DEVNO | D10: Y | E10: CHAR | F10: 12 | G10: 개발의뢰서번호 | H10: Development request number | I10: 3 | J10: DevNo | K10: Y | L10: NVARCHAR | M10: 1000 | N10: 개발의뢰서번호 | O10: Development request number | Z10: PRD_ENGL_NM | AA10: VARCHAR(200) | AB10: 상품영어명 | AC10: Product English Name.
B11: 4 | C11: MATNR | D11: Y | E11: CHAR | F11: 18 | G11: 제품코드 | H11: Product code | I11: 4 | J11: Item | K11: Y | L11: NVARCHAR | M11: 1000 | N11: 제품코드 | O11: Product code | Z11: ENGL_PRD_NM | AA11: VARCHAR(100) | AB11: 영어상품명(비표준) | AC11: English Product Name (Non-Standard).
B12: 5 | C12: YYMM | E12: CHAR | F12: 6 | G12: 생산회의년월( ex: 201709 ) | H12: Production meeting month (ex: 201709) | I12: 5 | J12: YYYYMM | L12: NVARCHAR | M12: 1000 | N12: 생산회의년월( ex: 201709 ) | O12: Production meeting month (ex: 201709) | Z12: BRND_CD | AA12: VARCHAR(5) | AB12: 브랜드코드 | AC12: Brand Code.
B13: 6 | C13: DEGREE | E13: CHAR | F13: 1 | G13: 주차(1,2,3,4) | H13: Week | I13: 6 | J13: Week | L13: NVARCHAR | M13: 1000 | N13: 주차(1,2,3,4) | O13: Week | Z13: BRND_DTL_CD | AA13: VARCHAR(6) | AB13: 브랜드상세코드 | AC13: Brand Detail Code.
B14: 7 | C14: ZZMANFT | E14: CHAR | F14: 4 | G14: 플랜트코드 | H14: Plant code | I14: 7 | J14: Plant | L14: NVARCHAR | M14: 1000 | N14: 플랜트코드 | O14: Plant code | Z14: RPRS_PRD_CD | AA14: VARCHAR(12) | AB14: 대표상품코드 | AC14: Representative Product Code.
B15: 8 | C15: MTBC | E15: CHAR | F15: 1 | G15: [NPD] 생산회의상정확인( X:확인, ‘’: 미확인 ) | H15: Production meeting Confirmation (X: OK, '': Unidentified) | I15: 8 | J15: NPDMeetFlag | L15: NVARCHAR | M15: 1000 | N15: [NPD] 생산회의상정확인( X:확인, ‘’: 미확인 ) | O15: Production meeting Confirmation (X: OK, '': Unidentified) | Z15: RPRS_PRD_NM | AA15: VARCHAR(100) | AB15: 대표상품명 | AC15: Product Name.
B16: 9 | C16: LVORM | E16: CHAR | F16: 1 | G16: 삭제여부(개발의뢰서 삭제하는경우( X:삭제, ‘’: 미삭제 ) | H16: Deletion (X: delete, ‘’: Undeleted ) | I16: 9 | J16: DeleteFlag | L16: NVARCHAR | M16: 1000 | N16: 삭제여부(개발의뢰서 삭제하는경우( X:삭제, ‘’: 미삭제 ) | O16: Deletion (X: delete, ‘’: Undeleted ) | Z16: RPRS_PRD_ENGL_NM | AA16: VARCHAR(100) | AB16: 대표상품영어명 | AC16: Representative Product English Name.
B17: 10 | I17: 10 | Z17: RPLC_PRD_CD | AA17: VARCHAR(12) | AB17: 대체상품코드 | AC17: Alternative Product Code.
B18: 11 | I18: 11 | Z18: PRD_MKT_CAT_CD | AA18: VARCHAR(2) | AB18: 상품마케팅분류코드 | AC18: Product Marketing Classification Code.
B19: 12 | I19: 12 | Z19: SET_PRD_YN | AA19: VARCHAR(1) | AB19: 세트상품여부 | AC19: Set product or not.
B20: 13 | I20: 13 | Z20: SET_DSMN_YN | AA20: VARCHAR(1) | AB20: 세트해체여부 | AC20: Set disassembly.
B21: 14 | I21: 14 | Z21: CNSM_UTPR_AMT | AA21: NUMBER(20,3) | AB21: 소비자단가금액 | AC21: Consumer Unit Price.
B22: 15 | I22: 15 | Z22: PRD_CPT | AA22: NUMBER(38,0) | AB22: 상품용량 | AC22: Product Capacity.
B23: 16 | I23: 16 | Z23: PRD_CPT_UNIT_CD | AA23: VARCHAR(3) | AB23: 상품용량단위코드 | AC23: Product Unit Code.
B24: 17 | I24: 17 | Z24: PRD_USE_CD | AA24: VARCHAR(3) | AB24: 상품용도코드 | AC24: Product Use Code.
B25: 18 | I25: 18 | Z25: PRD_CAT_CD | AA25: VARCHAR(10) | AB25: 상품분류코드 | AC25: Product Classification Code.
B26: 19 | I26: 19 | Z26: MAIN_FUNC_CD | AA26: VARCHAR(4) | AB26: 주요기능코드 | AC26: Main Function Code.
B27: 20 | I27: 20 | Z27: USER_TP_CD | AA27: VARCHAR(1) | AB27: 사용자유형코드 | AC27: User Type Code.
B28: 21 | I28: 21 | Z28: FRSH_CSMT_YN | AA28: VARCHAR(1) | AB28: 신선화장품여부 | AC28: Fresh Cosmetics.
... B38: 31 | I38: 31 | Z38: BRND_LN_CD | AA38: VARCHAR(4) | AB38: 브랜드라인코드 | AC38: Brand Line Code.
Z39: MFG_PLNT_CD | AA39: VARCHAR(4) | AB39: 생산플랜트코드 | AC39: Production Plant Code.
Z40: NITM_APLY_YN | AA40: VARCHAR(1) | AB40: 품목수적용여부 | AC40: Item Application.
B41: 변환규칙정의 | Z41: FST_MFG_DT | AA41: VARCHAR(10) | AB41: 최초생산일자 | AC41: Initial Production Date.
B42: 변환규칙 | D42: 내용 | Z42: LST_MFG_DT | AA42: VARCHAR(10) | AB42: 최종생산일자 | AC42: Final production date.
B43: R1 | Z43: PRD_BRCD_CD | AA43: VARCHAR(15) | AB43: 상품바코드코드 | AC43: Product barcode code.
B44: R2 | Z44: REG_APPL_CL_CD | AA44: VARCHAR(10) | AB44: 등록어플리케이션구분코드 | AC44: Registration Application Type Code.
Z45: CP_PRD_YN | AA45: VARCHAR(1) | AB45: 자사상품여부 | AC45: Is it a company product?.
B46: 기타정보 | Z46: INSD_MGNT_AMT | AA46: NUMBER(20,3) | AB46: 내부관리금액 | AC46: Internal Management Amount.
B47: 이벤트 발생조건 (DB Trigger) | Z47: WKPL_CL_CD | AA47: VARCHAR(10) | AB47: 사업장구분코드 | AC47: Business Site Classification Code.
B48: 연계데이터 추출조건 | Z48: ASRC_PRD_MKT_CAT_CD | AA48: VARCHAR(2) | AB48: 소스상품마케팅분류코드 | AC48: Source Product Marketing Classification Code.
B49: 데이터 반영방법 | Z49: ASRC_PRD_CAT_CD | AA49: VARCHAR(10) | AB49: 소스상품분류코드 | AC49: Source Product Classification Code.
B50: 기타 | Z50: PRD_TP_CD | AA50: VARCHAR(4) | AB50: 상품유형코드 | AC50: Product Type Code.

Sheet 제품허가정보
A1: Top
B2: 매핑정의서 - 제품허가정보 관리 Product License Information | J2: Source System | K2: SAP | O2: 문서작성일 | P2: 2025.09.25
J3: Target System | K3: APLAN | O3: 버전 | P3: 0.1
B4: 매핑정의
B5: Source Table : ? | I5: Target Table : ? | R5: Set Value | S5: 변환 규칙 | Z5: CDP 자재 마스터 테이블 명세서 (D_PRD_MSTR)
B6: RFC | I6: Web SVC | J6: PreProd : https://myamorepacificpreprod.o9solutions.com/ Prod : https://myamorepacific.o9solutions.com/
B7: SEQ | C7: Field | D7: PK | E7: Type | F7: Size | G7: Desc | H7: Desc(ENG) | I7: SEQ | J7: Field | K7: PK | L7: Type | M7: Size | N7: Desc | O7: Desc(ENG) | P7: Req No | Q7: Res No | Z7: 컬럼명 | AA7: 데이터타입 | AB7: 한글명 | AC7: 영문명
B8: 1 | C8: IT_TABLE | D8: Y | E8: CHAR | F8: 5 | G8: LEGACY SYSTEM | H8: Legacy System | I8: 1 | Z8: PRD_CD | AA8: VARCHAR(12) | AB8: 상품코드 | AC8: Product Code.
B9: 2 | C9: VKORG | D9: Y | E9: CHAR | F9: 4 | G9: 영업조직 | H9: Sales organization | I9: 2 | J9: SalesOrg | K9: Y | L9: NVARCHAR | M9: 1000 | N9: 영업조직 | O9: Sales organization | Z9: PRD_NM | AA9: VARCHAR(100) | AB9: 상품명 | AC9: Product Name.
B10: 3 | C10: MATNR | D10: Y | E10: CHAR | F10: 18 | G10: 자재 번호 | H10: Material number | I10: 3 | J10: Item | K10: Y | L10: NVARCHAR | M10: 1000 | N10: 자재 번호 | O10: Material number | Z10: PRD_ENGL_NM | AA10: VARCHAR(200) | AB10: 상품영어명 | AC10: Product English Name.
B11: 4 | C11: LAND1 | D11: Y | E11: CHAR | F11: 3 | G11: 국가 키 | H11: National key | I11: 4 | J11: Country | K11: Y | L11: NVARCHAR | M11: 1000 | N11: 국가 키 | O11: National key | Z11: ENGL_PRD_NM | AA11: VARCHAR(100) | AB11: 영어상품명(비표준) | AC11: English Product Name (Non-Standard).
B12: 5 | C12: CONT_CODE | D12: Y | E12: CHAR | F12: 20 | G12: 내용물코드 | H12: Content cord | I12: 5 | J12: Component | K12: Y | L12: NVARCHAR | M12: 1000 | N12: 내용물코드 | O12: Content cord | Z12: BRND_CD | AA12: VARCHAR(5) | AB12: 브랜드코드 | AC12: Brand Code.
B13: 6 | C13: LIC_DATEED | E13: DATS | F13: 8 | G13: 허가 만료일 | H13: License expiration date | I13: 6 | J13: LicenseExpDate | K13: Y | L13: NVARCHAR | M13: 1000 | N13: 허가 만료일 | O13: License expiration date | Z13: BRND_DTL_CD | AA13: VARCHAR(6) | AB13: 브랜드상세코드 | AC13: Brand Detail Code.
B14: 7 | C14: LIC_DATEOP | E14: DATS | F14: 8 | G14: 허가 취득일 | H14: License acquisition date | I14: 7 | J14: LicenseIssueDate | L14: NVARCHAR | M14: 1000 | N14: 허가 취득일 | O14: License acquisition date | Z14: RPRS_PRD_CD | AA14: VARCHAR(12) | AB14: 대표상품코드 | AC14: Representative Product Code.
B15: 8 | C15: LIC_ST_DT | E15: DATS | F15: 8 | G15: 허가 신청일 | H15: License application date | I15: 8 | J15: LicenseReqDate | L15: NVARCHAR | M15: 1000 | N15: 허가 신청일 | O15: License application date | Z15: RPRS_PRD_NM | AA15: VARCHAR(100) | AB15: 대표상품명 | AC15: Product Name.
B16: 9 | C16: LIC_CP_DT | E16: DATS | F16: 8 | G16: 예상허가 취득일 | H16: Expected permit acquisition date | I16: 9 | J16: ExpectIssueDate | L16: NVARCHAR | M16: 1000 | N16: 예상허가 취득일 | O16: Expected permit acquisition date | Z16: RPRS_PRD_ENGL_NM | AA16: VARCHAR(100) | AB16: 대표상품영어명 | AC16: Representative Product English Name.
B17: 10 | C17: LIC_FLAG | E17: CHAR | F17: 1 | G17: 허가 불필요 | H17: Unnecessary permission | I17: 10 | J17: NotConfirmFlag | L17: NVARCHAR | M17: 1000 | N17: 허가 불필요 | O17: Unnecessary permission | Z17: RPLC_PRD_CD | AA17: VARCHAR(12) | AB17: 대체상품코드 | AC17: Alternative Product Code.
B18: 11 | I18: 11 | Z18: PRD_MKT_CAT_CD | AA18: VARCHAR(2) | AB18: 상품마케팅분류코드 | AC18: Product Marketing Classification Code.
B19: 12 | I19: 12 | Z19: SET_PRD_YN | AA19: VARCHAR(1) | AB19: 세트상품여부 | AC19: Set product or not.
B20: 13 | I20: 13 | Z20: SET_DSMN_YN | AA20: VARCHAR(1) | AB20: 세트해체여부 | AC20: Set disassembly.
B21: 14 | I21: 14 | Z21: CNSM_UTPR_AMT | AA21: NUMBER(20,3) | AB21: 소비자단가금액 | AC21: Consumer Unit Price.
B22: 15 | I22: 15 | Z22: PRD_CPT | AA22: NUMBER(38,0) | AB22: 상품용량 | AC22: Product Capacity.
B23: 16 | I23: 16 | Z23: PRD_CPT_UNIT_CD | AA23: VARCHAR(3) | AB23: 상품용량단위코드 | AC23: Product Unit Code.
B24: 17 | I24: 17 | Z24: PRD_USE_CD | AA24: VARCHAR(3) | AB24: 상품용도코드 | AC24: Product Use Code.
B25: 18 | I25: 18 | Z25: PRD_CAT_CD | AA25: VARCHAR(10) | AB25: 상품분류코드 | AC25: Product Classification Code.
B26: 19 | I26: 19 | Z26: MAIN_FUNC_CD | AA26: VARCHAR(4) | AB26: 주요기능코드 | AC26: Main Function Code.
B27: 20 | I27: 20 | Z27: USER_TP_CD | AA27: VARCHAR(1) | AB27: 사용자유형코드 | AC27: User Type Code.
B28: 21 | I28: 21 | Z28: FRSH_CSMT_YN | AA28: VARCHAR(1) | AB28: 신선화장품여부 | AC28: Fresh Cosmetics.
B29: 22 | I29: 22 | Z29: PRD_CL_CD | AA29: VARCHAR(2) | AB29: 상품구분코드 | AC29: Product Classification Code.
... B38: 31 | I38: 31 | Z38: BRND_LN_CD | AA38: VARCHAR(4) | AB38: 브랜드라인코드 | AC38: Brand Line Code.
Z39: MFG_PLNT_CD | AA39: VARCHAR(4) | AB39: 생산플랜트코드 | AC39: Production Plant Code.
Z40: NITM_APLY_YN | AA40: VARCHAR(1) | AB40: 품목수적용여부 | AC40: Item Application.
B41: 변환규칙정의 | Z41: FST_MFG_DT | AA41: VARCHAR(10) | AB41: 최초생산일자 | AC41: Initial Production Date.
B42: 변환규칙 | D42: 내용 | Z42: LST_MFG_DT | AA42: VARCHAR(10) | AB42: 최종생산일자 | AC42: Final production date.
B43: R1 | Z43: PRD_BRCD_CD | AA43: VARCHAR(15) | AB43: 상품바코드코드 | AC43: Product barcode code.
B44: R2 | Z44: REG_APPL_CL_CD | AA44: VARCHAR(10) | AB44: 등록어플리케이션구분코드 | AC44: Registration Application Type Code.
Z45: CP_PRD_YN | AA45: VARCHAR(1) | AB45: 자사상품여부 | AC45: Is it a company product?.
B46: 기타정보 | Z46: INSD_MGNT_AMT | AA46: NUMBER(20,3) | AB46: 내부관리금액 | AC46: Internal Management Amount.
B47: 이벤트 발생조건 (DB Trigger) | Z47: WKPL_CL_CD | AA47: VARCHAR(10) | AB47: 사업장구분코드 | AC47: Business Site Classification Code.
B48: 연계데이터 추출조건 | Z48: ASRC_PRD_MKT_CAT_CD | AA48: VARCHAR(2) | AB48: 소스상품마케팅분류코드 | AC48: Source Product Marketing Classification Code.
B49: 데이터 반영방법 | Z49: ASRC_PRD_CAT_CD | AA49: VARCHAR(10) | AB49: 소스상품분류코드 | AC49: Source Product Classification Code.
B50: 기타 | Z50: PRD_TP_CD | AA50: VARCHAR(4) | AB50: 상품유형코드 | AC50: Product Type Code.

Sheet 단종품의완료
A1: Top
B2: 매핑정의서 - 단종품의완료 | J2: Source System | K2: AP-ON | O2: 문서작성일 | P2: 2025.09.25
J3: Target System | K3: APLAN | O3: 버전 | P3: 0.1
B4: 매핑정의
B5: Source Table : ? | I5: Target Table : ? | R5: Set Value | S5: 변환규칙 | Z5: CDP 자재 마스터 테이블 명세서 (D_PRD_MSTR)
B6: RFC | I6: Web SVC | J6: PreProd : https://myamorepacificpreprod.o9solutions.com/ Prod : https://myamorepacific.o9solutions.com/
B7: SEQ | C7: Field | D7: PK | E7: Type | F7: Size | G7: Desc | H7: Desc(ENG) | I7: SEQ | J7: Field | K7: PK | L7: Type | M7: Size | N7: Desc | O7: Desc(ENG) | P7: Req No | Q7: Res No | Z7: 컬럼명 | AA7: 데이터타입 | AB7: 한글명 | AC7: 영문명
B8: 1 | C8: REQNO | E8: CHAR | F8: 35 | G8: (승인)요청번호 | H8: (Approval) Request number | I8: 1 | J8: ReqNo | L8: NVARCHAR | M8: 1000 | N8: (승인)요청번호 | O8: (Approval) Request number | Z8: PRD_CD | AA8: VARCHAR(12) | AB8: 상품코드 | AC8: Product Code.
B9: 2 | C9: SEQNO | E9: CHAR | F9: 6 | G9: 일련번호 | H9: Serial Number | I9: 2 | J9: SeqNo | L9: NVARCHAR | M9: 1000 | N9: 일련번호 | O9: Serial Number | Z9: PRD_NM | AA9: VARCHAR(100) | AB9: 상품명 | AC9: Product Name.
B10: 3 | C10: BUKRS | E10: CHAR | F10: 4 | G10: 회사코드 | H10: Company code | I10: 3 | J10: Company | L10: NVARCHAR | M10: 1000 | N10: 회사코드 | O10: Company code | Z10: PRD_ENGL_NM | AA10: VARCHAR(200) | AB10: 상품영어명 | AC10: Product English Name.
B11: 4 | C11: VKORG | E11: CHAR | F11: 4 | G11: 영업조직 | H11: Sales organization | I11: 4 | J11: SalesOrg | L11: NVARCHAR | M11: 1000 | N11: 영업조직 | O11: Sales organization | Z11: ENGL_PRD_NM | AA11: VARCHAR(100) | AB11: 영어상품명(비표준) | AC11: English Product Name (Non-Standard).
B12: 5 | C12: CPRREGDAT | E12: DAT | F12: 8 | G12: 압축월 등록일 | H12: SKU Out registration date | I12: 5 | J12: SKUOutMonRegDate | L12: NVARCHAR | M12: 1000 | N12: 압축월 등록일 | O12: SKU Out registration date | Z12: BRND_CD | AA12: VARCHAR(5) | AB12: 브랜드코드 | AC12: Brand Code.
B13: 6 | C13: MATNR | E13: CHAR | F13: 18 | G13: 자재코드 | H13: Material code | I13: 6 | J13: Item | L13: NVARCHAR | M13: 1000 | N13: 자재코드 | O13: Material code | Z13: BRND_DTL_CD | AA13: VARCHAR(6) | AB13: 브랜드상세코드 | AC13: Brand Detail Code.
B14: 7 | C14: ERDAT | E14: DAT | F14: 8 | G14: 압축품의 일자 | H14: Date of SKU Out | I14: 7 | J14: SKUOutMonth | L14: NVARCHAR | M14: 1000 | N14: 압축품의 일자 | O14: Date of SKU Out | Z14: RPRS_PRD_CD | AA14: VARCHAR(12) | AB14: 대표상품코드 | AC14: Representative Product Code.
B15: 8 | C15: APSTK | E15: CHAR | F15: 1 | G15: 압축품의 진행상태 | H15: Progress status of SKU Out | I15: 8 | J15: SKUOutStatus | L15: NVARCHAR | M15: 1000 | N15: 압축품의 진행상태 | O15: Progress status of SKU Out | Z15: RPRS_PRD_NM | AA15: VARCHAR(100) | AB15: 대표상품명 | AC15: Product Name.
B16: 9 | I16: 9 | Z16: RPRS_PRD_ENGL_NM | AA16: VARCHAR(100) | AB16: 대표상품영어명 | AC16: Representative Product English Name.
B17: 10 | I17: 10 | Z17: RPLC_PRD_CD | AA17: VARCHAR(12) | AB17: 대체상품코드 | AC17: Alternative Product Code.
B18: 11 | I18: 11 | Z18: PRD_MKT_CAT_CD | AA18: VARCHAR(2) | AB18: 상품마케팅분류코드 | AC18: Product Marketing Classification Code.
B19: 12 | I19: 12 | Z19: SET_PRD_YN | AA19: VARCHAR(1) | AB19: 세트상품여부 | AC19: Set product or not.
B20: 13 | I20: 13 | Z20: SET_DSMN_YN | AA20: VARCHAR(1) | AB20: 세트해체여부 | AC20: Set disassembly.
B21: 14 | I21: 14 | Z21: CNSM_UTPR_AMT | AA21: NUMBER(20,3) | AB21: 소비자단가금액 | AC21: Consumer Unit Price.
B22: 15 | I22: 15 | Z22: PRD_CPT | AA22: NUMBER(38,0) | AB22: 상품용량 | AC22: Product Capacity.
B23: 16 | I23: 16 | Z23: PRD_CPT_UNIT_CD | AA23: VARCHAR(3) | AB23: 상품용량단위코드 | AC23: Product Unit Code.
B24: 17 | I24: 17 | Z24: PRD_USE_CD | AA24: VARCHAR(3) | AB24: 상품용도코드 | AC24: Product Use Code.
B25: 18 | I25: 18 | Z25: PRD_CAT_CD | AA25: VARCHAR(10) | AB25: 상품분류코드 | AC25: Product Classification Code.
B26: 19 | I26: 19 | Z26: MAIN_FUNC_CD | AA26: VARCHAR(4) | AB26: 주요기능코드 | AC26: Main Function Code.
B27: 20 | I27: 20 | Z27: USER_TP_CD | AA27: VARCHAR(1) | AB27: 사용자유형코드 | AC27: User Type Code.
... B38: 31 | I38: 31 | Z38: BRND_LN_CD | AA38: VARCHAR(4) | AB38: 브랜드라인코드 | AC38: Brand Line Code.
Z39: MFG_PLNT_CD | AA39: VARCHAR(4) | AB39: 생산플랜트코드 | AC39: Production Plant Code.
Z40: NITM_APLY_YN | AA40: VARCHAR(1) | AB40: 품목수적용여부 | AC40: Item Application.
B41: 변환규칙정의 | Z41: FST_MFG_DT | AA41: VARCHAR(10) | AB41: 최초생산일자 | AC41: Initial Production Date.
B42: 변환규칙 | D42: 내용 | Z42: LST_MFG_DT | AA42: VARCHAR(10) | AB42: 최종생산일자 | AC42: Final production date.
B43: R1 | Z43: PRD_BRCD_CD | AA43: VARCHAR(15) | AB43: 상품바코드코드 | AC43: Product barcode code.
B44: R2 | Z44: REG_APPL_CL_CD | AA44: VARCHAR(10) | AB44: 등록어플리케이션구분코드 | AC44: Registration Application Type Code.
Z45: CP_PRD_YN | AA45: VARCHAR(1) | AB45: 자사상품여부 | AC45: Is it a company product?.
B46: 기타정보 | Z46: INSD_MGNT_AMT | AA46: NUMBER(20,3) | AB46: 내부관리금액 | AC46: Internal Management Amount.
B47: 이벤트 발생조건 (DB Trigger) | Z47: WKPL_CL_CD | AA47: VARCHAR(10) | AB47: 사업장구분코드 | AC47: Business Site Classification Code.
B48: 연계데이터 추출조건 | Z48: ASRC_PRD_MKT_CAT_CD | AA48: VARCHAR(2) | AB48: 소스상품마케팅분류코드 | AC48: Source Product Marketing Classification Code.
B49: 데이터 반영방법 | Z49: ASRC_PRD_CAT_CD | AA49: VARCHAR(10) | AB49: 소스상품분류코드 | AC49: Source Product Classification Code.
B50: 기타 | Z50: PRD_TP_CD | AA50: VARCHAR(4) | AB50: 상품유형코드 | AC50: Product Type Code.

Sheet SKU현황
A1: Top
B2: 매핑정의서 - SKU 현황 SKU 합리화 실적 | J2: Source System | K2: BW | O2: 문서작성일 | P2: 2025.09.25
J3: Target System | K3: APLAN | O3: 버전 | P3: 0.1
B4: 매핑정의
B5: Source Table : ? | I5: Target Table : ? | R5: Set Value | S5: 변환규칙 | Z5: CDP 자재 마스터 테이블 명세서 (D_PRD_MSTR)
B6: RFC | I6: Web SVC | J6: PreProd : https://myamorepacificpreprod.o9solutions.com/ Prod : https://myamorepacific.o9solutions.com/
B7: SEQ | C7: Field | D7: PK | E7: Type | F7: Size | G7: Desc | H7: Desc(ENG) | I7: SEQ | J7: Field | K7: PK | L7: Type | M7: Size | N7: Desc | O7: Desc(ENG) | P7: Req No | Q7: Res No | Z7: 컬럼명 | AA7: 데이터타입 | AB7: 한글명 | AC7: 영문명
B8: 1 | C8: 0salesorg | I8: 1 | J8: SalesOrg | K8: Y | L8: NVARCHAR | M8: 1000 | N8: 영업조직 | O8: Sales organization | Z8: PRD_CD | AA8: VARCHAR(12) | AB8: 상품코드 | AC8: Product Code.
B9: 2 | C9: 0calmonth | I9: 2 | J9: Month | K9: Y | L9: NVARCHAR | M9: 1000 | N9: 월 | O9: month | Z9: PRD_NM | AA9: VARCHAR(100) | AB9: 상품명 | AC9: Product Name.
B10: 3 | C10: zgubuncd | I10: 3 | J10: LocalExportFlag | K10: Y | L10: NVARCHAR | M10: 1000 | N10: 국내/수출 구분(CUBE 기준) | O10: Domestic/export classification (based on CUBE) | Z10: PRD_ENGL_NM | AA10: VARCHAR(200) | AB10: 상품영어명 | AC10: Product English Name.
B11: 4 | C11: 0material | I11: 4 | J11: Item | L11: NVARCHAR | M11: 1000 | N11: 자재 코드 | O11: Material code | Z11: ENGL_PRD_NM | AA11: VARCHAR(100) | AB11: 영어상품명(비표준) | AC11: English Product Name (Non-Standard).
B12: 5 | I12: 5 | Z12: BRND_CD | AA12: VARCHAR(5) | AB12: 브랜드코드 | AC12: Brand Code.
B13: 6 | I13: 6 | Z13: BRND_DTL_CD | AA13: VARCHAR(6) | AB13: 브랜드상세코드 | AC13: Brand Detail Code.
B14: 7 | I14: 7 | Z14: RPRS_PRD_CD | AA14: VARCHAR(12) | AB14: 대표상품코드 | AC14: Representative Product Code.
B15: 8 | I15: 8 | Z15: RPRS_PRD_NM | AA15: VARCHAR(100) | AB15: 대표상품명 | AC15: Product Name.
B16: 9 | I16: 9 | Z16: RPRS_PRD_ENGL_NM | AA16: VARCHAR(100) | AB16: 대표상품영어명 | AC16: Representative Product English Name.
B17: 10 | I17: 10 | Z17: RPLC_PRD_CD | AA17: VARCHAR(12) | AB17: 대체상품코드 | AC17: Alternative Product Code.
B18: 11 | I18: 11 | Z18: PRD_MKT_CAT_CD | AA18: VARCHAR(2) | AB18: 상품마케팅분류코드 | AC18: Product Marketing Classification Code.
B19: 12 | I19: 12 | Z19: SET_PRD_YN | AA19: VARCHAR(1) | AB19: 세트상품여부 | AC19: Set product or not.
B20: 13 | I20: 13 | Z20: SET_DSMN_YN | AA20: VARCHAR(1) | AB20: 세트해체여부 | AC20: Set disassembly.
B21: 14 | I21: 14 | Z21: CNSM_UTPR_AMT | AA21: NUMBER(20,3) | AB21: 소비자단가금액 | AC21: Consumer Unit Price.
B22: 15 | I22: 15 | Z22: PRD_CPT | AA22: NUMBER(38,0) | AB22: 상품용량 | AC22: Product Capacity.
B23: 16 | I23: 16 | Z23: PRD_CPT_UNIT_CD | AA23: VARCHAR(3) | AB23: 상품용량단위코드 | AC23: Product Unit Code.
... B38: 31 | I38: 31 | Z38: BRND_LN_CD | AA38: VARCHAR(4) | AB38: 브랜드라인코드 | AC38: Brand Line Code.
Z39: MFG_PLNT_CD | AA39: VARCHAR(4) | AB39: 생산플랜트코드 | AC39: Production Plant Code.
Z40: NITM_APLY_YN | AA40: VARCHAR(1) | AB40: 품목수적용여부 | AC40: Item Application.
B41: 변환규칙정의 | Z41: FST_MFG_DT | AA41: VARCHAR(10) | AB41: 최초생산일자 | AC41: Initial Production Date.
B42: 변환규칙 | D42: 내용 | Z42: LST_MFG_DT | AA42: VARCHAR(10) | AB42: 최종생산일자 | AC42: Final production date.
B43: R1 | Z43: PRD_BRCD_CD | AA43: VARCHAR(15) | AB43: 상품바코드코드 | AC43: Product barcode code.
B44: R2 | Z44: REG_APPL_CL_CD | AA44: VARCHAR(10) | AB44: 등록어플리케이션구분코드 | AC44: Registration Application Type Code.
Z45: CP_PRD_YN | AA45: VARCHAR(1) | AB45: 자사상품여부 | AC45: Is it a company product?.
B46: 기타정보 | Z46: INSD_MGNT_AMT | AA46: NUMBER(20,3) | AB46: 내부관리금액 | AC46: Internal Management Amount.
B47: 이벤트 발생조건 (DB Trigger) | Z47: WKPL_CL_CD | AA47: VARCHAR(10) | AB47: 사업장구분코드 | AC47: Business Site Classification Code.
B48: 연계데이터 추출조건 | Z48: ASRC_PRD_MKT_CAT_CD | AA48: VARCHAR(2) | AB48: 소스상품마케팅분류코드 | AC48: Source Product Marketing Classification Code.
B49: 데이터 반영방법 | Z49: ASRC_PRD_CAT_CD | AA49: VARCHAR(10) | AB49: 소스상품분류코드 | AC49: Source Product Classification Code.
B50: 기타 | Z50: PRD_TP_CD | AA50: VARCHAR(4) | AB50: 상품유형코드 | AC50: Product Type Code.

Sheet SKU_IN일정
A1: Top
B2: 매핑정의서 - SKU In 일정 SKU In schedule | J2: Source System | K2: NPD | O2: 문서작성일 | P2: 2025.09.25
J3: Target System | K3: APLAN | O3: 버전 | P3: 0.1
B4: 매핑정의
B5: Source Table : ? | I5: Target Table : ? | R5: Set Value | S5: 변환규칙 | Z5: CDP 자재 마스터 테이블 명세서 (D_PRD_MSTR)
B6: RFC | I6: Web SVC | J6: PreProd : https://myamorepacificpreprod.o9solutions.com/ Prod : https://myamorepacific.o9solutions.com/
B7: SEQ | C7: Field | D7: PK | E7: Type | F7: Size | G7: Desc | H7: Desc(ENG) | I7: SEQ | J7: Field | K7: PK | L7: Type | M7: Size | N7: Desc | O7: Desc(ENG) | P7: Req No | Q7: Res No | Z7: 컬럼명 | AA7: 데이터타입 | AB7: 한글명 | AC7: 영문명
B8: 1 | C8: I_TERMS_F | D8: Y | E8: CHAR | F8: 8 | G8: 시작일 FROM | H8: From Date | I8: 1 | J8: From_date | K8: Y | L8: NVARCHAR | M8: 1000 | N8: From Date | O8: From Date | Z8: PRD_CD | AA8: VARCHAR(12) | AB8: 상품코드 | AC8: Product Code.
B9: 2 | C9: I_TERMS_T | D9: Y | E9: CHAR | F9: 8 | G9: 종료일 TO | H9: To Date | I9: 2 | J9: To_date | K9: Y | L9: NVARCHAR | M9: 1000 | N9: To Date | O9: To Date | Z9: PRD_NM | AA9: VARCHAR(100) | AB9: 상품명 | AC9: Product Name.
B10: 3 | C10: MATNR | D10: Y | E10: CHAR | F10: 18 | G10: 제품코드 | H10: Product code | I10: 3 | J10: Item | K10: Y | L10: NVARCHAR | M10: 1000 | N10: 자재 코드 | O10: Product code | Z10: PRD_ENGL_NM | AA10: VARCHAR(200) | AB10: 상품영어명 | AC10: Product English Name.
B11: 4 | C11: ZZMANFT | D11: Y | E11: CHAR | F11: 4 | G11: 플랜트코드 | H11: Plant code | I11: 4 | J11: Plant | K11: Y | L11: NVARCHAR | M11: 1000 | N11: 생산 플랜트 | O11: Plant code | Z11: ENGL_PRD_NM | AA11: VARCHAR(100) | AB11: 영어상품명(비표준) | AC11: English Product Name (Non-Standard).
B12: 5 | C12: YYMM | E12: CHAR | F12: 6 | G12: 생산회의년월( ex: 201709 ) | H12: Production Meeting Month | I12: 5 | J12: MeetingMonth | L12: NVARCHAR | M12: 1000 | N12: 생산회의 상정 월 | O12: Production Meeting Month | Z12: BRND_CD | AA12: VARCHAR(5) | AB12: 브랜드코드 | AC12: Brand Code.
B13: 6 | C13: DEGREE | E13: CHAR | F13: 1 | G13: 주차(1,2,3,4) | H13: Production Meeting Week | I13: 6 | J13: MeetingWeek | L13: NVARCHAR | M13: 1000 | N13: 생산회의 상정 주차 | O13: Production Meeting Week | Z13: BRND_DTL_CD | AA13: VARCHAR(6) | AB13: 브랜드상세코드 | AC13: Brand Detail Code.
B14: 7 | C14: PKGSDT | E14: CHAR | F14: 6 | G14: 실포장일시작주차 | H14: Packaging Start Date | I14: 7 | J14: ProdInitDate | L14: NVARCHAR | M14: 1000 | N14: 실포장일 시작 일자 | O14: Packaging Start Date | Z14: RPRS_PRD_CD | AA14: VARCHAR(12) | AB14: 대표상품코드 | AC14: Representative Product Code.
B15: 8 | C15: ACTPRD | E15: QUAN | F15: 13 | G15: 실초도량 | H15: Treadmill | I15: 8 | J15: InitQty | L15: NVARCHAR | M15: 1000 | N15: 초도 생산량 | O15: Treadmill | Z15: RPRS_PRD_NM | AA15: VARCHAR(100) | AB15: 대표상품명 | AC15: Product Name.
B16: 9 | C16: PRDPLN | E16: CHAR | F16: 1 | G16: 생산 계획 반영 여부 (R:반영, D:삭제, P:이월, M:보류2, N:보류3, O:보류4) | H16: Reflecting production plan (R:reflect, D:delete, P:over, M:hold 2, N:hold 3, O:hold 4) | I16: 9 | J16: POFlag | L16: NVARCHAR | M16: 1000 | N16: 생산계획반영여부(R:반영, D:삭제, P:이월, M:보류2, N:보류3, O:보류4) | O16: Reflecting production plan (R:reflect, D:delete, P:over, M:hold 2, N:hold 3, O:hold 4) | Z16: RPRS_PRD_ENGL_NM | AA16: VARCHAR(100) | AB16: 대표상품영어명 | AC16: Representative Product English Name.
B17: 10 | C17: CFRDT | E17: CHAR | F17: 8 | G17: 생산회의일자 | H17: Production meeting date | I17: 10 | J17: MeetingDate | L17: NVARCHAR | M17: 1000 | N17: 생산회의일자 | O17: Production meeting date | Z17: RPLC_PRD_CD | AA17: VARCHAR(12) | AB17: 대체상품코드 | AC17: Alternative Product Code.
B18: 11 | I18: 11 | Z18: PRD_MKT_CAT_CD | AA18: VARCHAR(2) | AB18: 상품마케팅분류코드 | AC18: Product Marketing Classification Code.
B19: 12 | I19: 12 | Z19: SET_PRD_YN | AA19: VARCHAR(1) | AB19: 세트상품여부 | AC19: Set product or not.
B20: 13 | I20: 13 | Z20: SET_DSMN_YN | AA20: VARCHAR(1) | AB20: 세트해체여부 | AC20: Set disassembly.
B21: 14 | I21: 14 | Z21: CNSM_UTPR_AMT | AA21: NUMBER(20,3) | AB21: 소비자단가금액 | AC21: Consumer Unit Price.
B22: 15 | I22: 15 | Z22: PRD_CPT | AA22: NUMBER(38,0) | AB22: 상품용량 | AC22: Product Capacity.
B23: 16 | I23: 16 | Z23: PRD_CPT_UNIT_CD | AA23: VARCHAR(3) | AB23: 상품용량단위코드 | AC23: Product Unit Code.
B24: 17 | I24: 17 | Z24: PRD_USE_CD | AA24: VARCHAR(3) | AB24: 상품용도코드 | AC24: Product Use Code.
B25: 18 | I25: 18 | Z25: PRD_CAT_CD | AA25: VARCHAR(10) | AB25: 상품분류코드 | AC25: Product Classification Code.
B26: 19 | I26: 19 | Z26: MAIN_FUNC_CD | AA26: VARCHAR(4) | AB26: 주요기능코드 | AC26: Main Function Code.
B27: 20 | I27: 20 | Z27: USER_TP_CD | AA27: VARCHAR(1) | AB27: 사용자유형코드 | AC27: User Type Code.
B28: 21 | I28: 21 | Z28: FRSH_CSMT_YN | AA28: VARCHAR(1) | AB28: 신선화장품여부 | AC28: Fresh Cosmetics.
B29: 22 | I29: 22 | Z29: PRD_CL_CD | AA29: VARCHAR(2) | AB29: 상품구분코드 | AC29: Product Classification Code.
... B38: 31 | I38: 31 | Z38: BRND_LN_CD | AA38: VARCHAR(4) | AB38: 브랜드라인코드 | AC38: Brand Line Code.
Z39: MFG_PLNT_CD | AA39: VARCHAR(4) | AB39: 생산플랜트코드 | AC39: Production Plant Code.
Z40: NITM_APLY_YN | AA40: VARCHAR(1) | AB40: 품목수적용여부 | AC40: Item Application.
B41: 변환규칙정의 | Z41: FST_MFG_DT | AA41: VARCHAR(10) | AB41: 최초생산일자 | AC41: Initial Production Date.
B42: 변환규칙 | D42: 내용 | Z42: LST_MFG_DT | AA42: VARCHAR(10) | AB42: 최종생산일자 | AC42: Final production date.
B43: R1 | Z43: PRD_BRCD_CD | AA43: VARCHAR(15) | AB43: 상품바코드코드 | AC43: Product barcode code.
B44: R2 | Z44: REG_APPL_CL_CD | AA44: VARCHAR(10) | AB44: 등록어플리케이션구분코드 | AC44: Registration Application Type Code.
Z45: CP_PRD_YN | AA45: VARCHAR(1) | AB45: 자사상품여부 | AC45: Is it a company product?.
B46: 기타정보 | Z46: INSD_MGNT_AMT | AA46: NUMBER(20,3) | AB46: 내부관리금액 | AC46: Internal Management Amount.
B47: 이벤트 발생조건 (DB Trigger) | Z47: WKPL_CL_CD | AA47: VARCHAR(10) | AB47: 사업장구분코드 | AC47: Business Site Classification Code.
B48: 연계데이터 추출조건 | Z48: ASRC_PRD_MKT_CAT_CD | AA48: VARCHAR(2) | AB48: 소스상품마케팅분류코드 | AC48: Source Product Marketing Classification Code.
B49: 데이터 반영방법 | Z49: ASRC_PRD_CAT_CD | AA49: VARCHAR(10) | AB49: 소스상품분류코드 | AC49: Source Product Classification Code.
B50: 기타 | Z50: PRD_TP_CD | AA50: VARCHAR(4) | AB50: 상품유형코드 | AC50: Product Type Code.

Sheet 자재대체단위
A1: Top
B2: 매핑정의서 - 자재대체단위 | J2: Source System | K2: SAP | O2: 문서작성일 | P2: 2025.09.25
J3: Target System | K3: APLAN | O3: 버전 | P3: 0.1
B4: 매핑정의
B5: Source Table : ? | I5: Target Table : ? | R5: Set Value | S5: 변환규칙 | Z5: CDP 자재 마스터 테이블 명세서 (D_PRD_MSTR)
B6: RFC | C6: ZPP_IF_MAT_ALTUNIT_SEND_BM_SP | I6: Web SVC | J6: PreProd : https://myamorepacificpreprod.o9solutions.com/ Prod : https://myamorepacific.o9solutions.com/
B7: SEQ | C7: Field | D7: PK | E7: Type | F7: Size | G7: Desc | H7: Desc(ENG) | I7: SEQ | J7: Field | K7: PK | L7: Type | M7: Size | N7: Desc | O7: Desc(ENG) | P7: Req No | Q7: Res No | Z7: 컬럼명 | AA7: 데이터타입 | AB7: 한글명 | AC7: 영문명
B8: 1 | C8: MATNR | D8: Y | E8: CHAR | F8: 18 | G8: 자재코드 | H8: Material code | I8: 1 | J8: Item | K8: Y | L8: nvarchar | M8: 1000 | N8: 자재코드 | O8: Material code | Z8: PRD_CD | AA8: VARCHAR(12) | AB8: 상품코드 | AC8: Product Code.
B9: 2 | C9: MEINH | D9: Y | E9: UNIT | F9: 3 | G9: 재고유지단위의 대체단위 | H9: Alternative unit | I9: 2 | J9: ReplaceMeasure | K9: Y | L9: nvarchar | M9: 1000 | N9: 재고유지단위의 대체단위 | O9: Alternative unit | Z9: PRD_NM | AA9: VARCHAR(100) | AB9: 상품명 | AC9: Product Name.
B10: 3 | C10: UMREZ | E10: DEC | F10: 5 | G10: 기본 단위로의 환산을 위한 분자 | H10: Molecule for conversion to basic units | I10: 3 | J10: Numerator | L10: nvarchar | M10: 1000 | N10: 기본 단위로의 환산을 위한 분자 | O10: Molecule for conversion to basic units | Z10: PRD_ENGL_NM | AA10: VARCHAR(200) | AB10: 상품영어명 | AC10: Product English Name.
B11: 4 | C11: UMREN | E11: DEC | F11: 5 | G11: 기본 단위로 환산하는데 사용하는 분모 | H11: Denominator | I11: 4 | J11: Denominator | L11: nvarchar | M11: 1000 | N11: 기본 단위로 환산하는데 사용하는 분모 | O11: Denominator | Z11: ENGL_PRD_NM | AA11: VARCHAR(100) | AB11: 영어상품명(비표준) | AC11: English Product Name (Non-Standard).
B12: 5 | I12: 5 | Z12: BRND_CD | AA12: VARCHAR(5) | AB12: 브랜드코드 | AC12: Brand Code.
B13: 6 | I13: 6 | Z13: BRND_DTL_CD | AA13: VARCHAR(6) | AB13: 브랜드상세코드 | AC13: Brand Detail Code.
B14: 7 | I14: 7 | Z14: RPRS_PRD_CD | AA14: VARCHAR(12) | AB14: 대표상품코드 | AC14: Representative Product Code.
B15: 8 | I15: 8 | Z15: RPRS_PRD_NM | AA15: VARCHAR(100) | AB15: 대표상품명 | AC15: Product Name.
B16: 9 | I16: 9 | Z16: RPRS_PRD_ENGL_NM | AA16: VARCHAR(100) | AB16: 대표상품영어명 | AC16: Representative Product English Name.
B17: 10 | I17: 10 | Z17: RPLC_PRD_CD | AA17: VARCHAR(12) | AB17: 대체상품코드 | AC17: Alternative Product Code.
B18: 11 | I18: 11 | Z18: PRD_MKT_CAT_CD | AA18: VARCHAR(2) | AB18: 상품마케팅분류코드 | AC18: Product Marketing Classification Code.
B19: 12 | I19: 12 | Z19: SET_PRD_YN | AA19: VARCHAR(1) | AB19: 세트상품여부 | AC19: Set product or not.
B20: 13 | I20: 13 | Z20: SET_DSMN_YN | AA20: VARCHAR(1) | AB20: 세트해체여부 | AC20: Set disassembly.
B21: 14 | I21: 14 | Z21: CNSM_UTPR_AMT | AA21: NUMBER(20,3) | AB21: 소비자단가금액 | AC21: Consumer Unit Price.
B22: 15 | I22: 15 | Z22: PRD_CPT | AA22: NUMBER(38,0) | AB22: 상품용량 | AC22: Product Capacity.
B23: 16 | I23: 16 | Z23: PRD_CPT_UNIT_CD | AA23: VARCHAR(3) | AB23: 상품용량단위코드 | AC23: Product Unit Code.
... B38: 31 | I38: 31 | Z38: BRND_LN_CD | AA38: VARCHAR(4) | AB38: 브랜드라인코드 | AC38: Brand Line Code.
Z39: MFG_PLNT_CD | AA39: VARCHAR(4) | AB39: 생산플랜트코드 | AC39: Production Plant Code.
Z40: NITM_APLY_YN | AA40: VARCHAR(1) | AB40: 품목수적용여부 | AC40: Item Application.
B41: 변환규칙정의 | Z41: FST_MFG_DT | AA41: VARCHAR(10) | AB41: 최초생산일자 | AC41: Initial Production Date.
B42: 변환규칙 | D42: 내용 | Z42: LST_MFG_DT | AA42: VARCHAR(10) | AB42: 최종생산일자 | AC42: Final production date.
B43: R1 | Z43: PRD_BRCD_CD | AA43: VARCHAR(15) | AB43: 상품바코드코드 | AC43: Product barcode code.
B44: R2 | Z44: REG_APPL_CL_CD | AA44: VARCHAR(10) | AB44: 등록어플리케이션구분코드 | AC44: Registration Application Type Code.
Z45: CP_PRD_YN | AA45: VARCHAR(1) | AB45: 자사상품여부 | AC45: Is it a company product?.
B46: 기타정보 | Z46: INSD_MGNT_AMT | AA46: NUMBER(20,3) | AB46: 내부관리금액 | AC46: Internal Management Amount.
B47: 이벤트 발생조건 (DB Trigger) | Z47: WKPL_CL_CD | AA47: VARCHAR(10) | AB47: 사업장구분코드 | AC47: Business Site Classification Code.
B48: 연계데이터 추출조건 | Z48: ASRC_PRD_MKT_CAT_CD | AA48: VARCHAR(2) | AB48: 소스상품마케팅분류코드 | AC48: Source Product Marketing Classification Code.
B49: 데이터 반영방법 | Z49: ASRC_PRD_CAT_CD | AA49: VARCHAR(10) | AB49: 소스상품분류코드 | AC49: Source Product Classification Code.
B50: 기타 | Z50: PRD_TP_CD | AA50: VARCHAR(4) | AB50: 상품유형코드 | AC50: Product Type Code.

Sheet 재고
A1: Top
B2: 매핑정의서 - 재고 | J2: Source System | K2: BW | O2: 문서작성일 | P2: 2025.09.25
J3: Target System | K3: APLAN | O3: 버전 | P3: 0.1
B4: 매핑정의
B5: Source Table : ? | I5: Target Table : ? | R5: Set Value | S5: 변환규칙 | Z5: CDP 자재 마스터 테이블 명세서 (D_PRD_MSTR)
B6: RFC | I6: Web SVC | J6: PreProd : https://myamorepacificpreprod.o9solutions.com/ Prod : https://myamorepacific.o9solutions.com/
B7: SEQ | C7: Field | D7: PK | E7: Type | F7: Size | G7: Desc | H7: Desc(ENG) | I7: SEQ | J7: Field | K7: PK | L7: Type | M7: Size | N7: Desc | O7: Desc(ENG) | P7: Req No | Q7: Res No | Z7: 컬럼명 | AA7: 데이터타입 | AB7: 한글명 | AC7: 영문명
B8: 1 | C8: BUKRS | D8: Y | F8: 4 | I8: 1 | J8: Company | L8: NVARCHAR | M8: 1000 | N8: 회사코드 | O8: Company code | Z8: PRD_CD | AA8: VARCHAR(12) | AB8: 상품코드 | AC8: Product Code.
B9: 2 | C9: DATUM | D9: Y | F9: 8 | I9: 2 | J9: Date | L9: NVARCHAR | M9: 1000 | N9: 일자 | O9: Date | Z9: PRD_NM | AA9: VARCHAR(100) | AB9: 상품명 | AC9: Product Name.
B10: 3 | C10: MATNR | D10: Y | F10: 18 | I10: 3 | J10: Item | L10: NVARCHAR | M10: 1000 | N10: 자재 | O10: material | Z10: PRD_ENGL_NM | AA10: VARCHAR(200) | AB10: 상품영어명 | AC10: Product English Name.
B11: 4 | C11: WERKS | D11: Y | F11: 4 | I11: 4 | J11: Plant | L11: NVARCHAR | M11: 1000 | N11: 플랜트 | O11: plant | Z11: ENGL_PRD_NM | AA11: VARCHAR(100) | AB11: 영어상품명(비표준) | AC11: English Product Name (Non-Standard).
B12: 5 | C12: LGORT | D12: Y | F12: 4 | I12: 5 | J12: SL | L12: NVARCHAR | M12: 1000 | N12: 저장위치 | O12: Storage location | Z12: BRND_CD | AA12: VARCHAR(5) | AB12: 브랜드코드 | AC12: Brand Code.
B13: 6 | C13: MEINS | I13: 6 | J13: UOM | L13: NVARCHAR | M13: 1000 | N13: 단위 | O13: unit | Z13: BRND_DTL_CD | AA13: VARCHAR(6) | AB13: 브랜드상세코드 | AC13: Brand Detail Code.
B14: 7 | C14: LABST | I14: 7 | J14: AvailQty | L14: NVARCHAR | M14: 1000 | N14: 가용재고 | O14: Available inventory | Z14: RPRS_PRD_CD | AA14: VARCHAR(12) | AB14: 대표상품코드 | AC14: Representative Product Code.
B15: 8 | C15: ZRESTO | I15: 8 | J15: STOInQty | L15: NVARCHAR | M15: 1000 | N15: STO입고예정 | O15: STO will be in stock | Z15: RPRS_PRD_NM | AA15: VARCHAR(100) | AB15: 대표상품명 | AC15: Product Name.
B16: 9 | C16: ZRERES | I16: 9 | J16: ReserveInQty | L16: NVARCHAR | M16: 1000 | N16: 예약입고예정 | O16: Scheduled reservation | Z16: RPRS_PRD_ENGL_NM | AA16: VARCHAR(100) | AB16: 대표상품영어명 | AC16: Representative Product English Name.
B17: 10 | C17: ZRETUR | I17: 10 | J17: ReturnQty | L17: NVARCHAR | M17: 1000 | N17: 반품입고예정 | O17: Scheduled to be in stock | Z17: RPLC_PRD_CD | AA17: VARCHAR(12) | AB17: 대체상품코드 | AC17: Alternative Product Code.
B18: 11 | C18: KULAB | I18: 11 | J18: CustomerQty | L18: NVARCHAR | M18: 1000 | N18: 고객위탁재고 | O18: Customer Consignment High School | Z18: PRD_MKT_CAT_CD | AA18: VARCHAR(2) | AB18: 상품마케팅분류코드 | AC18: Product Marketing Classification Code.
B19: 12 | C19: INSME | I19: 12 | J19: QMQty | L19: NVARCHAR | M19: 1000 | N19: 품질재고 | O19: Quality inventory | Z19: SET_PRD_YN | AA19: VARCHAR(1) | AB19: 세트상품여부 | AC19: Set product or not.
B20: 13 | C20: ZISSTO | I20: 13 | J20: STOOutQty | L20: NVARCHAR | M20: 1000 | N20: STO출고예정 | O20: STO shipping scheduled | Z20: SET_DSMN_YN | AA20: VARCHAR(1) | AB20: 세트해체여부 | AC20: Set disassembly.
B21: 14 | C21: ZISRES | I21: 14 | J21: ReserveOutQty | L21: NVARCHAR | M21: 1000 | N21: 예약출고예정 | O21: Scheduled to be reserved | Z21: CNSM_UTPR_AMT | AA21: NUMBER(20,3) | AB21: 소비자단가금액 | AC21: Consumer Unit Price.
B22: 15 | C22: ZISALE | I22: 15 | J22: SOOutQty | L22: NVARCHAR | M22: 1000 | N22: SO출고예정 | O22: SO shipped | Z22: PRD_CPT | AA22: NUMBER(38,0) | AB22: 상품용량 | AC22: Product Capacity.
B23: 16 | I23: 16 | Z23: PRD_CPT_UNIT_CD | AA23: VARCHAR(3) | AB23: 상품용량단위코드 | AC23: Product Unit Code.
B24: 17 | I24: 17 | Z24: PRD_USE_CD | AA24: VARCHAR(3) | AB24: 상품용도코드 | AC24: Product Use Code.
B25: 18 | I25: 18 | Z25: PRD_CAT_CD | AA25: VARCHAR(10) | AB25: 상품분류코드 | AC25: Product Classification Code.
B26: 19 | I26: 19 | Z26: MAIN_FUNC_CD | AA26: VARCHAR(4) | AB26: 주요기능코드 | AC26: Main Function Code.
B27: 20 | I27: 20 | Z27: USER_TP_CD | AA27: VARCHAR(1) | AB27: 사용자유형코드 | AC27: User Type Code.
B28: 21 | I28: 21 | Z28: FRSH_CSMT_YN | AA28: VARCHAR(1) | AB28: 신선화장품여부 | AC28: Fresh Cosmetics.
B29: 22 | I29: 22 | Z29: PRD_CL_CD | AA29: VARCHAR(2) | AB29: 상품구분코드 | AC29: Product Classification Code.
B30: 23 | I30: 23 | Z30: SLS_TP_CD | AA30: VARCHAR(3) | AB30: 영업유형코드 | AC30: Sales Type Code.
B31: 24 | I31: 24 | Z31: SAP_PRD_LN_CD | AA31: VARCHAR(4) | AB31: SAP상품라인코드 | AC31: SAP Product Line Code.
B32: 25 | I32: 25 | Z32: PRD_CLR_CD | AA32: VARCHAR(4) | AB32: 상품색상코드 | AC32: Product Color Code.
B33: 26 | I33: 26 | Z33: NEW_PRD_CL_CD | AA33: VARCHAR(3) | AB33: 신상품구분코드 | AC33: New Product Code.
B34: 27 | I34: 27 | Z34: STRO_PRD_YN | AA34: VARCHAR(1) | AB34: 강한상품여부 | AC34: Strong product or not.
... B38: 31 | I38: 31 | Z38: BRND_LN_CD | AA38: VARCHAR(4) | AB38: 브랜드라인코드 | AC38: Brand Line Code.
Z39: MFG_PLNT_CD | AA39: VARCHAR(4) | AB39: 생산플랜트코드 | AC39: Production Plant Code.
Z40: NITM_APLY_YN | AA40: VARCHAR(1) | AB40: 품목수적용여부 | AC40: Item Application.
B41: 변환규칙정의 | Z41: FST_MFG_DT | AA41: VARCHAR(10) | AB41: 최초생산일자 | AC41: Initial Production Date.
B42: 변환규칙 | D42: 내용 | Z42: LST_MFG_DT | AA42: VARCHAR(10) | AB42: 최종생산일자 | AC42: Final production date.
B43: R1 | Z43: PRD_BRCD_CD | AA43: VARCHAR(15) | AB43: 상품바코드코드 | AC43: Product barcode code.
B44: R2 | Z44: REG_APPL_CL_CD | AA44: VARCHAR(10) | AB44: 등록어플리케이션구분코드 | AC44: Registration Application Type Code.
Z45: CP_PRD_YN | AA45: VARCHAR(1) | AB45: 자사상품여부 | AC45: Is it a company product?.
B46: 기타정보 | Z46: INSD_MGNT_AMT | AA46: NUMBER(20,3) | AB46: 내부관리금액 | AC46: Internal Management Amount.
B47: 이벤트 발생조건 (DB Trigger) | Z47: WKPL_CL_CD | AA47: VARCHAR(10) | AB47: 사업장구분코드 | AC47: Business Site Classification Code.
B48: 연계데이터 추출조건 | Z48: ASRC_PRD_MKT_CAT_CD | AA48: VARCHAR(2) | AB48: 소스상품마케팅분류코드 | AC48: Source Product Marketing Classification Code.
B49: 데이터 반영방법 | Z49: ASRC_PRD_CAT_CD | AA49: VARCHAR(10) | AB49: 소스상품분류코드 | AC49: Source Product Classification Code.
B50: 기타 | Z50: PRD_TP_CD | AA50: VARCHAR(4) | AB50: 상품유형코드 | AC50: Product Type Code.

Sheet 자재원가
A1: Top
B2: 매핑정의서 - 자재 원가 | J2: Source System | K2: SAP | O2: 문서작성일 | P2: 2025.09.25
J3: Target System | K3: APLAN | O3: 버전 | P3: 0.1
B4: 매핑정의
B5: Source Table : ? | I5: Target Table : ? | R5: Set Value | S5: 변환규칙 | Z5: CDP 자재 마스터 테이블 명세서 (D_PRD_MSTR)
B6: RFC | C6: ZPP_IF_STD_PRICE_SEND_BM_SP | I6: Web SVC | J6: PreProd : https://myamorepacificpreprod.o9solutions.com/ Prod : https://myamorepacific.o9solutions.com/
B7: SEQ | C7: Field | D7: PK | E7: Type | F7: Size | G7: Desc | H7: Desc(ENG) | I7: SEQ | J7: Field | K7: PK | L7: Type | M7: Size | N7: Desc | O7: Desc(ENG) | P7: Req No | Q7: Res No | Z7: 컬럼명 | AA7: 데이터타입 | AB7: 한글명 | AC7: 영문명
B8: 1 | C8: MATNR | D8: Y | E8: CHAR | F8: 18 | G8: 자재코드 | H8: Material code | I8: 1 | J8: Item | K8: Y | L8: NVARCHAR | M8: 1000 | N8: 자재코드 | O8: Material code | Z8: PRD_CD | AA8: VARCHAR(12) | AB8: 상품코드 | AC8: Product Code.
B9: 2 | C9: WERKS | D9: Y | E9: CHAR | F9: 4 | G9: 플랜트 | H9: plant | I9: 2 | J9: Plant | K9: Y | L9: NVARCHAR | M9: 1000 | N9: 플랜트 | O9: plant | Z9: PRD_NM | AA9: VARCHAR(100) | AB9: 상품명 | AC9: Product Name.
B10: 3 | C10: PREIS | E10: CURR | F10: 11.2 | G10: 가격 | H10: price | I10: 3 | J10: Price | L10: NVARCHAR | M10: 1000 | N10: 가격 | O10: price | Z10: PRD_ENGL_NM | AA10: VARCHAR(200) | AB10: 상품영어명 | AC10: Product English Name.
B11: 4 | C11: WAERS | D11: Y | E11: CUKY | F11: 5 | G11: 통화키 | H11: Call key | I11: 4 | J11: CurrencyKey | K11: Y | L11: NVARCHAR | M11: 1000 | N11: 통화키 | O11: Call key | Z11: ENGL_PRD_NM | AA11: VARCHAR(100) | AB11: 영어상품명(비표준) | AC11: English Product Name (Non-Standard).
B12: 5 | C12: PEINH | E12: DEC | F12: 5 | G12: 가격단위 | H12: Price unit | I12: 5 | J12: PRICE_UNIT_QTY | L12: NVARCHAR | M12: 1000 | N12: 가격단위 | O12: Price unit | Z12: BRND_CD | AA12: VARCHAR(5) | AB12: 브랜드코드 | AC12: Brand Code.
B13: 6 | C13: VPRSV | E13: CHAR | F13: 1 | G13: 가격관리 지시자(S:표준가, V:이동평균가) | H13: Price management indicator (S: Standard price, V: average mobile price) | I13: 6 | J13: PriceType | L13: NVARCHAR | M13: 1000 | N13: 가격관리 지시자(S:표준가, V:이동평균가) | O13: Price management indicator (S: Standard price, V: average mobile price) | Z13: BRND_DTL_CD | AA13: VARCHAR(6) | AB13: 브랜드상세코드 | AC13: Brand Detail Code.
B14: 7 | I14: 7 | Z14: RPRS_PRD_CD | AA14: VARCHAR(12) | AB14: 대표상품코드 | AC14: Representative Product Code.
B15: 8 | I15: 8 | Z15: RPRS_PRD_NM | AA15: VARCHAR(100) | AB15: 대표상품명 | AC15: Product Name.
B16: 9 | I16: 9 | Z16: RPRS_PRD_ENGL_NM | AA16: VARCHAR(100) | AB16: 대표상품영어명 | AC16: Representative Product English Name.
B17: 10 | I17: 10 | Z17: RPLC_PRD_CD | AA17: VARCHAR(12) | AB17: 대체상품코드 | AC17: Alternative Product Code.
B18: 11 | I18: 11 | Z18: PRD_MKT_CAT_CD | AA18: VARCHAR(2) | AB18: 상품마케팅분류코드 | AC18: Product Marketing Classification Code.
B19: 12 | I19: 12 | Z19: SET_PRD_YN | AA19: VARCHAR(1) | AB19: 세트상품여부 | AC19: Set product or not.
B20: 13 | I20: 13 | Z20: SET_DSMN_YN | AA20: VARCHAR(1) | AB20: 세트해체여부 | AC20: Set disassembly.
B21: 14 | I21: 14 | Z21: CNSM_UTPR_AMT | AA21: NUMBER(20,3) | AB21: 소비자단가금액 | AC21: Consumer Unit Price.
B22: 15 | I22: 15 | Z22: PRD_CPT | AA22: NUMBER(38,0) | AB22: 상품용량 | AC22: Product Capacity.
B23: 16 | I23: 16 | Z23: PRD_CPT_UNIT_CD | AA23: VARCHAR(3) | AB23: 상품용량단위코드 | AC23: Product Unit Code.
B24: 17 | I24: 17 | Z24: PRD_USE_CD | AA24: VARCHAR(3) | AB24: 상품용도코드 | AC24: Product Use Code.
B25: 18 | I25: 18 | Z25: PRD_CAT_CD | AA25: VARCHAR(10) | AB25: 상품분류코드 | AC25: Product Classification Code.
... B38: 31 | I38: 31 | Z38: BRND_LN_CD | AA38: VARCHAR(4) | AB38: 브랜드라인코드 | AC38: Brand Line Code.
Z39: MFG_PLNT_CD | AA39: VARCHAR(4) | AB39: 생산플랜트코드 | AC39: Production Plant Code.
Z40: NITM_APLY_YN | AA40: VARCHAR(1) | AB40: 품목수적용여부 | AC40: Item Application.
B41: 변환규칙정의 | Z41: FST_MFG_DT | AA41: VARCHAR(10) | AB41: 최초생산일자 | AC41: Initial Production Date.
B42: 변환규칙 | D42: 내용 | Z42: LST_MFG_DT | AA42: VARCHAR(10) | AB42: 최종생산일자 | AC42: Final production date.
B43: R1 | Z43: PRD_BRCD_CD | AA43: VARCHAR(15) | AB43: 상품바코드코드 | AC43: Product barcode code.
B44: R2 | Z44: REG_APPL_CL_CD | AA44: VARCHAR(10) | AB44: 등록어플리케이션구분코드 | AC44: Registration Application Type Code.
Z45: CP_PRD_YN | AA45: VARCHAR(1) | AB45: 자사상품여부 | AC45: Is it a company product?.
B46: 기타정보 | Z46: INSD_MGNT_AMT | AA46: NUMBER(20,3) | AB46: 내부관리금액 | AC46: Internal Management Amount.
B47: 이벤트 발생조건 (DB Trigger) | Z47: WKPL_CL_CD | AA47: VARCHAR(10) | AB47: 사업장구분코드 | AC47: Business Site Classification Code.
B48: 연계데이터 추출조건 | Z48: ASRC_PRD_MKT_CAT_CD | AA48: VARCHAR(2) | AB48: 소스상품마케팅분류코드 | AC48: Source Product Marketing Classification Code.
B49: 데이터 반영방법 | Z49: ASRC_PRD_CAT_CD | AA49: VARCHAR(10) | AB49: 소스상품분류코드 | AC49: Source Product Classification Code.
B50: 기타 | Z50: PRD_TP_CD | AA50: VARCHAR(4) | AB50: 상품유형코드 | AC50: Product Type Code.

Sheet 거래처
A1: Top
B2: 매핑정의서 - 거래처마스터 | J2: Source System | K2: SAP | O2: 문서작성일 | P2: 2025.09.25
J3: Target System | K3: APLAN | O3: 버전 | P3: 0.1
B4: 매핑정의
B5: Source Table : ? | I5: Target Table : ALIFCI_PRTN_MSTR | R5: Set Value | S5: 변환규칙
B6: RFC | C6: ZSD_SEND_CUSTOMER_01 | I6: Web SVC | J6: PreProd : https://myamorepacificpreprod.o9solutions.com/ Prod : https://myamorepacific.o9solutions.com/
B7: SEQ | C7: Field | D7: PK | E7: Type | F7: Size | G7: Desc | H7: Desc(ENG) | I7: SEQ | J7: Field | K7: PK | L7: Type | M7: Size | N7: Desc | O7: Desc(ENG) | P7: Req No | Q7: Res No
B8: 1 | C8: I_LEGACY | E8: CHAR | F8: 5 | G8: LEGACY SYSTEM 명 | H8: Legacy System Name | I8: 1
B9: 2 | C9: KTOKD | E9: CHAR | F9: 4 | G9: 고객계정그룹 | H9: Customer account group | I9: 2 | J9: KTOKD | L9: CHAR | M9: 4 | N9: 고객계정그룹 | O9: Customer account group
B10: 3 | C10: BUKRS | D10: Y | E10: CHAR | F10: 4 | G10: 회사코드 | H10: Company code | I10: 3 | J10: Company | K10: Y | L10: NVARCHAR | M10: 1000 | N10: 회사코드 | O10: Company code
B11: 4 | C11: VKORG | D11: Y | E11: CHAR | F11: 4 | G11: 판매조직 | H11: Sales organization | I11: 4 | J11: SalesOrg | K11: Y | L11: NVARCHAR | M11: 1000 | N11: 영업조직 | O11: Sales organization
B12: 5 | C12: VTWEG | E12: CHAR | F12: 2 | G12: 유통경로 | H12: Distribution path | I12: 5 | J12: SalesChannel | L12: NVARCHAR | M12: 1000 | N12: 유통경로 | O12: Distribution path
B13: 6 | C13: SPART | E13: CHAR | F13: 2 | G13: 제품군 | H13: product family | I13: 6 | J13: ProductGroup | L13: NVARCHAR | M13: 1000 | N13: 제품군 | O13: product family
B14: 7 | C14: KUNNR | D14: Y | E14: CHAR | F14: 10 | G14: 거래처코드 | H14: Traffic | I14: 7 | J14: SoldToParty | K14: Y | L14: NVARCHAR | M14: 1000 | N14: 거래처 코드 | O14: Customer
B15: 8 | C15: AUFSD | E15: CHAR | F15: 2 | G15: 상태구분 | H15: State distinction | I15: 8 | J15: Status | L15: NVARCHAR | M15: 1000 | N15: 상태구분 | O15: State distinction
B16: 9 | C16: NAME1 | E16: CHAR | F16: 40 | G16: 거래처명 1 | H16: ShipTo Name1 | I16: 9 | J16: ShipToDesc1 | L16: NVARCHAR | M16: 1000 | N16: 거래처명 1 | O16: ShipTo Name1
B17: 10 | C17: NAME2 | E17: CHAR | F17: 40 | G17: 거래처명 2 | H17: ShipTo Name2 | I17: 10 | J17: ShipToDesc2 | L17: NVARCHAR | M17: 1000 | N17: 거래처명 2 | O17: ShipTo Name2
B18: 11 | C18: NAME3 | E18: CHAR | F18: 40 | G18: 거래처명 3 | H18: ShipTo Name3 | I18: 11 | J18: ShipToDesc3 | L18: NVARCHAR | M18: 1000 | N18: 거래처명 3 | O18: ShipTo Name3
B19: 12 | C19: PRCTR | E19: CHAR | F19: 10 | G19: 손익센터 | H19: Income Center | I19: 12 | J19: ProfitCenter | L19: NVARCHAR | M19: 1000 | N19: 손익센터 | O19: Income Center
B20: 13 | C20: COUNTRY | E20: CHAR | F20: 3 | G20: 국가 키 | H20: National key | I20: 13 | J20: Country | L20: NVARCHAR | M20: 1000 | N20: 국가 키 | O20: National key
B21: 14 | C21: POST_CODE1 | E21: CHAR | F21: 10 | G21: 우편번호 | H21: Zip code | I21: 14
B22: 15 | C22: REGION | E22: CHAR | F22: 3 | G22: 지역 | H22: region | I22: 15 | J22: IF_DATE | L22: DATE | N22: 인터페이스 일자 | O22: Interface date
B23: 16 | C23: CITY1 | E23: CHAR | F23: 40 | G23: 도시 | H23: city | I23: 16 | J23: IF_STATUS | L23: VARCHAR2 | M23: 30 | N23: 인터페이스 처리 상태 | O23: Interface Status
B24: 17 | C24: STREET | E24: CHAR | F24: 60 | G24: 상세 주소 1 | H24: Details 1 | I24: 17 | J24: IF_PROCESS_DATE | L24: DATE | N24: 인터페이스 처리 일자 | O24: Interface Process date
B25: 18 | C25: STR_SUPPL1 | E25: CHAR | F25: 40 | G25: 상세 주소 2 | H25: Details 2 | I25: 18 | J25: IF_GRP_ID | L25: NUMBER | N25: 인터페이스 그룹 id(처리 시) | O25: Interface group id
B26: 19 | C26: STR_SUPPL2 | E26: CHAR | F26: 40 | G26: 상세 주소 3 | H26: Details 3 | I26: 19
B27: 20 | C27: STR_SUPPL3 | E27: CHAR | F27: 40 | G27: 상세 주소 4 | H27: Details 4 | I27: 20
B28: 21 | C28: TEL_NUMBER | E28: CHAR | F28: 30 | G28: 전화번호 | H28: phone number | I28: 21
B29: 22 | C29: FAX_NUMBER | E29: CHAR | F29: 30 | G29: 팩스번호 | H29: Fax number | I29: 22
B30: 23 | C30: SMTP_ADDR | E30: CHAR | F30: 241 | G30: 전자메일 주소 | H30: E -mail address | I30: 23
B31: 24 | C31: TRANSPZONE | E31: CHAR | F31: 10 | G31: 운송 지역 | H31: Transportation area | I31: 24
B32: 25 | C32: REGIOGROUP | E32: CHAR | F32: 8 | G32: 지역구조그루핑 | H32: Regional structure groop | I32: 25
B33: 26 | C33: DLVSQ | E33: CHAR | F33: 4 | G33: 배송순서 | H33: Shipping order | I33: 26
B34: 27 | C34: J_1KFREPRE | E34: CHAR | F34: 10 | G34: 대표자이름 | H34: Representative name | I34: 27
B35: 28 | C35: BAHNS | E35: CHAR | F35: 25 | G35: Sales Note1 | H35: SALES NOTE1 | I35: 28
B36: 29 | C36: STCD1 | E36: CHAR | F36: 16 | G36: 주민등록번호 | H36: resident registration number | I36: 29
B37: 30 | C37: STCD2 | E37: CHAR | F37: 11 | G37: 사업자등록번호 | H37: Company Registration Number | I37: 30
... B43: 36 | C43: ESDAT | E43: CHAR | F43: 8 | G43: 거래종료일 | H43: Termination date | I43: 36
B44: 37 | C44: BZIRK | E44: CHAR | F44: 6 | G44: 영업지역 | H44: Business area | I44: 37 | J44: SalesRegion | L44: NVARCHAR | M44: 1000 | N44: 영업지역 | O44: Business area
B45: 38 | C45: VKBUR | E45: CHAR | F45: 4 | G45: 영업팀 | H45: Sales team | I45: 38 | J45: SalesTeam | L45: NVARCHAR | M45: 1000 | N45: 영업팀코드 | O45: Sales Team Code
B46: 39 | C46: VKGRP | E46: CHAR | F46: 3 | G46: 영업그룹 | H46: Business group | I46: 39 | J46: SalesGroup | L46: NVARCHAR | M46: 1000 | N46: 영업그룹 | O46: Business group
B47: 40 | C47: KDGRP | E47: CHAR | F47: 2 | G47: 거래처그룹(Customer group) | H47: Customer Group | I47: 40 | J47: BizType | L47: NVARCHAR | M47: 1000 | N47: 거래처 그룹 | O47: Customer Group
B48: 41 | C48: KVGR1 | E48: CHAR | F48: 3 | G48: 고객무상품그룹 | H48: Customer Product Group | I48: 41
B49: 42 | C49: KVGR2 | E49: CHAR | F49: 3 | G49: 고객허용그룹 | H49: Customer allowance group | I49: 42
B50: 43 | C50: DISTB | E50: CHAR | F50: 4 | G50: 유통사(Distributer) | H50: Distributer | I50: 43
B51: 44 | C51: MNTYP | E51: CHAR | F51: 4 | G51: 운영방식 | H51: Operating | I51: 44
B52: 45 | C52: BUSUN | E52: CHAR | F52: 4 | G52: BU(부문) | H52: BU (division) | I52: 45 | J52: BU | L52: NVARCHAR | M52: 1000 | N52: BU(부문) | O52: BU (division)
B53: 46 | C53: DIVSN | E53: CHAR | F53: 4 | G53: Sales Division(사업부) | H53: Sales Division | I53: 46 | J53: SalesDivision | L53: NVARCHAR | M53: 1000 | N53: Sales Division(사업부) | O53: Sales Division
B54: 47 | C54: SUBSC | E54: CHAR | F54: 4 | G54: Sub-Sales Channel(경로) | H54: Sub-Sales Channel (path) | I54: 47 | J54: Channel | L54: NVARCHAR | M54: 1000 | N54: 하위영업경로코드 | O54: Sub -sales route code
B55: 48 | C55: PLTYP | E55: CHAR | F55: 2 | G55: 가격리스트유형 | H55: Price list type | I55: 48
B56: 49 | C56: KBETR | E56: NUMBER | F56: 11 | G56: 가격 | H56: price | I56: 49
B57: 50 | C57: LPRIO | E57: CHAR | F57: 2 | G57: 납품 우선순위 | H57: Priority of delivery | I57: 50
B58: 51 | C58: VWERK | E58: CHAR | F58: 4 | G58: 납품 플랜트 | H58: Delivery plant | I58: 51 | J58: DeliveryPlant | L58: NVARCHAR | M58: 1000 | N58: 납품 플랜트 | O58: Delivery plant
B59: 52 | C59: SWERKS | E59: CHAR | F59: 4 | G59: 영업 플랜트 | H59: Operating plant | I59: 52 | J59: SalesPlant | L59: NVARCHAR | M59: 1000 | N59: 영업 플랜트 | O59: Operating plant
B60: 53 | C60: SLGORT | E60: CHAR | F60: 4 | G60: 영업 저장위치 | H60: Sales storage location | I60: 53 | J60: SalesLocation | L60: NVARCHAR | M60: 1000 | N60: 영업 저장위치 | O60: Sales storage location
B61: 54 | C61: KATR1 | E61: CHAR | F61: 2 | G61: 배송조건 | H61: Shipping | I61: 54
B62: 55 | C62: SHOPC | E62: CHAR | F62: 4 | G62: 매장컨셉 | H62: Store concept | I62: 55
B63: 56 | C63: MAINB | E63: CHAR | F63: 5 | G63: 메인 브랜드 | H63: Main brand | I63: 56
B64: 57 | C64: KUNWE | E64: CHAR | F64: 10 | G64: 납품처(Ship-to party) | H64: Ship-to Party | I64: 57
B65: 58 | C65: KUNRE | E65: CHAR | F65: 10 | G65: 대표거래처(Bill-to party) | H65: Bill-to Party | I65: 58
B66: 59 | C66: KUNRG | E66: CHAR | F66: 10 | G66: 지급처(Payer) | H66: Payer | I66: 59
B67: 60 | C67: HKUNNR | E67: CHAR | F67: 10 | G67: 총괄거래처 | H67: Overall business | I67: 60
B68: 61 | C68: PERNR | E68: CHAR | F68: 8 | G68: 사원 번호 | H68: Employee number | I68: 61
B69: 62 | C69: SNAME | E69: CHAR | F69: 40 | G69: 사원이름 | H69: Employee name | I69: 62
B70: 63 | C70: BANKL | E70: CHAR | F70: 15 | G70: 은행키 | H70: Bank | I70: 63
B71: 64 | C71: TAXKD_DESC | E71: CHAR | G71: 세금유형명 | H71: Tax classification name | I71: 64 | T71: 추가-251022 | U71: 온/오프라인 구분임
B72: 65 | C72: KTGRD_DESC | E72: CHAR | G72: 계정지정그룹명 | I72: 65 | T72: 추가-251022
B73: 66 | I73: 66 | T73: 추가-251022
B74: 67 | I74: 67 | T74: 추가-251022
B75: 68 | I75: 68 | T75: 추가-251022
B78: 변환규칙정의
B79: 변환규칙 | D79: 내용
B80: R1
B81: R2
B83: 기타정보
B84: 이벤트 발생조건 (DB Trigger)
B85: 연계데이터 추출조건
B86: 데이터 반영방법
B87: 기타
H88: AU000001
C89: 기술적이름 | G89: 메저명 | H89: 추가데이터확인용 파일 존재 | I89: SAP-기존 | J89: BW-
B90: bw | C90: 0cust_sales | D90: O | E90: CHAR | F90: 10 | G90: 거래처코드 | I90: 1
B91: bw | C91: 0salesorg | D91: O | E91: CHAR | F91: 4 | G91: 영업조직 | I91: 1
B92: bw | C92: 0distr_chan | D92: O | E92: CHAR | F92: 2 | G92: 유통경로 | I92: 1
B93: bw | C93: ZCUSCT | E93: CHAR | F93: 4 | G93: 거래처형태 | H93: 1 | J93: 1
B94: bw | C94: ZCHAR_5 | E94: CHAR | F94: 5 | G94: GPS 목표채널 | J94: 1
B95: bw | C95: 0CUST_GRP1 | E95: CHAR | F95: 3 | G95: 고객그룹1(N) | J95: 1
B96: bw | C96: 0CUST_GRP2 | E96: CHAR | F96: 3 | G96: 고객그룹2(N) | J96: 1
B97: bw | C97: 0SALES_GRP | E97: CHAR | F97: 3 | G97: 영업그룹(N) | I97: 1
B98: bw | C98: ZAPGCHNL | E98: CHAR | F98: 5 | G98: 그룹거래처채널(N) | J98: 1
B99: bw | C99: ZCHAR_10A | E99: CHAR | F99: 10 | G99: (그룹채널)Unit
B100: bw | C100: ZDISTB | E100: CHAR | F100: 4 | G100: 유통사(N) | I100: 1
B101: bw | C101: ZCHAR_10B | E101: CHAR | F101: 10 | G101: (그룹채널)Division | J101: 1
B102: bw | C102: ZGRPAMT | E102: CHAR | F102: 1 | G102: (그룹채널)그룹매출 | J102: 1
B103: bw | C103: ZGRPPRO | E103: CHAR | F103: 1 | G103: (그룹채널)그룹이익 | J103: 1
B104: bw | C104: ZCRSHOPSV_ZDISTB | E104: CHAR | F104: 4 | G104: 매장 유통사(N) | J104: 1 | N104: KNA1 | O104: KNA1 값 | P104: KNB1 | Q104: KNB1 값 | R104: KNVV | S104: KNVV값
C105: BI=0CUST_COMPC_ZSUBCH2 | G105: 하위채널 | H105: 1
C106: CUSTOMER_PFC_FITYP | G106: 펀매유형 예) 직매입 순액 | H106: 없음
C107: CUST_SALES_ZCHAR_2 | G107: ON/OFF 구분 | H107: 없음
B111: sap | C111: I_LEGACY | E111: CHAR | F111: 5 | G111: LEGACY SYSTEM 명 | H111: Legacy System Name
...

Sheet CP-40.재고(계획용)
B1: Overview!A3
B2: 매핑정의서 - 재고(계획용) Inventory (For planning) | O2: 2022.07.08
O3: 0
B6: 5. 매핑정의
B7: Source - SAP | I7: Target - 싱글플랫폼 | S7: Set Value | T7: 변환규칙
B8: RFC | D8: ZSD_SEND_FILE_TO_O9 /interface/O9/send/SSD01<DATE>000000.csv(000000은 생성시간) | I8: Web Service Methods | K8: sftpaws-ane2.o9solutions.com(Port: 2222) o9 SFTP 서버 내 \Preprod\Inbound\SAP_Onhand_<Timestamp>_<Count><Seq>.csv
B9: SEQ | C9: Table(Path) | D9: Field | E9: PK | F9: Type | G9: Size | H9: Desc | I9: SEQ | J9: Table(Path) | K9: Field | L9: PK | M9: Type | N9: Size | O9: Desc | Q9: Req No | R9: Res No
B10: 1 | C10: BUKRS | D10: Y | F10: 4 | I10: 1 | K10: OrgID | M10: NVARCHAR | N10: 1000 | O10: OrgID | P10: Organization ID | S10: 회사코드 | T10: Company code
B11: 2 | C11: DATUM | D11: Y | F11: 8 | I11: 2 | K11: CutOffDate | M11: NVARCHAR | N11: 1000 | O11: CutOffDate | P11: Cut-Off Date | S11: 일자 | T11: Date
B12: 3 | C12: MATNR | D12: Y | F12: 18 | I12: 3 | K12: Item | M12: NVARCHAR | N12: 1000 | O12: Item | P12: Material | S12: 자재 | T12: material
B13: 4 | C13: WERKS | D13: Y | F13: 4 | I13: 4 | K13: Plant | M13: NVARCHAR | N13: 1000 | O13: Plant | P13: Plant | S13: 플랜트 | T13: plant
B14: 5 | C14: LGORT | D14: Y | F14: 4 | I14: 5 | K14: Location | M14: NVARCHAR | N14: 1000 | O14: Location | P14: Location | S14: 저장위치 | T14: Storage location
B15: 6 | C15: MEINS | I15: 6 | K15: UOM | M15: NVARCHAR | N15: 1000 | O15: UOM | P15: UOM | S15: 단위 | T15: unit
B16: 7 | C16: LABST | I16: 7 | K16: AvailQty | M16: NVARCHAR | N16: 1000 | O16: AvailQty | P16: Available Quantity | S16: 가용재고 | T16: Available inventory
B17: 8 | C17: ZRESTO | I17: 8 | K17: STOInQty | M17: NVARCHAR | N17: 1000 | O17: STOInQty | P17: STO In Quantity | S17: STO입고예정 | T17: STO will be in stock
B18: 9 | C18: ZRERES | I18: 9 | K18: ReserveInQty | M18: NVARCHAR | N18: 1000 | O18: ReserveInQty | P18: Reserve In Quantity | S18: 예약입고예정 | T18: Scheduled reservation
B19: 10 | C19: ZRETUR | I19: 10 | K19: ReturnQty | M19: NVARCHAR | N19: 1000 | O19: ReturnQty | P19: Return Quantity | S19: 반품입고예정 | T19: Scheduled to be in stock
B20: 11 | C20: KULAB | I20: 11 | K20: CustomerQty | M20: NVARCHAR | N20: 1000 | O20: CustomerQty | P20: Customer Quantity | S20: 고객위탁재고 | T20: Customer Consignment High School
B21: 12 | C21: INSME | I21: 12 | K21: QMQty | M21: NVARCHAR | N21: 1000 | O21: QMQty | P21: QM Quantity | S21: 품질재고 | T21: Quality inventory
B22: 13 | C22: ZISSTO | I22: 13 | K22: STOOutQty | M22: NVARCHAR | N22: 1000 | O22: STOOutQty | P22: STO Out Quantity | S22: STO출고예정 | T22: STO shipping scheduled
B23: 14 | C23: ZISRES | I23: 14 | K23: ReserveOutQty | M23: NVARCHAR | N23: 1000 | O23: ReserveOutQty | P23: Reserve Out Quantity | S23: 예약출고예정 | T23: Scheduled to be reserved
B24: 15 | C24: ZISALE | I24: 15 | K24: SOOutQty | M24: NVARCHAR | N24: 1000 | O24: SOOutQty | P24: SO Out Quantity | S24: SO출고예정 | T24: SO shipped
B25: 16 | I25: 16
B26: 17 | I26: 17
B27: 18 | I27: 18
B28: 19
B29: 20 | I29: 20
B30: 21 | I30: 21
B32: 6. 변환규칙정의
B33: 변환규칙 | D33: 내용
B34: R1
B35: R2
B37: 7. 기타정보
B38: 이벤트 발생조건 (DB Trigger)
B39: 연계데이터 추출조건
B40: 데이터 반영방법
B41: 기타
C43: Weekly2, WeeklyB2
C45: AP_CUST_OnHands

Sheet 기준환율
A1: Top
B2: 매핑정의서 - 환율 Standard exchange rate | J2: Source System | K2: BW | O2: 문서작성일 | P2: 2025.09.25
J3: Target System | K3: APLAN | O3: 버전 | P3: 0.1
B4: 매핑정의
B5: Source Table : ? | I5: Target Table : ? | R5: Set Value | S5: 변환규칙
B6: RFC | I6: Web SVC | J6: PreProd : https://myamorepacificpreprod.o9solutions.com/ Prod : https://myamorepacific.o9solutions.com/
B7: SEQ | C7: Field | D7: PK | E7: Type | F7: Size | G7: Desc | H7: Desc(ENG) | I7: SEQ | J7: Field | K7: PK | L7: Type | M7: Size | N7: Desc | O7: Desc(ENG) | P7: Req No | Q7: Res No
B8: 1 | C8: ??? | I8: 1 | J8: SalesOrg | L8: NVARCHAR | M8: 1000 | N8: 영업조직 | O8: Sales Org
B9: 2 | C9: FCURR | E9: CUKY | G9: 소스 통화 | H9: Source Currency | I9: 2 | J9: FromCurrency | L9: NVARCHAR | M9: 1000 | N9: 소스통화 | O9: Source Currency
B10: 3 | C10: TCURR | E10: CUKY | G10: 대상통화 | H10: Target Currency | I10: 3 | J10: ToCurrency | L10: NVARCHAR | M10: 1000 | N10: 타겟통화 | O10: Target Currency
B11: 4 | C11: UKURS | E11: CHAR | G11: 환율 | H11: Exchange Rate | I11: 4 | J11: ExchangeRate | L11: NVARCHAR | M11: 1000 | N11: 환율값 | O11: Exchange Rate
B12: 5 | I12: 5
B13: 6 | I13: 6
B14: 7 | I14: 7
B15: 8 | I15: 8
B16: 9 | I16: 9
B17: 10 | I17: 10
B20: 변환규칙정의
B21: 변환규칙 | D21: 내용
B22: R1
B23: R2
B25: 기타정보
B26: 이벤트 발생조건 (DB Trigger)
B27: 연계데이터 추출조건
B28: 데이터 반영방법
B29: 기타

Sheet 수출진행모니터링
A1: Top
B2: 매핑정의서 - 수출진행모니터링 Export Progress Monitoring | J2: Source System | K2: BW | O2: 문서작성일 | P2: 2025.09.25
J3: Target System | K3: APLAN | O3: 버전 | P3: 0.1
B4: 매핑정의
B5: Source Table : ? | I5: Target Table : ? | R5: Set Value | S5: 변환규칙
B6: RFC | I6: Web SVC | J6: PreProd : https://myamorepacificpreprod.o9solutions.com/ Prod : https://myamorepacific.o9solutions.com/
B7: SEQ | C7: Field | D7: PK | E7: Type | F7: Size | G7: Desc | H7: Desc(ENG) | I7: SEQ | J7: Field | K7: PK | L7: Type | M7: Size | N7: Desc | O7: Desc(ENG) | P7: Req No | Q7: Res No
B8: 1 | C8: IT_TABLE | E8: CHAR | F8: 5 | G8: LEGACY SYSTEM | H8: LEGACY SYSTEM | I8: 1
B9: 2 | C9: REQ_STATUS | D9: Y | E9: CHAR | F9: 1 | G9: 요청상태 | H9: Request status | I9: 2 | J9: ReqStatus | K9: Y | L9: NVARCHAR | M9: 1000 | N9: 요청상태 | O9: Request status
B10: 3 | C10: ZSHIPSTAT | D10: Y | E10: CHAR | F10: 2 | G10: 선적상태 | H10: Shipment | I10: 3 | J10: ShipStatus | K10: Y | L10: NVARCHAR | M10: 1000 | N10: 선적상태 | O10: Shipment
B11: 4 | C11: SONR | D11: Y | E11: CHAR | F11: 10 | G11: 판매 문서 | H11: Sales document | I11: 4 | J11: SONo | K11: Y | L11: NVARCHAR | M11: 1000 | N11: 판매 문서 | O11: Sales document
B12: 5 | C12: SOPOS | D12: Y | E12: NUMC | F12: 6 | G12: 판매 문서 품목 | H12: Sales document item | I12: 5 | J12: SOLine | K12: Y | L12: NVARCHAR | M12: 1000 | N12: 판매 문서 품목 | O12: Sales document item
B13: 6 | C13: DNNR | D13: Y | E13: CHAR | F13: 10 | G13: 납품 | H13: Delivery | I13: 6 | J13: DNNo | K13: Y | L13: NVARCHAR | M13: 1000 | N13: 납품 | O13: Delivery
B14: 7 | C14: DNPOS | D14: Y | E14: NUMC | F14: 6 | G14: 납품품목 | H14: Delivery | I14: 7 | J14: DNLine | K14: Y | L14: NVARCHAR | M14: 1000 | N14: 납품품목 | O14: Delivery
B15: 8 | C15: GRNR | D15: Y | E15: CHAR | F15: 10 | G15: 자재문서번호 | H15: Material document number | I15: 8 | J15: GRNo | K15: Y | L15: NVARCHAR | M15: 1000 | N15: 자재문서번호 | O15: Material document number
B16: 9 | C16: GRPOS | D16: Y | E16: NUMC | F16: 4 | G16: 자재 문서 항목 | H16: Material document item | I16: 9 | J16: GRLine | K16: Y | L16: NVARCHAR | M16: 1000 | N16: 자재 문서 항목 | O16: Material document item
B17: 10 | C17: SODAT | E17: DATS | F17: 8 | G17: 레코드 생성일 | H17: Record creation date | I17: 10 | J17: SOCreationDate | L17: NVARCHAR | M17: 1000 | N17: 레코드 생성일 | O17: Record creation date
B18: 11 | C18: SOMNG | E18: CHAR | F18: 15 | G18: SO 수량 | H18: SO quantity | I18: 11 | J18: SOQty | L18: NVARCHAR | M18: 1000 | N18: SO 수량 | O18: SO quantity
B19: 12 | C19: DNDAT | E19: DATS | F19: 8 | G19: 레코드 생성일 | H19: Record creation date | I19: 12 | J19: DNCreationDate | L19: NVARCHAR | M19: 1000 | N19: 레코드 생성일 | O19: Record creation date
B20: 13 | C20: DNMNG | E20: CHAR | F20: 15 | G20: DN 수량 | H20: DN quantity | I20: 13 | J20: DNQty | L20: NVARCHAR | M20: 1000 | N20: DN 수량 | O20: DN quantity
B21: 14 | C21: HQNR | E21: CHAR | F21: 35 | G21: 참조전표번호 (관련사항은 설명을 참조하십시오.) | H21: Reference document number (see the explanation for related matters.) | I21: 14 | J21: HQNo | L21: NVARCHAR | M21: 1000 | N21: 참조전표번호 (관련사항은 설명을 참조하십시오.) | O21: Reference document number (see the explanation for related matters.)
B22: 15 | C22: GRDAT | E22: DATS | F22: 8 | G22: 전표의 전기일 | H22: Electricity date of the document | I22: 15 | J22: GRCreationDate | L22: NVARCHAR | M22: 1000 | N22: 전표의 전기일 | O22: Electricity date of the document
B23: 16 | C23: GRMNG | E23: CHAR | F23: 15 | G23: GR 수량 | H23: GR quantity | I23: 16 | J23: GRQty | L23: NVARCHAR | M23: 1000 | N23: GR 수량 | O23: GR quantity
B24: 17 | C24: MEINS | E24: UNIT | F24: 3 | G24: 기본 단위 | H24: Basic unit | I24: 17 | J24: UOM | L24: NVARCHAR | M24: 1000 | N24: 기본 단위 | O24: Basic unit
B25: 18 | C25: DELIV_DATE | E25: DATS | F25: 8 | G25: 현지입고 예정일 | H25: Local Warehousing Estimated date | I25: 18 | J25: ETD | L25: NVARCHAR | M25: 1000 | N25: 현지입고 예정일 | O25: Local Warehousing Estimated date
B26: 19 | C26: ETA | E26: DATS | F26: 8 | G26: ETA | H26: ETA | I26: 19 | J26: ETA | L26: NVARCHAR | M26: 1000 | N26: ETA | O26: ETA
B27: 20 | C27: ATD | E27: DATS | F27: 8 | G27: ATD | H27: ATD | I27: 20 | J27: ATD | L27: NVARCHAR | M27: 1000 | N27: ATD | O27: ATD
B28: 21 | C28: ATA | E28: DATS | F28: 8 | G28: ATA | H28: ATA | I28: 21 | J28: ATA | L28: NVARCHAR | M28: 1000 | N28: ATA | O28: ATA
... B32: 25 | C32: MANTR | E32: CHAR | F32: 18 | G32: 자재코드 | H32: Material code | I32: 25 | J32: Item | L32: NVARCHAR | M32: 1000 | N32: 자재 | O32: Material code
B33: 26 | I33: 26
B34: 27 | E34: CHAR | F34: 20 | G34: To Site_cd | H34: sap에서 맵핑된 정보임 | I34: 27 | J34: TO_SITE_CD | L34: NVARCHAR | M34: 1000 | N34: 도착사이트코드 | T34: 추가-20251205 ERP팀 미팅후
B35: 28 | C35: WERKS | E35: CHAR | F35: 4 | G35: 플랜트 | I35: 28 | J35: PLANT | L35: NVARCHAR | N35: 플랜트 | T35: 추가-20251205 ERP팀 미팅후
C36: LGORT | E36: CHAR | F36: 4 | G36: 저장위치 | I36: 28 | J36: SLOC | L36: NVARCHAR | N36: 저장위치 | T36: 추가-20251205 ERP팀 미팅후
B37: 29 | C37: EBELN | E37: CHAR | F37: 10 | G37: 구매오더번호 | H37: 현지법인 po (so생성후 발행된것) | I37: 29 | J37: PONO | L37: NVARCHAR | N37: 구매오더번호 | T37: 추가-20251205 ERP팀 미팅후
B38: 30 | C38: EBELP | E38: NUMC | F38: 5 | G38: 구매오더품목 | H38: 현지법인 po (so생성후 발행된것) | I38: 30 | J38: POITEM | L38: NVARCHAR | N38: 구매오더품목 | O38: 삭제. 품목코드 중복 기입(251210) | T38: 추가-20251205 ERP팀 미팅후
B39: 31 | I39: 31
B42: 변환규칙정의
B43: 변환규칙 | D43: 내용
B44: R1
B45: R2
B47: 기타정보
B48: 이벤트 발생조건 (DB Trigger)
B49: 연계데이터 추출조건
B50: 데이터 반영방법
B51: 기타

Sheet 거래처재고
A1: Top
B2: 매핑정의서 - 거래처 재고 Customer Inventory | J2: Source System | K2: BW | O2: 문서작성일 | P2: 2025.09.25
J3: Target System | K3: APLAN | O3: 버전 | P3: 0.1
B4: 매핑정의
B5: Source Table : ? | I5: Target Table : ? | R5: Set Value | S5: 변환규칙
B6: RFC | I6: Web SVC | J6: PreProd : https://myamorepacificpreprod.o9solutions.com/ Prod : https://myamorepacific.o9solutions.com/
B7: SEQ | C7: Field | D7: PK | E7: Type | F7: Size | G7: Desc | H7: Desc(ENG) | I7: SEQ | J7: Field | K7: PK | L7: Type | M7: Size | N7: Desc | O7: Desc(ENG) | P7: Req No | Q7: Res No
B8: 1 | I8: 1 | J8: Company | K8: Y | L8: NVARCHAR | M8: 1000 | N8: 회사코드 | O8: Company code
B9: 2 | I9: 2 | J9: Date | K9: Y | L9: NVARCHAR | M9: 1000 | N9: 일자 | O9: Date
B10: 3 | I10: 3 | J10: Item | K10: Y | L10: NVARCHAR | M10: 1000 | N10: 자재 | O10: material
B11: 4 | I11: 4 | J11: ShipTo -> Sold To 변경 필요 | K11: Y | L11: NVARCHAR | M11: 1000 | N11: 협업거래처 | O11: Collaborative business
B12: 5 | I12: 5 | J12: UOM | L12: NVARCHAR | M12: 1000 | N12: 단위 | O12: unit
B13: 6 | I13: 6 | J13: AvailQty | L13: NVARCHAR | M13: 1000 | N13: 가용재고 | O13: Available inventory
B14: 7 | I14: 7 | J14: STOInQty | L14: NVARCHAR | M14: 1000 | N14: STO입고예정 | O14: STO Scheduled Receipt
B15: 8 | I15: 8 | J15: ReserveInQty | L15: NVARCHAR | M15: 1000 | N15: 예약입고예정 | O15: Reservation Scheduled Receipt
B16: 9 | I16: 9 | J16: ReturnQty | L16: NVARCHAR | M16: 1000 | N16: 반품입고예정 | O16: Return Scheduled Receipt
B17: 10 | I17: 10 | J17: CustomerQty | L17: NVARCHAR | M17: 1000 | N17: 고객위탁재고 | O17: Customer consignment stock
B18: 11 | I18: 11 | J18: QMQty | L18: NVARCHAR | M18: 1000 | N18: 품질재고 | O18: Quality inventory
B19: 12 | I19: 12 | J19: STOOutQty | L19: NVARCHAR | M19: 1000 | N19: STO출고예정 | O19: STO Release scheduled
B20: 13 | I20: 13 | J20: ReserveOutQty | L20: NVARCHAR | M20: 1000 | N20: 예약출고예정 | O20: Reservation shipping scheduled
B21: 14 | I21: 14 | J21: SOOutQty | L21: NVARCHAR | M21: 1000 | N21: SO출고예정 | O21: SO Release scheduled
B22: 15 | I22: 15
B23: 16 | I23: 16
B24: 17 | I24: 17
B25: 18 | I25: 18
B26: 19 | I26: 19
B27: 20 | I27: 20
B28: 21 | I28: 21
B29: 22 | I29: 22
B30: 23 | I30: 23
B31: 24 | I31: 24
B32: 25 | I32: 25
B33: 26 | I33: 26
... B38: 31 | I38: 31
B41: 변환규칙정의
B42: 변환규칙 | D42: 내용
B43: R1
B44: R2
B46: 기타정보
B47: 이벤트 발생조건 (DB Trigger)
B48: 연계데이터 추출조건
B49: 데이터 반영방법
B50: 기타

Sheet 기타수요
A1: Top
B2: 매핑정의서 - 기타수요 Other demands (appointment) | J2: Source System | K2: BW | O2: 문서작성일 | P2: 2025.09.25
J3: Target System | K3: APLAN | O3: 버전 | P3: 0.1
B4: 매핑정의
B5: Source Table : ? | I5: Target Table : ? | R5: Set Value | S5: 변환규칙
B6: RFC | I6: Web SVC | J6: PreProd : https://myamorepacificpreprod.o9solutions.com/ Prod : https://myamorepacific.o9solutions.com/
B7: SEQ | C7: Field | D7: PK | E7: Type | F7: Size | G7: Desc | H7: Desc(ENG) | I7: SEQ | J7: Field | K7: PK | L7: Type | M7: Size | N7: Desc | O7: Desc(ENG) | P7: Req No | Q7: Res No
B8: 1 | C8: ZPGCODE | I8: 1 | J8: PG -> Sold To Party 변경 필요 | L8: NVARCHAR | M8: 1000 | N8: PG코드 | O8: PG code
B9: 2 | C9: 0calweek | I9: 2 | J9: Week -> Day로 변경 필요 | L9: NVARCHAR | M9: 1000 | N9: 발생주(주차로 Sum) | O9: Occupational stock (Sum by Week)
B10: 3 | C10: 0material | I10: 3 | J10: Item | L10: NVARCHAR | M10: 1000 | N10: 자재 코드 | O10: Material code
B11: 4 | C11: 0salesorg | I11: 4 | J11: SalesOrg | L11: NVARCHAR | M11: 1000 | N11: 영업조직 | O11: Sales organization
B12: 5 | C12: 0distr_chnl | I12: 5 | J12: Distrchannel | L12: NVARCHAR | M12: 1000 | N12: 유통경로 | O12: Distribution path
B13: 6 | C13: 0base_uom | G13: B02 국내/해외 잡출수량 | I13: 6 | J13: UOM | L13: NVARCHAR | M13: 1000 | N13: UOM | O13: UOM
B14: 7 | C14: 0currency | G14: 통화단위 | I14: 7 | J14: Currency | L14: NVARCHAR | M14: 1000 | N14: 통화단위 | O14: Currency
B15: 8 | C15: ZCM_002_CB02 | G15: B02 국내/해외 잡출수량 | I15: 8 | J15: Qty | L15: NVARCHAR | M15: 1000 | N15: 잡출수량 | O15: Quantity
B16: 9 | C16: ZCM_002_CB04 | G16: 잡출 금액 | I16: 9 | J16: Price | L16: NVARCHAR | M16: 1000 | N16: 잡출금액 | O16: Price
B17: 10 | I17: 10
B18: 11 | I18: 11
B19: 12 | I19: 12
B20: 13 | I20: 13
B21: 14 | I21: 14
B22: 15 | I22: 15
B23: 16 | I23: 16
B24: 17 | I24: 17
B25: 18 | I25: 18
B26: 19 | I26: 19
B27: 20 | I27: 20
B28: 21 | I28: 21
... B38: 31 | I38: 31
B41: 변환규칙정의
B42: 변환규칙 | D42: 내용
B43: R1
B44: R2
B46: 기타정보
B47: 이벤트 발생조건 (DB Trigger)
B48: 연계데이터 추출조건
B49: 데이터 반영방법
B50: 기타

Sheet BOM
A1: Top`
B2: 매핑정의서 - BOM | J2: Source System | K2: SAP | O2: 문서작성일 | P2: 2025.09.25
J3: Target System | K3: APLAN | O3: 버전 | P3: 0.1
B4: 매핑정의
B5: Source Table : ? | I5: Target Table : ? | R5: Set Value | S5: 변환 규칙
B6: RFC | C6: ZPP_IF_BOM_SEND_BM_SP | I6: Web SVC | J6: PreProd : https://myamorepacificpreprod.o9solutions.com/ Prod : https://myamorepacific.o9solutions.com/
B7: SEQ | C7: Field | D7: PK | E7: Type | F7: Size | G7: Desc | H7: Desc(ENG) | I7: SEQ | J7: Field | K7: PK | L7: Type | M7: Size | N7: Desc | O7: Desc(ENG) | P7: Req No | Q7: Res No
B8: 1 | C8: MATNR | D8: Y | E8: CHAR | F8: 18 | G8: 상위자재코드 | H8: Top material code | I8: 1 | J8: Item | K8: Y | L8: NVARCHAR | M8: 1000 | N8: 상위자재코드 | O8: Top material code
B9: 2 | C9: WERKS | D9: Y | E9: CHAR | F9: 4 | G9: 플랜트 | H9: plant | I9: 2 | J9: Plant | K9: Y | L9: NVARCHAR | M9: 1000 | N9: 플랜트 | O9: plant
B10: 3 | C10: STLAN | D10: Y | E10: CHAR | F10: 1 | G10: BOM 용도(1:생산,Z:ODM) | H10: BOM use (1: Production, Z: ODM) | I10: 3 | J10: Usage | K10: Y | L10: NVARCHAR | M10: 1000 | N10: BOM 용도(1:생산,Z:ODM) | O10: BOM use (1: Production, Z: ODM)
B11: 4 | C11: STLAL | D11: Y | E11: CHAR | F11: 2 | G11: 대체 BOM | H11: Alternative BOM | I11: 4 | J11: AltBOM | K11: Y | L11: NVARCHAR | M11: 1000 | N11: 대체 BOM | O11: Alternative BOM
B12: 5 | C12: POSNR | E12: CHAR | F12: 4 | G12: BOM 품목번호 | H12: BOM item number | I12: 5 | J12: Seq | L12: NVARCHAR | M12: 1000 | N12: BOM 품목번호 | O12: BOM item number
B13: 6 | C13: IDNRK | D13: Y | E13: CHAR | F13: 18 | G13: 하위자재코드 | H13: Subcort | I13: 6 | J13: Component | K13: Y | L13: NVARCHAR | M13: 1000 | N13: 하위자재코드 | O13: Subcort
B14: 7 | C14: STUFE | E14: DEC | F14: 2 | G14: 레벨(다중 레벨 BOM 전개) | H14: Level (multiple level BOM development) | I14: 7 | J14: Level | L14: NVARCHAR | M14: 1000 | N14: 레벨(다중 레벨 BOM 전개) | O14: Level (multiple level BOM development)
B15: 8 | C15: MENGE | E15: QUAN | F15: 13.3 | G15: 구성부품수량 | H15: Configuration parts quantity | I15: 8 | J15: ConsumedPer | L15: NVARCHAR | M15: 1000 | N15: 구성부품수량 | O15: Configuration parts quantity
B16: 9 | C16: MEINS | E16: UNIT | F16: 3 | G16: 구성부품단위 | H16: Configuration parts unit | I16: 9 | J16: UOM | L16: NVARCHAR | M16: 1000 | N16: 구성부품단위 | O16: Configuration parts unit
B17: 10 | C17: DATUV | E17: DATS | F17: 8 | G17: 효력시작일 | H17: Effective Start Date | I17: 10 | J17: EffStartDate | L17: NVARCHAR | M17: 1000 | N17: 효력시작일 | O17: Effective Start Date
B18: 11 | C18: DATUB | E18: DATS | F18: 8 | G18: 효력종료일 | H18: Effective end date | I18: 11 | J18: EffEndDate | L18: NVARCHAR | M18: 1000 | N18: 효력종료일 | O18: Effective end date
B19: 12 | I19: 12
B20: 13 | I20: 13
B21: 14 | I21: 14
B22: 15 | I22: 15
B23: 16 | I23: 16
B24: 17 | I24: 17
B25: 18 | I25: 18
B26: 19 | I26: 19
B27: 20 | I27: 20
B28: 21 | I28: 21
B29: 22 | I29: 22
B30: 23 | I30: 23
... B38: 31 | I38: 31
B41: 변환규칙정의
B42: 변환규칙 | D42: 내용
B43: R1
B44: R2
B46: 기타정보
B47: 이벤트 발생조건 (DB Trigger)
B48: 연계데이터 추출조건
B49: 데이터 반영방법
B50: 기타

Sheet 생산오더
A1: Top
B2: 매핑정의서 - 생산 오더 Production Order | J2: Source System | K2: SAP | O2: 문서작성일 | P2: 2025.09.25
J3: Target System | K3: APLAN | O3: 버전 | P3: 0.1
B4: 매핑정의
B5: Source Table : ? | I5: Target Table : ? | R5: Set Value | S5: 변환규칙
B6: RFC | I6: Web SVC | J6: PreProd : https://myamorepacificpreprod.o9solutions.com/ Prod : https://myamorepacific.o9solutions.com/
B7: SEQ | C7: Field | D7: PK | E7: Type | F7: Size | G7: Desc | H7: Desc(ENG) | I7: SEQ | J7: Field | K7: PK | L7: Type | M7: Size | N7: Desc | O7: Desc(ENG) | P7: Req No | Q7: Res No
B8: 1 | C8: AUFNR | D8: Y | E8: CHAR | F8: 12 | G8: 생산오더번호 | H8: Production order number | I8: 1 | J8: OrderID | K8: Y | L8: NVARCHAR | M8: 1000 | N8: 오더 번호 | O8: Production order number
B9: 2 | C9: MATNR | E9: CHAR | F9: 18 | G9: 자재코드 | H9: Material code | I9: 2 | J9: Item | L9: NVARCHAR | M9: 1000 | N9: 자재코드 | O9: Material code
B10: 3 | C10: ARBPL | E10: CHAR | F10: 8 | G10: 작업장 | H10: work place | I10: 3 | J10: Line | L10: NVARCHAR | M10: 1000 | N10: 생산라인 --> 작업장 | O10: work place
B11: 4 | C11: GAMNG | E11: QUAN | F11: 13.3 | G11: 총 오더수량 | H11: Total order quantity | I11: 4 | J11: PlanQty | L11: NVARCHAR | M11: 1000 | N11: 계획수량 --> 총 오더수량 | O11: Total order quantity
B12: 5 | C12: GSTRS | E12: DATS | F12: 8 | G12: 계획시작일 | H12: Plan Start Date | I12: 5 | J12: PlanStartDateTime | L12: NVARCHAR | M12: 1000 | N12: 계획 시작 시간 | O12: Plan Start Date
B13: 6 | C13: GLTRS | E13: DATS | F13: 8 | G13: 계획종료일 | H13: Plan End Date | I13: 6 | J13: PlanEndDateTime | L13: NVARCHAR | M13: 1000 | N13: 계획 종료 시간 | O13: Plan End Date
B14: 7 | C14: GSTRI | E14: DATS | F14: 8 | G14: 실제 시작일 | H14: Actual start date | I14: 7 | J14: TxStartDateTime | L14: NVARCHAR | M14: 1000 | N14: 실적 시작 시간 | O14: Actual start date
B15: 8 | C15: GLTRI | E15: DATS | F15: 8 | G15: 실제 종료일 | H15: Actual end date | I15: 8 | J15: TxEndDateTime | L15: NVARCHAR | M15: 1000 | N15: 실적 종료 시간 | O15: Actual end date
B16: 9 | C16: CNFFLAG | E16: CHAR | F16: 1 | G16: X : 마감(CNF 됨) | H16: X: Finish (CNF) | I16: 9 | J16: ClosedFlag | L16: NVARCHAR | M16: 1000 | N16: 마감여부 | O16: X: Finish (CNF)
B17: 10 | C17: WEMNG | E17: QUAN | F17: 13.3 | G17: 오더품목 입고수량 | H17: Order item wearing quantity | I17: 10 | J17: ProdQty | L17: NVARCHAR | M17: 1000 | N17: 생산 수량 --> 생산수량 | O17: Order item wearing quantity
B18: 11 | C18: MEINS | E18: UNIT | F18: 3 | G18: 기본단위 | H18: Basic unit | I18: 11 | J18: UOM | L18: NVARCHAR | M18: 1000 | N18: 기본단위 | O18: Basic unit
B19: 12 | C19: AUART | E19: CHAR | F19: 4 | G19: 오더유형 | H19: Order type | I19: 12 | J19: OrderType | L19: NVARCHAR | M19: 1000 | N19: 오더 유형(PP01 : 표준오더, PP99 :재작업오더 등과 같은 유형값) | O19: Order type
B20: 13 | C20: CUD_CI | E20: CHAR | F20: 1 | G20: D : 삭제 | H20: D: Delete | I20: 13 | J20: CUD | L20: NVARCHAR | M20: 1000 | N20: D : 삭제 | O20: D: Delete
B21: 14 | C21: WERKS | D21: Y | E21: CHAR | F21: 4 | G21: 플랜트 | H21: plant | I21: 14 | J21: Plant | K21: Y | L21: NVARCHAR | M21: 1000 | N21: 플랜트 | O21: plant
B22: 15 | I22: 15
B23: 16 | I23: 16
B24: 17 | I24: 17
B25: 18 | I25: 18
B26: 19 | I26: 19
B27: 20 | I27: 20
B28: 21 | I28: 21
B29: 22 | I29: 22
B30: 23 | I30: 23
B31: 24 | I31: 24
B32: 25 | I32: 25
B33: 26 | I33: 26
... B38: 31 | I38: 31
B41: 변환규칙정의
B42: 변환규칙 | D42: 내용
B43: R1
B44: R2
B46: 기타정보
B47: 이벤트 발생조건 (DB Trigger)
B48: 연계데이터 추출조건
B49: 데이터 반영방법
B50: 기타

Sheet 구매오더
A1: Top
B2: 매핑정의서 - 구매 오더 Purchase Order | J2: Source System | K2: SAP | O2: 문서작성일 | P2: 2025.09.25
J3: Target System | K3: APLAN | O3: 버전 | P3: 0.1
B4: 매핑정의
B5: Source Table : ? | I5: Target Table : ? | R5: Set Value | S5: 변환규칙
B6: RFC | I6: Web SVC | J6: PreProd : https://myamorepacificpreprod.o9solutions.com/ Prod : https://myamorepacific.o9solutions.com/
B7: SEQ | C7: Field | D7: PK | E7: Type | F7: Size | G7: Desc | H7: Desc(ENG) | I7: SEQ | J7: Field | K7: PK | L7: Type | M7: Size | N7: Desc | O7: Desc(ENG) | P7: Req No | Q7: Res No
B8: 1 | C8: EKORG | E8: CHAR | F8: 4 | G8: 구매조직 | H8: Purchasing organization | I8: 1 | J8: PurchaseOrg | L8: NVARCHAR | M8: 1000 | N8: 구매조직 | O8: Purchasing organization
B9: 2 | C9: EBELN | E9: CHAR | F9: 10 | G9: 구매오더 번호 | H9: Purchase order number | I9: 2 | J9: OrderID | L9: NVARCHAR | M9: 1000 | N9: 구매오더 번호 | O9: Purchase order number
B10: 3 | C10: EBELP | E10: CHAR | F10: 18 | G10: 구매오더 품목번호 | H10: Purchase order item number | I10: 3 | J10: OrderLineID | L10: NVARCHAR | M10: 1000 | N10: 구매오더 품목번호 | O10: Purchase order item number
B11: 4 | C11: WERKS | E11: CHAR | F11: 4 | G11: 플랜트 | H11: plant | I11: 4 | J11: Plant | L11: NVARCHAR | M11: 1000 | N11: 플랜트 | O11: plant
B12: 5 | C12: MATNR | E12: CHAR | F12: 18 | G12: 자재코드 | H12: Material code | I12: 5 | J12: Item | L12: NVARCHAR | M12: 1000 | N12: 자재코드 | O12: Material code
B13: 6 | C13: LIFNR | E13: CHAR | F13: 10 | G13: 공급업체 | H13: Supplier | I13: 6 | J13: Supplier | L13: NVARCHAR | M13: 1000 | N13: 공급업체 | O13: Supplier
B14: 7 | C14: EINDT | E14: DATS | F14: 8 | G14: 품목 납품일 | H14: Item delivery date | I14: 7 | J14: DeliveryDate | L14: NVARCHAR | M14: 1000 | N14: 품목 납품일 | O14: Item delivery date
B15: 8 | C15: MENGE | E15: QUAN | F15: 13.3 | G15: 구매오더 수량 | H15: Purchase order quantity | I15: 8 | J15: PlanQty | L15: NVARCHAR | M15: 1000 | N15: 구매오더 수량 | O15: Purchase order quantity
B16: 9 | C16: WECMG | E16: QUAN | F16: 13.3 | G16: 구매오더 입고수량 | H16: Purchased order quantity | I16: 9 | J16: ReceiveQty | L16: NVARCHAR | M16: 1000 | N16: 구매오더 입고수량 | O16: Purchased order quantity
B17: 10 | C17: MEINS | E17: UNIT | F17: 3 | G17: 구매오더 단위 | H17: Purchase order unit | I17: 10 | J17: UOM | L17: NVARCHAR | M17: 1000 | N17: 구매오더 단위 | O17: Purchase order unit
B18: 11 | C18: ELIKZ | E18: CHAR | F18: 1 | G18: 납품완료여부('X' : 납품완료) | H18: Whether to complete the delivery ('X': Delivery complete) | I18: 11 | J18: ClosedFlag | L18: NVARCHAR | M18: 1000 | N18: 납품완료여부('X' : 납품완료) | O18: Whether to complete the delivery ('X': Delivery complete)
B19: 12 | C19: EPSTP | E19: CHAR | F19: 1 | G19: L : 외주오더 품목 | H19: L: Outsourcing order item | I19: 12 | J19: OrderType | L19: NVARCHAR | M19: 1000 | N19: 외주오더 품목( 값이 L이면 외주 품목) | O19: L: Outsourcing order item
B20: 13 | C20: CUD_CI | E20: CHAR | F20: 1 | G20: D : 삭제 | H20: D: Delete | I20: 13 | J20: CUD | L20: NVARCHAR | M20: 1000 | N20: D : 삭제 | O20: D: Delete
B21: 14 | I21: 14
B22: 15 | I22: 15
B23: 16 | I23: 16
B24: 17 | I24: 17
B25: 18 | I25: 18
B26: 19 | I26: 19
B27: 20 | I27: 20
B28: 21 | I28: 21
B29: 22 | I29: 22
B30: 23 | I30: 23
B31: 24 | I31: 24
B32: 25 | I32: 25
... B38: 31 | I38: 31
B41: 변환규칙정의
B42: 변환규칙 | D42: 내용
B43: R1
B44: R2
B46: 기타정보
B47: 이벤트 발생조건 (DB Trigger)
B48: 연계데이터 추출조건
B49: 데이터 반영방법
B50: 기타

Sheet 구매오더 (ODM 원부자재)
A1: Top
B2: 매핑정의서 - 구매정보(ODM 원부자재) | J2: Source System | K2: SAP | O2: 문서작성일 | P2: 2025.09.25
J3: Target System | K3: APLAN | O3: 버전 | P3: 0.1
B4: 매핑정의
B5: Source Table : ZPP_IF_INFOREC_SEND_SP | I5: Target Table : ? | R5: Set Value | S5: 변환규칙
B6: RFC | I6: Web SVC | J6: PreProd : https://myamorepacificpreprod.o9solutions.com/ Prod : https://myamorepacific.o9solutions.com/
B7: SEQ | C7: Field | D7: PK | E7: Type | F7: Size | G7: Desc | H7: Desc(ENG) | I7: SEQ | J7: Field | K7: PK | L7: Type | M7: Size | N7: Desc | O7: Desc(ENG) | P7: Req No | Q7: Res No
B8: 1 | C8: MATNR | E8: CHAR | F8: 18 | G8: 자재코드 | H8: Item Code | I8: 1 | J8: Item | L8: NVARCHAR | M8: 1000 | N8: 자재코드 | O8: Item Code
B9: 2 | C9: LIFNR | E9: CHAR | F9: 10 | G9: 공급업체 | H9: Supplier | I9: 2 | J9: Supplier | L9: NVARCHAR | M9: 1000 | N9: 공급업체 | O9: Supplier
B10: 3 | C10: EKORG | E10: CHAR | F10: 4 | G10: 구매조직 | H10: Purchasing organization | I10: 3 | J10: PurchaseOrg | L10: NVARCHAR | M10: 1000 | N10: 구매조직 | O10: Purchasing organization
B11: 4 | C11: WERKS | E11: CHAR | F11: 4 | G11: 플랜트 | H11: plant | I11: 4 | J11: Plant | L11: NVARCHAR | M11: 1000 | N11: 플랜트 | O11: plant
B12: 5 | C12: ESOKZ | E12: CHAR | F12: 1 | G12: 구매정보레코드 범주 | H12: Purchase information record category | I12: 5 | J12: Category | L12: NVARCHAR | M12: 1000 | N12: 구매정보레코드 범주 | O12: Purchase information record category
B13: 6 | C13: APLFZ | E13: CHAR | F13: 3 | G13: 계획납품기간 | H13: Planning period | I13: 6 | J13: LT | L13: NVARCHAR | M13: 1000 | N13: 계획납품기간 | O13: Planning period
B14: 7 | C14: EKGRP | E14: CHAR | F14: 3 | G14: 구매그룹 | H14: Purchase group | I14: 7 | J14: ProcGroup | L14: NVARCHAR | M14: 1000 | N14: 구매그룹 | O14: Purchase group
B15: 8 | C15: DATAB | E15: DATS | F15: 8 | G15: 효력 시작일 | H15: Effective Start date | I15: 8 | J15: EffStartDate | L15: NVARCHAR | M15: 1000 | N15: 효력 시작일 | O15: Effective Start date
B16: 9 | C16: DATAI | E16: DATS | F16: 8 | G16: 효력 종료일 | H16: Effective End Date | I16: 9 | J16: EffEndDate | L16: NVARCHAR | M16: 1000 | N16: 효력 종료일 | O16: Effective End Date
B17: 10 | C17: CUD_CI | E17: CHAR | F17: 1 | G17: D : 삭제 | H17: D: Delete | I17: 10 | J17: CUD | L17: NVARCHAR | M17: 1000 | N17: D : 삭제 | O17: D: Delete
B18: 11 | C18: NETPR | E18: CHAR | F18: 15 | G18: 단가(1.구매오더,2.정보레코드) | H18: Unit price (1. Purchase Order, 2. Information Record) | I18: 11 | J18: Price | L18: NVARCHAR | M18: 1000 | N18: 단가(1.구매오더,2.정보레코드) | O18: Unit price (1. Purchase Order, 2. Information Record)
B19: 12 | C19: WAERS | E19: CUKY | F19: 5 | G19: 통화키 | H19: Currency | I19: 12 | J19: Curreny | L19: NVARCHAR | M19: 1000 | N19: 통화키 | O19: Currency
B20: 13 | I20: 13
B21: 14 | I21: 14
B22: 15 | I22: 15
B23: 16 | I23: 16
B24: 17 | I24: 17
B25: 18 | I25: 18
B26: 19 | I26: 19
B27: 20 | I27: 20
B28: 21 | I28: 21
B29: 22 | I29: 22
B30: 23 | I30: 23
B31: 24 | I31: 24
... B38: 31 | I38: 31
B41: 변환규칙정의
B42: 변환규칙 | D42: 내용
B43: R1
B44: R2
B46: 기타정보
B47: 이벤트 발생조건 (DB Trigger)
B48: 연계데이터 추출조건
B49: 데이터 반영방법
B50: 기타

Sheet 협력사마스터
A1: Top
B2: 매핑정의서 - 협력사 마스터 | J2: Source System | K2: SAP | O2: 문서작성일 | P2: 2025.09.25
J3: Target System | K3: APLAN | O3: 버전 | P3: 0.1
B4: 매핑정의
B5: Source Table : ZPP_IF_VENDOR_SEND_SP | I5: Target Table : ? | R5: Set Value | S5: 변환규칙
B6: RFC | C6: ZPP_IF_VENDOR_SEND_BM_SP | I6: Web SVC | J6: PreProd : https://myamorepacificpreprod.o9solutions.com/ Prod : https://myamorepacific.o9solutions.com/
B7: SEQ | C7: Field | D7: PK | E7: Type | F7: Size | G7: Desc | H7: Desc(ENG) | I7: SEQ | J7: Field | K7: PK | L7: Type | M7: Size | N7: Desc | O7: Desc(ENG) | P7: Req No | Q7: Res No
B8: 1 | C8: LIFNR | E8: CHAR | F8: 10 | G8: 공급업체 코드 | H8: Supplier code | I8: 1 | J8: Supplier | L8: NVARCHAR | M8: 1000 | N8: 공급업체 코드 | O8: Supplier code
B9: 2 | C9: NAME1 | E9: CHAR | F9: 35 | G9: 공급업체명 | H9: Name of supplier | I9: 2 | J9: SupplierDesc | L9: NVARCHAR | M9: 1000 | N9: 공급업체명 | O9: Name of supplier
B10: 3 | C10: BUKRS | E10: CHAR | F10: 4 | G10: 회사코드 | H10: Company code | I10: 3 | J10: Company | L10: NVARCHAR | M10: 1000 | N10: 회사코드 | O10: Company code
B11: 4 | C11: EKORG | E11: CHAR | F11: 4 | G11: 구매조직 | H11: Purchasing organization | I11: 4 | J11: PurchaseOrg | L11: NVARCHAR | M11: 1000 | N11: 구매조직 | O11: Purchasing organization
B12: 5 | C12: CUD_CI | E12: CHAR | F12: 1 | G12: D : 삭제 | H12: D: Delete | I12: 5 | J12: CUD | L12: NVARCHAR | M12: 1000 | N12: D : 삭제 | O12: D: Delete
B13: 6 | I13: 6
B14: 7 | I14: 7
B15: 8 | I15: 8
B16: 9 | I16: 9
B17: 10 | I17: 10
B18: 11 | I18: 11
B19: 12 | I19: 12
B20: 13 | I20: 13
B21: 14 | I21: 14
B22: 15 | I22: 15
B23: 16 | I23: 16
B24: 17 | I24: 17
... B38: 31 | I38: 31
B41: 변환규칙정의
B42: 변환규칙 | D42: 내용
B43: R1
B44: R2
B46: 기타정보
B47: 이벤트 발생조건 (DB Trigger)
B48: 연계데이터 추출조건
B49: 데이터 반영방법
B50: 기타

Sheet 가용화입고실적
A1: Top
B2: 매핑정의서 - 가용화 입고 실적 Available Warehousing Performance | J2: Source System | K2: SAP | O2: 문서작성일 | P2: 2025.09.25
J3: Target System | K3: APLAN | O3: 버전 | P3: 0.1
B4: 매핑정의
B5: Source Table : ? | I5: Target Table : ? | R5: Set Value | S5: 변환규칙
B6: RFC | I6: Web SVC | J6: PreProd : https://myamorepacificpreprod.o9solutions.com/ Prod : https://myamorepacific.o9solutions.com/
B7: SEQ | C7: Field | D7: PK | E7: Type | F7: Size | G7: Desc | H7: Desc(ENG) | I7: SEQ | J7: Field | K7: PK | L7: Type | M7: Size | N7: Desc | O7: Desc(ENG) | P7: Req No | Q7: Res No
B8: 1 | C8: MBLNR | D8: Y | E8: CHAR | F8: 10 | G8: 자재문서 번호 | H8: Material document number | I8: 1 | J8: DocumentID | L8: NVARCHAR | M8: 1000 | N8: 자재문서 번호 | O8: Material document number
B9: 2 | C9: MJAHR | D9: Y | E9: NUMC | F9: 4 | G9: 자재문서 연도 | H9: Materials document year | I9: 2 | J9: DocumentYear | L9: NVARCHAR | M9: 1000 | N9: 자재문서 연도 | O9: Materials document year
B10: 3 | C10: ZEILE | D10: Y | E10: NUMC | F10: 4 | G10: 자재문서 항목번호 | H10: Materials document item number | I10: 3 | J10: DeocumentNo | L10: NVARCHAR | M10: 1000 | N10: 자재문서 항목번호 | O10: Materials document item number
B11: 4 | C11: CPUDT_MKPF | D11: Y | E11: DATS | F11: 8 | G11: 입력일자(시점재고 입고일시) | H11: Input date (date and time in stock) | I11: 4 | J11: TransactionDate | L11: NVARCHAR | M11: 1000 | N11: 입력일자(시점재고 입고일시) | O11: Input date (date and time in stock)
B12: 5 | C12: CPUTM_MKPF | E12: TIMS | F12: 6 | G12: 입력시간 | H12: Input time | I12: 5 | J12: TransactionTime | L12: NVARCHAR | M12: 1000 | N12: 입력시간 | O12: Input time
B13: 6 | C13: LOCGRP | E13: CHAR | F13: 10 | G13: 로케이션 그룹 | H13: Location group | I13: 6 | J13: LocationGroup | L13: NVARCHAR | M13: 1000 | N13: 로케이션 그룹 | O13: Location group
B14: 7 | C14: MATNR | D14: Y | E14: CHAR | F14: 18 | G14: 자재코드 | H14: Material code | I14: 7 | J14: Item | L14: NVARCHAR | M14: 1000 | N14: 자재코드 | O14: Material code
B15: 8 | C15: BWART | D15: Y | E15: CHAR | F15: 3 | G15: 이동유형 | H15: Mobility | I15: 8 | J15: MovingType | L15: NVARCHAR | M15: 1000 | N15: 이동유형 | O15: Mobility
B16: 9 | C16: MENGE | E16: QUAN | F16: 13.3 | G16: 수량 | H16: quantity | I16: 9 | J16: Qty | L16: NVARCHAR | M16: 1000 | N16: 수량 | O16: quantity
B17: 10 | C17: MEINS | E17: UNIT | F17: 3 | G17: 단위 | H17: unit | I17: 10 | J17: UOM | L17: NVARCHAR | M17: 1000 | N17: 단위 | O17: unit
B18: 11 | I18: 11
B19: 12 | G19: 플랜트??? | I19: 12
B20: 13 | I20: 13
B21: 14 | I21: 14
B22: 15 | I22: 15
B23: 16 | I23: 16
B24: 17 | I24: 17
B25: 18 | I25: 18
B26: 19 | I26: 19
B27: 20 | I27: 20
B28: 21 | I28: 21
B29: 22 | I29: 22
B30: 23 | I30: 23
B31: 24 | I31: 24
... B38: 31 | I38: 31
B41: 변환규칙정의
B42: 변환규칙 | D42: 내용
B43: R1
B44: R2
B46: 기타정보
B47: 이벤트 발생조건 (DB Trigger)
B48: 연계데이터 추출조건
B49: 데이터 반영방법
B50: 기타

Sheet 협력사재고(원부자재)
A1: Top
B2: 매핑정의서 - 협력사 원부자재 재고 Inventory of suppliers raw materials | J2: Source System | K2: 구매포털 | O2: 문서작성일 | P2: 2025.09.25
J3: Target System | K3: APLAN | O3: 버전 | P3: 0.1
B4: 매핑정의
B5: Source Table : ? | I5: Target Table : ? | R5: Set Value | S5: 변환규칙
B6: RFC | I6: Web SVC | J6: PreProd : https://myamorepacificpreprod.o9solutions.com/ Prod : https://myamorepacific.o9solutions.com/
B7: SEQ | C7: Field | D7: PK | E7: Type | F7: Size | G7: Desc | H7: Desc(ENG) | I7: SEQ | J7: Field | K7: PK | L7: Type | M7: Size | N7: Desc | O7: Desc(ENG) | P7: Req No | Q7: Res No
B8: 1 | C8: VD_CD | D8: PK | E8: VARCHAR2 | F8: 18 | G8: 업체코드 | I8: 1 | J8: Item | L8: NVARCHAR | M8: 1000 | N8: 자재코드 | O8: Material code
B9: 2 | C9: FIN_PROD_CD | D9: PK | E9: VARCHAR2 | F9: 18 | G9: 7자재코드 | I9: 2 | J9: Supplier | L9: NVARCHAR | M9: 1000 | N9: 협력사코드 | O9: Supplier code
B10: 3 | C10: FIN_STK_QTY | E10: NUMBER | F10: 30,5 | G10: 7자재재고수량 | I10: 3 | J10: Qty | L10: NVARCHAR | M10: 1000 | N10: 재고수량 | O10: Stock Quantity
B11: 4 | C11: MOD_DT | E11: DATE | G11: 수정일시 | I11: 4 | J11: INV_DATE | L11: NVARCHAR | M11: 1000 | N11: 일자 | O11: Date
B12: 5 | C12: TYPE | E12: CHAR | F12: 1 | G12: O9 시스템 전송 조건 'N'전송대상, 'S'전송완료, 'E'전송에러 | I12: 5
B13: 6 | C13: MESSAGE | E13: VARCHAR2 | F13: 220 | G13: O9 전송 결과 메시지 | I13: 6
B14: 7 | I14: 7
B15: 8 | I15: 8
B16: 9 | I16: 9
B17: 10 | I17: 10
B18: 11 | I18: 11
B19: 12 | I19: 12
B20: 13 | I20: 13
B21: 14 | I21: 14
B22: 15 | I22: 15
B23: 16 | I23: 16
B24: 17 | I24: 17
B25: 18 | I25: 18
... B38: 31 | I38: 31
B41: 변환규칙정의
B42: 변환규칙 | D42: 내용
B43: R1
B44: R2
B46: 기타정보
B47: 이벤트 발생조건 (DB Trigger)
B48: 연계데이터 추출조건
B49: 데이터 반영방법
B50: 기타

Sheet SOP잔량(선적잔량)
A1: Top
B2: 매핑정의서 - SOP 잔량 Status 정보 SOP remaining information | J2: Source System | K2: SAP | O2: 문서작성일 | P2: 2025.09.25
J3: Target System | K3: APLAN | O3: 버전 | P3: 0.1
B4: 매핑정의
B5: Source Table : ZSC_PIR_O9_SAP_002 | I5: Target Table : ? | R5: Set Value | S5: 변환규칙
B6: RFC | I6: Web SVC | J6: PreProd : https://myamorepacificpreprod.o9solutions.com/ Prod : https://myamorepacific.o9solutions.com/
B7: SEQ | C7: Field | D7: PK | E7: Type | F7: Size | G7: Desc | H7: Desc(ENG) | I7: SEQ | J7: Field | K7: PK | L7: Type | M7: Size | N7: Desc | O7: Desc(ENG) | P7: Req No | Q7: Res No
B8: 1 | C8: SOP_NR | D8: Y | E8: CHAR | F8: 20 | G8: SOP 번호 | H8: SOP number | I8: 1 | J8: SOPNo | L8: NVARCHAR | M8: 1000 | N8: SOP 번호 | O8: SOP number
B9: 2 | C9: REQ_TYPE | E9: CHAR | F9: 1 | G9: 요청유형 | H9: Request type | I9: 2 | J9: ReqType | L9: NVARCHAR | M9: 1000 | N9: 요청유형 | O9: Request type
B10: 3 | C10: S_VKORG | E10: CHAR | F10: 4 | G10: 공급법인 | H10: Supply Corporation | I10: 3 | J10: FromCompany | L10: NVARCHAR | M10: 1000 | N10: 공급법인 | O10: Supply Corporation
B11: 4 | C11: R_VKORG | E11: CHAR | F11: 4 | G11: 요청법인 | H11: Request corporation | I11: 4 | J11: ToCompany | L11: NVARCHAR | M11: 1000 | N11: 요청법인 | O11: Request corporation
B12: 5 | C12: TR_AGENT | E12: CHAR | F12: 10 | G12: TR Agent | H12: Tr agent | I12: 5 | J12: TRAgent | L12: NVARCHAR | M12: 1000 | N12: TR Agent | O12: Tr agent
B13: 6 | C13: MATNR | E13: CHAR | F13: 18 | G13: 자재 번호 | H13: Material number | I13: 6 | J13: Item | L13: NVARCHAR | M13: 1000 | N13: 자재 번호 | O13: Material number
B14: 7 | C14: REQ_STATUS | E14: CHAR | F14: 1 | G14: 요청상태 | H14: Request status | I14: 7 | J14: ReqStatus | L14: NVARCHAR | M14: 1000 | N14: 요청상태 | O14: Request status
B15: 8 | C15: REQ_QTY | E15: QUAN | F15: 13 | G15: 요청량 | H15: Request Quantity | I15: 8 | J15: ReqQty | L15: NVARCHAR | M15: 1000 | N15: 요청량 | O15: Request Quantity
B16: 9 | C16: REM_QTY | E16: QUAN | F16: 13 | G16: 요청잔량 | H16: Request Remaining Quantity | I16: 9 | J16: RemainQty | L16: NVARCHAR | M16: 1000 | N16: 요청잔량 | O16: Request Remaining Quantity
B17: 10 | C17: RTN_TYPE | E17: CHAR | F17: 1 | G17: 타입 | H17: type | I17: 10 | J17: TYPE | L17: VARCHAR2 | M17: 1 | N17: 타입 | O17: type
B18: 11 | I18: 11
B19: 12 | G19: To Site_cd | H19: sap에서 맵핑된 정보임/ 아웃바운드에 있음 (cp-101) | I19: 12 | T19: 추가-20251205 ERP팀 미팅후
B20: 13 | I20: 13
B21: 14 | I21: 14
B22: 15 | I22: 15
B23: 16 | I23: 16
B24: 17 | I24: 17
B25: 18 | I25: 18
B26: 19 | I26: 19
B27: 20 | I27: 20
B28: 21 | I28: 21
B29: 22 | I29: 22
B30: 23 | I30: 23
B31: 24 | I31: 24
... B38: 31 | I38: 31
B41: 변환규칙정의
B42: 변환규칙 | D42: 내용
B43: R1
B44: R2
B46: 기타정보
B47: 이벤트 발생조건 (DB Trigger)
B48: 연계데이터 추출조건
B49: 데이터 반영방법
B50: 기타

Sheet 반제품_포장재_재고
A1: Top
B2: 매핑정의서 - 반제품 재고 Semi-product packaging material | J2: Source System | K2: SAP | O2: 문서작성일 | P2: 2025.09.25
J3: Target System | K3: APLAN | O3: 버전 | P3: 0.1
B4: 매핑정의
B5: Source Table : MD04 | I5: Target Table : ? | R5: Set Value | S5: 변환규칙
B6: RFC | I6: Web SVC | J6: PreProd : https://myamorepacificpreprod.o9solutions.com/ Prod : https://myamorepacific.o9solutions.com/
B7: SEQ | C7: Field | D7: PK | E7: Type | F7: Size | G7: Desc | H7: Desc(ENG) | I7: SEQ | J7: Field | K7: PK | L7: Type | M7: Size | N7: Desc | O7: Desc(ENG) | P7: Req No | Q7: Res No
B8: 1 | C8: MATNR | E8: CHAR | F8: 18 | G8: 자재코드 | H8: Material code | I8: 1 | J8: Item | K8: Y | L8: NVARCHAR | M8: 1000 | N8: 자재코드 | O8: Material code
B9: 2 | C9: WERKS | E9: CHAR | F9: 4 | G9: 플랜트 | H9: plant | I9: 2 | J9: Plant | K9: Y | L9: NVARCHAR | M9: 1000 | N9: 플랜트 | O9: plant
B10: 3 | C10: LABST | E10: QUAN | F10: 13.3 | G10: 가용수량 | H10: Water quantity | I10: 3 | J10: Qty | L10: NVARCHAR | M10: 1000 | N10: 반제품 재고 수량 | O10: Water quantity
B11: 4 | C11: INSME | E11: QUAN | F11: 13.3 | G11: 품질 검사 재고 | H11: Quality inspection inventory | I11: 4 | J11: QMQty | L11: NVARCHAR | M11: 1000 | N11: 품질 검사 재고 | O11: Quality inspection inventory
B12: 5 | C12: LBLAB | E12: QUAN | F12: 13.3 | G12: 공급업체 위탁수량 | H12: Supplier consignment quantity | I12: 5 | J12: VendorQty | L12: NVARCHAR | M12: 1000 | N12: 공급업체 위탁수량 | O12: Supplier consignment quantity
B13: 6 | C13: MEINS | E13: UNIT | F13: 3 | G13: 단위 | H13: unit | I13: 6 | J13: UOM | L13: NVARCHAR | M13: 1000 | N13: 단위 | O13: unit
B14: 7 | C14: SELDAT | E14: DATS | F14: 8 | G14: 일자(조회일) | H14: Date (inquiry date) | I14: 7 | J14: Date | K14: Y | L14: NVARCHAR | M14: 1000 | N14: 일자(조회일) | O14: Date (inquiry date)
B15: 8 | I15: 8
B16: 9 | I16: 9
B17: 10 | I17: 10
B18: 11 | I18: 11
B19: 12 | I19: 12
B20: 13 | I20: 13
B21: 14 | I21: 14
B22: 15 | I22: 15
B23: 16 | I23: 16
B24: 17 | I24: 17
B25: 18 | I25: 18
B26: 19 | I26: 19
... B38: 31 | I38: 31
B41: 변환규칙정의
B42: 변환규칙 | D42: 내용
B43: R1
B44: R2
B46: 기타정보
B47: 이벤트 발생조건 (DB Trigger)
B48: 연계데이터 추출조건
B49: 데이터 반영방법
B50: 기타

Sheet Role권한승인
A1: Top
B2: 매핑정의서 - Role 권한 승인 정보 Role approval information | J2: Source System | K2: IAM | O2: 문서작성일 | P2: 2025.09.25
J3: Target System | K3: APLAN | O3: 버전 | P3: 0.1
B4: 매핑정의
B5: Source Table : EX_IF_ROLE | I5: Target Table : ? | R5: Set Value | S5: 변환규칙
B6: RFC | I6: Web SVC | J6: PreProd : https://myamorepacificpreprod.o9solutions.com/ Prod : https://myamorepacific.o9solutions.com/
B7: SEQ | C7: Field | D7: PK | E7: Type | F7: Size | G7: Desc | H7: Desc(ENG) | I7: SEQ | J7: Field | K7: PK | L7: Type | M7: Size | N7: Desc | O7: Desc(ENG) | P7: Req No | Q7: Res No
B8: 1 | C8: SYS_CODE | D8: Y | E8: VARCHAR2 | F8: 64 | G8: 시스템코드 | H8: System code | I8: 1
B9: 2 | C9: PERNR | D9: Y | E9: VARCHAR2 | F9: 20 | G9: 로그인 아이디 | H9: Login ID | I9: 2 | J9: UserID | K9: Y | L9: NVARCHAR | M9: 1000 | N9: 사번 | O9: Employee Number
B10: 3 | C10: ROLE_CODE | D10: Y | E10: VARCHAR2 | F10: 30 | G10: 역할 코드정보 | H10: Role Code Information | I10: 3 | J10: UserRole | K10: Y | L10: NVARCHAR | M10: 1000 | N10: Role | O10: Role
B11: 4 | C11: MOD_DT | E11: DATE | G11: 변경일 | H11: Change date | I11: 4 | J11: UpdateDate | L11: NVARCHAR | M11: 1000 | N11: 변경일 | O11: Change date
B12: 5 | C12: REG_DT | E12: DATE | G12: 등록일 | H12: Registration date | I12: 5 | J12: CreateDate | L12: NVARCHAR | M12: 1000 | N12: 등록일 | O12: Registration date
B13: 6 | I13: 6 | J13: CUD | L13: NVARCHAR | M13: 1000 | N13: CUD(EAI에서 셋팅) | O13: CUD
B14: 7 | I14: 7
B15: 8 | I15: 8
B16: 9 | I16: 9
B17: 10 | I17: 10
B18: 11 | I18: 11
B19: 12 | I19: 12
B20: 13 | I20: 13
B21: 14 | I21: 14
B22: 15 | I22: 15
B23: 16 | I23: 16
B24: 17 | I24: 17
B25: 18 | I25: 18
... B38: 31 | I38: 31
B41: 변환규칙정의
B42: 변환규칙 | D42: 내용
B43: R1
B44: R2
B46: 기타정보
B47: 이벤트 발생조건 (DB Trigger)
B48: 연계데이터 추출조건
B49: 데이터 반영방법
B50: 기타

Sheet 계정승인
A1: Top
B2: 매핑정의서 - 계정 승인 정보 Account approval information | J2: Source System | K2: IAM | O2: 문서작성일 | P2: 2025.09.25
J3: Target System | K3: APLAN | O3: 버전 | P3: 0.1
B4: 매핑정의
B5: Source Table : EX_IF_USER, EX_IF_RES_USER | I5: Target Table : ? | R5: Set Value | S5: 변환규칙
B6: RFC | I6: Web SVC | J6: PreProd : https://myamorepacificpreprod.o9solutions.com/ Prod : https://myamorepacific.o9solutions.com/
B7: SEQ | C7: Field | D7: PK | E7: Type | F7: Size | G7: Desc | H7: Desc(ENG) | I7: SEQ | J7: Field | K7: PK | L7: Type | M7: Size | N7: Desc | O7: Desc(ENG) | P7: Req No | Q7: Res No
B8: 1 | C8: SNAME | E8: VARCHAR2 | F8: 60 | G8: 이름 | H8: name | I8: 1 | J8: UserName | L8: NVARCHAR | M8: 1000 | N8: 이름 | O8: name
B9: 2 | C9: EMAIL | E9: VARCHAR2 | F9: 80 | G9: Email | H9: Email | I9: 2 | J9: UserEmail | L9: NVARCHAR | M9: 1000 | N9: Email | O9: Email
B10: 3 | C10: PERNR | E10: VARCHAR2 | F10: 20 | G10: 사번 | H10: Employee Number | I10: 3 | J10: UserID | L10: NVARCHAR | M10: 1000 | N10: 사번 | O10: Employee Number
B11: 4 | C11: DEL_DT | E11: DATE | G11: 삭제일 | H11: Deletion date | I11: 4 | J11: DeleteDate | L11: NVARCHAR | M11: 1000 | N11: 삭제일 | O11: Deletion date
B12: 5 | C12: MOD_DT | E12: DATE | G12: 수정일시 | H12: Modified date and time | I12: 5 | J12: UpdateDate | L12: NVARCHAR | M12: 1000 | N12: 수정일시 | O12: Modified date and time
B13: 6 | C13: REG_DT | E13: DATE | G13: 등록일 | H13: Registration date | I13: 6 | J13: CreateDate | L13: NVARCHAR | M13: 1000 | N13: 등록일 | O13: Registration date
B14: 7 | G14: CUD(상세 설명 하단 참조) | H14: CUD (see the bottom description below) | I14: 7 | J14: CUD | L14: NVARCHAR | M14: 1000 | N14: CUD | O14: CUD (see the bottom description below)
B15: 8 | I15: 8
B16: 9 | I16: 9
B17: 10 | I17: 10
B18: 11 | I18: 11
B19: 12 | I19: 12
B20: 13 | I20: 13
B21: 14 | I21: 14
B22: 15 | I22: 15
B23: 16 | I23: 16
B24: 17 | I24: 17
B25: 18 | I25: 18
B26: 19 | I26: 19
... B38: 31 | I38: 31
B41: 변환규칙정의
B42: 변환규칙 | D42: 내용
B43: R1
B44: R2
B46: 기타정보
B47: 이벤트 발생조건 (DB Trigger) | D47: 1) 싱글플랫폼에 처음으로 권한이 등록되는 신규 유저의 경우에는 CUD 필드값을 "C"로 하여 전송 2) 기존에 싱글플랫폼에 권한 등록된 유저에게 권한이 추가되는 경우에는 추가되는 권한명을 Role 필드에, CUD 필드값은 "U"로 하여 전송 3) 기존에 싱글플랫폼에 권한 등록된 유저의 권한이 제거되는 경우에는 제거되는 권한명을 Role 필드에, CUD 필드값은 "D"로 하여 전송 4) 부서가 변경되어 기본 권한이 부여되는 유저의 경우 기본 권한명을 Role 필드에, CUD 필드값은 "U"로 하여 전송 1) For new users whose permissions are registered on a single platform for the first time, send the CUD field value to "C" 2) If permissions are added to a user who has previously registered permissions on a single platform, send the added permission name to the Role field and the CUD field value to "U" 3) If the permission of a user who has previously registered permissions on a single platform is removed, send the permission name to the Role field and the CUD field value to "D" 4) Send default permission name to Role field and CUD field value to "U" for users who are given default permissions due to department changes
B48: 연계데이터 추출조건
B49: 데이터 반영방법
B50: 기타

Sheet CP코드마스터
A1: Top
B2: 매핑정의서 - CP 코드 마스터 CP code master | J2: Source System | K2: SAP | O2: 문서작성일 | P2: 2025.09.25
J3: Target System | K3: APLAN | O3: 버전 | P3: 0.1
B4: 매핑정의
B5: Source Table : ZSD_SEND_TEXT_01 | I5: Target Table : ALIFCI_CP_CD_MSTR | R5: Set Value | S5: 변환규칙
B6: RFC | I6: Web SVC | J6: PreProd : https://myamorepacificpreprod.o9solutions.com/ Prod : https://myamorepacific.o9solutions.com/
B7: SEQ | C7: Field | D7: PK | E7: Type | F7: Size | G7: Desc | H7: Desc(ENG) | I7: SEQ | J7: Field | K7: PK | L7: Type | M7: Size | N7: Desc | O7: Desc(ENG) | P7: Req No | Q7: Res No
B8: 1 | C8: CODE | E8: CHAR | F8: 10 | G8: Code | H8: Code | I8: 1 | J8: Code | L8: NVARCHAR | M8: 1000 | N8: Code | O8: Code
B9: 2 | C9: CODENM | E9: CHAR | F9: 50 | G9: Code Description | H9: Code Description | I9: 2 | J9: CodeDesc | L9: NVARCHAR | M9: 1000 | N9: Code Description | O9: Code Description
B10: 3 | C10: CODEKEY | E10: CHAR | F10: 10 | G10: 코드키 | H10: Code key | I10: 3 | J10: CodeKey | L10: NVARCHAR | M10: 1000 | N10: 코드키 | O10: Code key
B11: 4 | C11: LANGU | E11: CHAR | F11: 2 | G11: 언어 | H11: language | I11: 4 | J11: Lang | L11: NVARCHAR | M11: 1000 | N11: 언어 | O11: language
B12: 5 | C12: CODEKEY_DESC | E12: CHAR | F12: 50 | G12: 코드키내역 | H12: Code Keynae Station | I12: 5 | J12: CodeKeyDesc | L12: NVARCHAR | M12: 1000 | N12: 코드키내역 | O12: Code Keynae Station
B13: 6 | C13: ZMODE | E13: CHAR | F13: 1 | G13: 'I' (Insert) , 'U'(Update), 'D'(Delete) | H13: 'I' (INSERT), 'U' (update), 'D' (Delete) | I13: 6 | J13: CUD | L13: NVARCHAR | M13: 1000 | N13: 'I' (Insert) , 'U'(Update), 'D'(Delete) | O13: 'I' (INSERT), 'U' (update), 'D' (Delete)
B14: 7 | C14: TFLG | E14: CHAR | F14: 1 | G14: 이관 Flag | H14: Transfer flag | I14: 7 | J14: Transflag | L14: NVARCHAR | M14: 1000 | N14: 이관 Flag | O14: Transfer flag
B15: 8 | I15: 8
B16: 9 | I16: 9
B17: 10 | I17: 10
B18: 11 | I18: 11
B19: 12 | I19: 12
B20: 13 | I20: 13
B21: 14 | I21: 14
B22: 15 | I22: 15
B23: 16 | I23: 16
B24: 17 | I24: 17
B25: 18 | I25: 18
B26: 19 | I26: 19
... B38: 31 | I38: 31
B41: 변환규칙정의
B42: 변환규칙 | D42: 내용
B43: R1
B44: R2
B46: 기타정보
B47: 이벤트 발생조건 (DB Trigger)
B48: 연계데이터 추출조건
B49: 데이터 반영방법
B50: 기타
B52: ID#AAAAwkmaw3M
B53: AC800097 (2023-05-11 05:12:59)
B54: A001 회사코드
B55: A002 국가코드
B56: A003 영업조직코드
... B62: ** 2025-11-25
B63: A001 | C63: 회사코드
B64: A002 | C64: 국가코드
B65: A003 | C65: 영업조직코드
B66: A004 | C66: BU코드
B67: A005 | C67: 하위영업경로코드
B68: A006 | C68: PG그룹코드
B69: A007 | C69: PG유형코드
B70: A008 | C70: 브랜드그룹
B71: A009 | C71: 자재유형
B72: A010 | C72: 제품용도
B73: A011 | C73: 세트구분
B74: A012 | C74: 제품계층구조
... B99: B013 | C99: 제품카테고리

Sheet 공장달력 인터페이스
A1: Top
B2: 매핑정의서 - 공장달력 인터페이스 Plant Calendar Interface | J2: Source System | K2: SAP | O2: 문서작성일 | P2: 2025.09.25
J3: Target System | K3: APLAN | O3: 버전 | P3: 0.1
B4: 매핑정의
B5: Source Table : ZME_MES_FACTORY_CAL | I5: Target Table : ? | R5: Set Value | S5: 변환규칙
B6: RFC | I6: Web SVC
B7: SEQ | C7: Field | D7: PK | E7: Type | F7: Size | G7: Desc | H7: Desc(ENG) | I7: SEQ | J7: Field | K7: PK | L7: Type | M7: Size | N7: Desc | O7: Desc(ENG) | P7: Req No | Q7: Res No
B8: 1 | C8: IDENT | E8: CHAR | F8: 2 | G8: 공장 달력 | H8: Plant Calendar | I8: 1 | J8: CalendarID | L8: nvarchar | M8: 1000 | N8: 공장 달력 ID | O8: Plant Calendar
B9: 2 | C9: JAHR | E9: NUMC | F9: 4 | G9: 저장연도 | H9: Zetal | I9: 2 | J9: Year | L9: nvarchar | M9: 1000 | N9: 연도 | O9: Zetal
B10: 3 | C10: WERKS | E10: CHAR | F10: 4 | G10: 플랜트 | H10: plant | I10: 3 | J10: Plant | L10: nvarchar | M10: 1000 | N10: Plnt | O10: plant
B11: 4 | C11: CUD_CI | E11: CHAR | F11: 1 | G11: CUD 구분 | H11: CUD classification | I11: 4 | J11: CUD | L11: nvarchar | M11: 1000 | N11: CUD 구분 | O11: CUD classification
B12: 5 | C12: MON01 | E12: CHAR | F12: 31 | G12: 달력: 일 수(월) | H12: Calendar: Daily (Mon) | I12: 5 | J12: M1 | L12: nvarchar | M12: 1000 | N12: Month1 | O12: Calendar: Daily (Mon)
B13: 6 | C13: MON02 | E13: CHAR | F13: 31 | G13: 달력: 일 수(월) | H13: Calendar: Daily (Mon) | I13: 6 | J13: M2 | L13: nvarchar | M13: 1000 | N13: Month2 | O13: Calendar: Daily (Mon)
B14: 7 | C14: MON03 | E14: CHAR | F14: 31 | G14: 달력: 일 수(월) | H14: Calendar: Daily (Mon) | I14: 7 | J14: M3 | L14: nvarchar | M14: 1000 | N14: Month3 | O14: Calendar: Daily (Mon)
B15: 8 | C15: MON04 | E15: CHAR | F15: 31 | G15: 달력: 일 수(월) | H15: Calendar: Daily (Mon) | I15: 8 | J15: M4 | L15: nvarchar | M15: 1000 | N15: Month4 | O15: Calendar: Daily (Mon)
B16: 9 | C16: MON05 | E16: CHAR | F16: 31 | G16: 달력: 일 수(월) | H16: Calendar: Daily (Mon) | I16: 9 | J16: M5 | L16: nvarchar | M16: 1000 | N16: Month5 | O16: Calendar: Daily (Mon)
B17: 10 | C17: MON06 | E17: CHAR | F17: 31 | G17: 달력: 일 수(월) | H17: Calendar: Daily (Mon) | I17: 10 | J17: M6 | L17: nvarchar | M17: 1000 | N17: Month6 | O17: Calendar: Daily (Mon)
B18: 11 | C18: MON07 | E18: CHAR | F18: 31 | G18: 달력: 일 수(월) | H18: Calendar: Daily (Mon) | I18: 11 | J18: M7 | L18: nvarchar | M18: 1000 | N18: Month7 | O18: Calendar: Daily (Mon)
B19: 12 | C19: MON08 | E19: CHAR | F19: 31 | G19: 달력: 일 수(월) | H19: Calendar: Daily (Mon) | I19: 12 | J19: M8 | L19: nvarchar | M19: 1000 | N19: Month8 | O19: Calendar: Daily (Mon)
... B26: 19 | C26: WENUM | E26: NUMC | F26: 3 | G26: 연간 근무일 수 | H26: The number of annual work | I26: 19 | J26: WorkingDayCount | L26: nvarchar | M26: 1000 | N26: 연간 근무일 수 | O26: The number of annual work
B27: 20 | I27: 20
B28: 21 | I28: 21
B29: 22 | I29: 22
B30: 23 | I30: 23
B31: 24 | I31: 24
B32: 25 | I32: 25
B33: 26 | I33: 26
B34: 27 | I34: 27
B35: 28 | I35: 28
B36: 29 | I36: 29
B37: 30 | I37: 30
B38: 31 | I38: 31
B41: 변환규칙정의
B42: 변환규칙 | D42: 내용
B43: R1
B44: R2
B46: 기타정보
B47: 이벤트 발생조건 (DB Trigger)
B48: 연계데이터 추출조건
B49: 데이터 반영방법
B50: 기타
B52: ID#AAAAwkmaw3M
B53: AC800097 (2023-05-11 05:12:59)
B54: A001 회사코드
B55: A002 국가코드
B56: A003 영업조직코드
... B60: A007 PG유형코드로 정의하고 코드키를 보내드릴 것입니다. SAP기준으로 맵핑 부탁드립니다.

Sheet 유통사 판매 재고
A1: Top
B2: 매핑정의서 - 유통사 판매 재고 | J2: Source System | K2: CDP | O2: 문서작성일 | P2: 2025.09.25
J3: Target System | K3: APLAN | O3: 버전 | P3: 0.1
B4: 매핑정의
B5: Source Table : cdp.sf_cdpdw.F_DSTR_INVN_HIST | I5: Target Table : ? | R5: Set Value | S5: 변환규칙
B6: RFC | I6: Web SVC
B7: SEQ | C7: Field | D7: PK | E7: Type | F7: Size | G7: Desc | H7: Desc(ENG) | I7: SEQ | J7: Field | K7: PK | L7: Type | M7: Size | N7: Desc | O7: Desc(ENG) | P7: Req No | Q7: Res No
B8: 1 | C8: STND_YMD | E8: CHAR | G8: 기준년월일자 | I8: 1 | J8: STND_YMD | L8: NVARCHAR2 | M8: 1000 | N8: 기준년월일자
B9: 2 | C9: CNTR_CD | E9: CHAR | G9: 국가코드 | H9: Country Code. | I9: 2 | J9: CNTR_CD | L9: NVARCHAR2 | M9: 1000 | N9: 국가코드 | O9: Country Code.
B10: 3 | C10: CNTR_GRP_CD | E10: CHAR | G10: 국가그룹코드 | H10: Country Group Code | I10: 3 | J10: CNTR_GRP_CD | L10: NVARCHAR2 | M10: 1000 | N10: 국가그룹코드 | O10: Country Group Code
B11: 4 | C11: CLCT_MTHD_CD | E11: CHAR | G11: 수집방법코드 | I11: 4 | J11: CLCT_MTHD_CD | L11: NVARCHAR2 | M11: 1000 | N11: 수집방법코드
B12: 5 | C12: DSTR_CD | E12: CHAR | G12: 유통사코드 | H12: Distribution Code. | I12: 5 | J12: DSTR_CD | L12: NVARCHAR2 | M12: 1000 | N12: 유통사코드 | O12: Distribution Code.
B13: 6 | C13: SLS_ORG_CD | E13: CHAR | G13: 영업조직코드 | I13: 6 | J13: SLS_ORG_CD | L13: NVARCHAR2 | M13: 1000 | N13: 영업조직코드
B14: 7 | C14: PRTN_Q_CD | E14: CHAR | G14: 거래처Q코드 | I14: 7 | J14: PRTN_Q_CD | L14: NVARCHAR2 | M14: 1000 | N14: 거래처Q코드
B15: 8 | C15: PRTN_ID | E15: CHAR | G15: 거래처코드 | H15: Partner Code | I15: 8 | J15: PRTN_ID | L15: NVARCHAR2 | M15: 1000 | N15: 거래처코드 | O15: Partner Code
B16: 9 | C16: DSTR_SHOP_CD | E16: CHAR | G16: 유통사매장코드 | I16: 9 | J16: DSTR_SHOP_CD | L16: NVARCHAR2 | M16: 1000 | N16: 유통사매장코드
B17: 10 | C17: DSTR_SHOP_NM | E17: CHAR | G17: 유통사매장명 | I17: 10 | J17: DSTR_SHOP_NM | L17: NVARCHAR2 | M17: 1000 | N17: 유통사매장명
B18: 11 | C18: BRND_CD | E18: CHAR | G18: 브랜드코드 | I18: 11 | J18: BRND_CD | L18: NVARCHAR2 | M18: 1000 | N18: 브랜드코드
B19: 12 | C19: DSTR_SKU_ID | E19: CHAR | G19: 유통사상품코드 | I19: 12 | J19: DSTR_SKU_ID | L19: NVARCHAR2 | M19: 1000 | N19: 유통사상품코드
B20: 13 | C20: DSTR_SKU_NM | E20: CHAR | G20: 유통사상품명 | I20: 13 | J20: DSTR_SKU_NM | L20: NVARCHAR2 | M20: 1000 | N20: 유통사상품명
B21: 14 | C21: PRD_BRCD_CD | E21: CHAR | G21: 상품바코드코드 | I21: 14 | J21: PRD_BRCD_CD | L21: NVARCHAR2 | M21: 1000 | N21: 상품바코드코드
B22: 15 | C22: PRD_CD | E22: CHAR | G22: 상품코드 | I22: 15 | J22: PRD_CD | L22: NVARCHAR2 | M22: 1000 | N22: 상품코드
B23: 16 | C23: CURR_CD | E23: CHAR | G23: 통화코드 | I23: 16 | J23: CURR_CD | L23: NVARCHAR2 | M23: 1000 | N23: 통화코드
B24: 17 | C24: INVN_QTY | E24: CHAR | G24: 재고수량 | I24: 17 | J24: INVN_QTY | L24: NVARCHAR2 | M24: 1000 | N24: 재고수량
B25: 18 | C25: WRHS_QTY | E25: CHAR | G25: 입고수량 | H25: 주문수량 | I25: 18 | J25: WRHS_QTY | L25: NVARCHAR2 | M25: 1000 | N25: 입고수량 | O25: 주문수량
B26: 19 | C26: RLS_QTY | E26: CHAR | G26: 출고수량 | I26: 19 | J26: RLS_QTY | L26: NVARCHAR2 | M26: 1000 | N26: 출고수량
B27: 20 | C27: PRCH_PRPR | E27: CHAR | G27: 매입원가 | I27: 20 | J27: PRCH_PRPR | L27: NVARCHAR2 | M27: 1000 | N27: 매입원가
B28: 21 | C28: ORN_INSD_UTPR_AMT | E28: CHAR | G28: 발생통화내부단가금액 | I28: 21 | J28: ORN_INSD_UTPR_AMT | L28: NVARCHAR2 | M28: 1000 | N28: 발생통화내부단가금액
B29: 22 | C29: INSD_UTPR_AMT | E29: CHAR | G29: 내부단가금액 | I29: 22 | J29: INSD_UTPR_AMT | L29: NVARCHAR2 | M29: 1000 | N29: 내부단가금액
B30: 23 | C30: ETL_PROC_DTTM | E30: CHAR | G30: ETL처리일시 | H30: ETL Processing Date.' | I30: 23 | J30: ETL_PROC_DTTM | L30: NVARCHAR2 | M30: 1000 | N30: ETL처리일시 | O30: ETL Processing Date.'
B31: 24 | I31: 24
B32: 25 | I32: 25
B33: 26 | I33: 26
B34: 27 | I34: 27
B35: 28 | I35: 28
B36: 29 | I36: 29
B37: 30 | I37: 30
B38: 31 | I38: 31
B41: 변환규칙정의
B42: 변환규칙 | D42: 내용
B43: R1
B44: R2
B46: 기타정보
B47: 이벤트 발생조건 (DB Trigger)
B48: 연계데이터 추출조건
B49: 데이터 반영방법
B50: 기타
B52: ID#AAAAwkmaw3M
B53: AC800097 (2023-05-11 05:12:59)
B54: A001 회사코드
B55: A002 국가코드
B56: A003 영업조직코드
... B60: A007 PG유형코드로 정의하고 코드키를 보내드릴 것입니다. SAP기준으로 맵핑 부탁드립니다.

Sheet 유통사 판매 재고_월
A1: Top
B2: 매핑정의서 - 유통사 판매 재고(월집계) | J2: Source System | K2: CDP | O2: 문서작성일 | P2: 2025.09.25
J3: Target System | K3: APLAN | O3: 버전 | P3: 0.1
B4: 매핑정의
B5: Source Table : cdp.sf_cdpdw.F_DSTR_INVN_M_HIST | I5: Target Table : ? | R5: Set Value | S5: 변환규칙
B6: RFC | I6: Web SVC
B7: SEQ | C7: Field | D7: PK | E7: Type | F7: Size | G7: Desc | H7: Desc(ENG) | I7: SEQ | J7: Field | K7: PK | L7: Type | M7: Size | N7: Desc | O7: Desc(ENG) | P7: Req No | Q7: Res No
B8: 1 | C8: STND_YM DATE | E8: CHAR | G8: 기준년월 | I8: 1 | J8: STND_YM DATE | L8: nvarchar2 | M8: 1000 | N8: 기준년월
B9: =+B8+1 -> 2 | C9: CNTR_CD | E9: CHAR | G9: 국가코드 | H9: Country Code. | I9: 2 | J9: CNTR_CD | L9: nvarchar2 | M9: 1000 | N9: 국가코드 | O9: Country Code.
B10: =+B9+1 -> 3 | C10: CNTR_GRP_CD | E10: CHAR | G10: 국가그룹코드 | H10: Country Group Code | I10: 3 | J10: CNTR_GRP_CD | L10: nvarchar2 | M10: 1000 | N10: 국가그룹코드 | O10: Country Group Code
B11: =+B10+1 -> 4 | C11: CLCT_MTHD_CD | E11: CHAR | G11: 수집방법코드 | I11: 4 | J11: CLCT_MTHD_CD | L11: nvarchar2 | M11: 1000 | N11: 수집방법코드
B12: =+B11+1 -> 5 | C12: DSTR_CD | E12: CHAR | G12: 유통사코드 | H12: Distribution Code. | I12: 5 | J12: DSTR_CD | L12: nvarchar2 | M12: 1000 | N12: 유통사코드 | O12: Distribution Code.
B13: =+B12+1 -> 6 | C13: SLS_ORG_CD | E13: CHAR | G13: 영업조직코드 | I13: 6 | J13: SLS_ORG_CD | L13: nvarchar2 | M13: 1000 | N13: 영업조직코드
B14: =+B13+1 -> 7 | C14: PRTN_Q_CD | E14: CHAR | G14: 거래처Q코드 | J14: PRTN_Q_CD | L14: nvarchar2 | M14: 1000 | N14: 거래처Q코드
C15: PRTN_ID | E15: CHAR | G15: =VLOOKUP(C15,'유통사 판매 재고'!$C$8:$G$30,5,0) -> 거래처코드 | J15: PRTN_ID | L15: nvarchar2 | M15: 1000 | N15: 거래처코드
C16: DSTR_SHOP_CD | E16: CHAR | G16: =VLOOKUP(C16,'유통사 판매 재고'!$C$8:$G$30,5,0) -> 유통사매장코드 | J16: DSTR_SHOP_CD | L16: nvarchar2 | M16: 1000 | N16: 유통사매장코드
C17: DSTR_SHOP_NM | E17: CHAR | G17: =VLOOKUP(C17,'유통사 판매 재고'!$C$8:$G$30,5,0) -> 유통사매장명 | J17: DSTR_SHOP_NM | L17: nvarchar2 | M17: 1000 | N17: 유통사매장명
C18: BRND_CD | E18: CHAR | G18: =VLOOKUP(C18,'유통사 판매 재고'!$C$8:$G$30,5,0) -> 브랜드코드 | J18: BRND_CD | L18: nvarchar2 | M18: 1000 | N18: 브랜드코드
C19: DSTR_SKU_ID | E19: CHAR | G19: =VLOOKUP(C19,'유통사 판매 재고'!$C$8:$G$30,5,0) -> 유통사상품코드 | J19: DSTR_SKU_ID | L19: nvarchar2 | M19: 1000 | N19: 유통사상품코드
C20: DSTR_SKU_NM | E20: CHAR | G20: =VLOOKUP(C20,'유통사 판매 재고'!$C$8:$G$30,5,0) -> 유통사상품명 | J20: DSTR_SKU_NM | L20: nvarchar2 | M20: 1000 | N20: 유통사상품명
C21: PRD_BRCD_CD | E21: CHAR | G21: =VLOOKUP(C21,'유통사 판매 재고'!$C$8:$G$30,5,0) -> 상품바코드코드 | J21: PRD_BRCD_CD | L21: nvarchar2 | M21: 1000 | N21: 상품바코드코드
C22: PRD_CD | E22: CHAR | G22: =VLOOKUP(C22,'유통사 판매 재고'!$C$8:$G$30,5,0) -> 상품코드 | J22: PRD_CD | L22: nvarchar2 | M22: 1000 | N22: 상품코드
C23: CURR_CD | E23: CHAR | G23: =VLOOKUP(C23,'유통사 판매 재고'!$C$8:$G$30,5,0) -> 통화코드 | J23: CURR_CD | L23: nvarchar2 | M23: 1000 | N23: 통화코드
C24: INVN_QTY | E24: CHAR | G24: =VLOOKUP(C24,'유통사 판매 재고'!$C$8:$G$30,5,0) -> 재고수량 | J24: INVN_QTY | L24: nvarchar2 | M24: 1000 | N24: 재고수량
C25: WRHS_QTY | E25: CHAR | G25: =VLOOKUP(C25,'유통사 판매 재고'!$C$8:$G$30,5,0) -> 입고수량 | J25: WRHS_QTY | L25: nvarchar2 | M25: 1000 | N25: 입고수량
C26: RLS_QTY | E26: CHAR | G26: =VLOOKUP(C26,'유통사 판매 재고'!$C$8:$G$30,5,0) -> 출고수량 | J26: RLS_QTY | L26: nvarchar2 | M26: 1000 | N26: 출고수량
... C30: ETL_PROC_DTTM | E30: CHAR | G30: =VLOOKUP(C30,'유통사 판매 재고'!$C$8:$G$30,5,0) -> ETL처리일시 | J30: ETL_PROC_DTTM | L30: nvarchar2 | M30: 1000 | N30: ETL처리일시
B32: =+B14+1 -> 8 | C32: PRD_CD | E32: CHAR | G32: 상품코드 | I32: 7
B33: =+B32+1 -> 9 | C33: CURR_CD | E33: CHAR | G33: 통화코드 | I33: 8
B34: =+B33+1 -> 10 | C34: INVN_ST_CD | E34: CHAR | G34: 재고상태코드 | I34: 9
B35: =+B34+1 -> 11 | C35: INVN_QTY | E35: CHAR | G35: 재고수량 | I35: 10
B36: =+B35+1 -> 12 | C36: ORN_INVN_AMT | E36: CHAR | G36: 발생통화재고금액 | I36: 11
B37: =+B36+1 -> 13 | C37: INVN_AMT | E37: CHAR | G37: 재고금액 | I37: 12
B38: =+B37+1 -> 14 | C38: WRHS_QTY | E38: CHAR | G38: 입고수량 | I38: 13
B39: =+B38+1 -> 15 | C39: RLS_QTY | E39: CHAR | G39: 출고수량 | I39: 14
B40: =+B39+1 -> 16 | C40: ORN_RLS_AMT | E40: CHAR | G40: 발생통화_출고금액 | I40: 15
B41: =+B40+1 -> 17 | C41: RLS_AMT | E41: CHAR | G41: 출고금액 | I41: 16
B42: =+B41+1 -> 18 | C42: ORN_ACCM_INVN_AMT | E42: CHAR | G42: 발생통화누적재고금액 | I42: 17
B43: =+B42+1 -> 19 | C43: ORN_ACCM_RLS_AMT | E43: CHAR | G43: 발생통화누적출고금액 | I43: 18
B44: =+B43+1 -> 20 | C44: ORN_DSMN_BF_ACNT_SAL_AMT | E44: CHAR | G44: 발생통화해체전순매출금액 | I44: 19
... B49: =+B48+1 -> 25 | C49: ETL_PROC_DTTM TIMESTAMP | E49: CHAR | G49: ETL처리일시 | I49: 24
B50: =+B49+1 -> 26 | I50: 25
B51: =+B50+1 -> 27 | I51: 26
B52: =+B51+1 -> 28 | I52: 27
B53: =+B52+1 -> 29 | I53: 28
B54: =+B53+1 -> 30 | I54: 29
B55: =+B54+1 -> 31 | I55: 30
B56: =+B55+1 -> 32 | I56: 31
B59: 변환규칙정의
B60: 변환규칙 | D60: 내용
B61: R1
B62: R2
B64: 기타정보
B65: 이벤트 발생조건 (DB Trigger)
B66: 연계데이터 추출조건
B67: 데이터 반영방법
B68: 기타
B70: ID#AAAAwkmaw3M
B71: AC800097 (2023-05-11 05:12:59)
B72: A001 회사코드
B73: A002 국가코드
B74: A003 영업조직코드
... B78: A007 PG유형코드로 정의하고 코드키를 보내드릴 것입니다. SAP기준으로 맵핑 부탁드립니다.

Sheet 유통사 오더수량
A1: Top
B2: 매핑정의서 - 유통사 오더수량(발수) | J2: Source System | K2: CDP | O2: 문서작성일 | P2: 2025.09.25
J3: Target System | K3: APLAN | O3: 버전 | P3: 0.1
B4: 매핑정의
B5: Source Table : | I5: Target Table : ? | R5: Set Value | S5: 변환규칙
B6: RFC | I6: Web SVC
B7: SEQ | C7: Field | D7: PK | E7: Type | F7: Size | G7: Desc | H7: Desc(ENG) | I7: SEQ | J7: Field | K7: PK | L7: Type | M7: Size | N7: Desc | O7: Desc(ENG) | P7: Req No | Q7: Res No
B8: 1 | I8: 1
B9: 2 | I9: 2
B10: 3 | I10: 3
B11: 4 | I11: 4
B12: 5 | I12: 5
B13: 6 | I13: 6
B14: 7 | I14: 7
B15: 8 | I15: 8
B16: 9 | I16: 9
B17: 10 | I17: 10
B18: 11 | I18: 11
B19: 12 | I19: 12
... B38: 31 | I38: 31
B41: 변환규칙정의
B42: 변환규칙 | D42: 내용
B43: R1
B44: R2
B46: 기타정보
B47: 이벤트 발생조건 (DB Trigger)
B48: 연계데이터 추출조건
B49: 데이터 반영방법
B50: 기타
B52: ID#AAAAwkmaw3M
B53: AC800097 (2023-05-11 05:12:59)
B54: A001 회사코드
B55: A002 국가코드
B56: A003 영업조직코드
... B60: A007 PG유형코드로 정의하고 코드키를 보내드릴 것입니다. SAP기준으로 맵핑 부탁드립니다.

Sheet 재고 Aging 상태
A1: Top
B2: 매핑정의서 - 재고 Aging 상태 | J2: Source System | K2: CDP | O2: 문서작성일 | P2: 2025.09.25
J3: Target System | K3: APLAN | O3: 버전 | P3: 0.1
B4: 매핑정의 | G4: CDP.SF_CDPDW.TEMP_AP3505195_F_GWMS_QW_HIST
B5: Source Table : SF_CDPDW.TEMP_AP3505195_F_GWMS_QW_HIST(임시) | I5: Target Table : ? | R5: Set Value | S5: 변환규칙
B6: RFC | I6: Web SVC
B7: SEQ | C7: Field | D7: PK | E7: Type | F7: Size | G7: Desc | H7: Desc(ENG) | I7: SEQ | J7: Field | K7: PK | L7: Type | M7: Size | N7: Desc | O7: Desc(ENG) | P7: Req No | Q7: Res No
B8: 1 | C8: VALUE | I8: 1 | J8: VALUE_VAL | L8: nvarchar2 | M8: 1000
B9: =+B8+1 -> 2 | C9: PARTITIONKEY | I9: 2 | J9: PARTITIONKEY | L9: nvarchar2 | M9: 1000
B10: =+B9+1 -> 3 | C10: COUNTRY | G10: 국가 | I10: 3 | J10: COUNTRY | L10: nvarchar2 | M10: 1000 | N10: 국가
B11: =+B10+1 -> 4 | C11: PROVIDER_NAME | G11: 3PL Provider Name | I11: 4 | J11: PROVIDER_NAME | L11: nvarchar2 | M11: 1000 | N11: 3PL Provider Name
B12: =+B11+1 -> 5 | C12: CLIENT | G12: 화주 | I12: 5 | J12: CLIENT | L12: nvarchar2 | M12: 1000 | N12: 화주
B13: =+B12+1 -> 6 | C13: PLANT | G13: 플랜트 | I13: 6 | J13: PLANT | L13: nvarchar2 | M13: 1000 | N13: 플랜트
B14: =+B13+1 -> 7 | C14: BRAND_NAME | G14: 브랜드명 | J14: BRAND_NAME | L14: nvarchar2 | M14: 1000 | N14: 브랜드명
B15: =+B14+1 -> 8 | C15: SKU | G15: 제품코드 | J15: SKU | L15: nvarchar2 | M15: 1000 | N15: 제품코드
B16: =+B15+1 -> 9 | C16: PRODUCT_NAME | G16: 제품명(현지) | J16: PRODUCT_NAME | L16: nvarchar2 | M16: 1000 | N16: 제품명(현지)
B17: =+B16+1 -> 10 | C17: STORAGE_BIN | G17: 저장빈 | J17: STORAGE_BIN | L17: nvarchar2 | M17: 1000 | N17: 저장빈
B18: =+B17+1 -> 11 | C18: QTY | G18: 가용수량 | J18: QTY | L18: nvarchar2 | M18: 1000 | N18: 가용수량
B19: =+B18+1 -> 12 | C19: PRODUCT_TYPE | G19: 본판구분 | J19: PRODUCT_TYPE | L19: nvarchar2 | M19: 1000 | N19: 본판구분
B20: =+B19+1 -> 13 | C20: LOT_NO | G20: 롯트넘버 | J20: LOT_NO | L20: nvarchar2 | M20: 1000 | N20: 롯트넘버
B21: =+B20+1 -> 14 | C21: EXPIRATION_DATE | G21: 사용기한 | J21: EXPIRATION_DATE | L21: nvarchar2 | M21: 1000 | N21: 사용기한
B22: =+B21+1 -> 15 | C22: INBOUND_DATE | G22: 입고일자 | J22: INBOUND_DATE | L22: nvarchar2 | M22: 1000 | N22: 입고일자
B23: =+B22+1 -> 16 | C23: LAST_OUTBOUND_DATE | G23: 최종출고일 | J23: LAST_OUTBOUND_DATE | L23: nvarchar2 | M23: 1000 | N23: 최종출고일
B24: =+B23+1 -> 17 | C24: STOCK_STATUS | G24: 재고상태 | J24: STOCK_STATUS | L24: nvarchar2 | M24: 1000 | N24: 재고상태
B25: =+B24+1 -> 18 | C25: QUALITY_STATUS | J25: QUALITY_STATUS | L25: nvarchar2 | M25: 1000
B26: =+B25+1 -> 19 | C26: BASE_UNIT | G26: 주문단위 | J26: BASE_UNIT | L26: nvarchar2 | M26: 1000 | N26: 주문단위
B27: =+B26+1 -> 20 | C27: DAY_KEY | I27: 7 | J27: DAY_KEY | L27: nvarchar2 | M27: 1000
B28: =+B27+1 -> 21 | C28: IDX | I28: 8 | J28: IDX | L28: nvarchar2 | M28: 1000
B29: =+B28+1 -> 22 | C29: ZONE | I29: 9 | J29: ZONE | L29: nvarchar2 | M29: 1000
B30: =+B29+1 -> 23 | C30: STORAGE_TYPE | G30: 로케이션종류 | H30: 팔레트-쉘프-평치등 | I30: 10 | J30: STORAGE_TYPE | L30: nvarchar2 | M30: 1000 | N30: 로케이션종류 | O30: 팔레트-쉘프-평치등
B31: =+B30+1 -> 24 | C31: MANUFACTURING_DATE | G31: 제조일자 | I31: 11 | J31: MANUFACTURING_DATE | L31: nvarchar2 | M31: 1000 | N31: 제조일자
B32: =+B31+1 -> 25 | C32: BOXES_PER_PALLET | G32: 팔레트 입수 | I32: 12 | J32: BOXES_PER_PALLET | L32: nvarchar2 | M32: 1000 | N32: 팔레트 입수
B33: =+B32+1 -> 26 | C33: UNITS_PER_BOX | G33: 박스 입수 | I33: 13 | J33: UNITS_PER_BOX | L33: nvarchar2 | M33: 1000 | N33: 박스 입수
B34: =+B33+1 -> 27 | C34: UNITS_PER_INNER_BOX | G34: ta 입수 | I34: 14 | J34: UNITS_PER_INNER_BOX | L34: nvarchar2 | M34: 1000 | N34: ta 입수
B35: =+B34+1 -> 28 | C35: FILE_NAME | I35: 15 | J35: FILE_NAME | L35: nvarchar2 | M35: 1000
B36: =+B35+1 -> 29 | C36: CREATED_AT | I36: 16 | J36: CREATED_AT | L36: nvarchar2 | M36: 1000
B37: =+B36+1 -> 30 | C37: BRND_NM | I37: 17 | J37: BRND_NM | L37: nvarchar2 | M37: 1000
B38: =+B37+1 -> 31 | C38: PRD_NM | G38: 제품명(KO) | I38: 18 | J38: PRD_NM | L38: nvarchar2 | M38: 1000 | N38: 제품명(KO)
B39: =+B38+1 -> 32 | C39: RPRS_PRD_CD | G39: 대표상품코드 | I39: 19 | J39: RPRS_PRD_CD | L39: nvarchar2 | M39: 1000 | N39: 대표상품코드
B40: =+B39+1 -> 33 | C40: RPRS_PRD_NM | G40: 대표상품명 | I40: 20 | J40: RPRS_PRD_NM | L40: nvarchar2 | M40: 1000 | N40: 대표상품명
B41: =+B40+1 -> 34 | C41: CURR_CD | G41: 통화 | I41: 21 | J41: CURR_CD | L41: nvarchar2 | M41: 1000 | N41: 통화
B42: =+B41+1 -> 35 | C42: INSD_UTPR_AMT | I42: 22 | J42: INSD_UTPR_AMT | L42: nvarchar2 | M42: 1000
B43: =+B42+1 -> 36 | C43: ETL_PROC_DTTM | I43: 23 | J43: ETL_PROC_DTTM | L43: nvarchar2 | M43: 1000
B44: =+B43+1 -> 37 | I44: 24
B45: =+B44+1 -> 38 | I45: 25
B46: =+B45+1 -> 39 | I46: 26
B47: =+B46+1 -> 40 | I47: 27
B48: =+B47+1 -> 41 | I48: 28
B49: =+B48+1 -> 42 | I49: 29
B50: =+B49+1 -> 43 | I50: 30
B51: =+B50+1 -> 44 | I51: 31
B54: 변환규칙정의
B55: 변환규칙 | D55: 내용
B56: R1
B57: R2
B59: 기타정보
B60: 이벤트 발생조건 (DB Trigger)
B61: 연계데이터 추출조건
B62: 데이터 반영방법
B63: 기타
B65: ID#AAAAwkmaw3M
B66: AC800097 (2023-05-11 05:12:59)
B67: A001 회사코드
B68: A002 국가코드
B69: A003 영업조직코드
... B73: A007 PG유형코드로 정의하고 코드키를 보내드릴 것입니다. SAP기준으로 맵핑 부탁드립니다.

Sheet 엔진상품리스트
A1: Top
B2: 매핑정의서 - 엔진상품 리스트 | J2: Source System | K2: CDP | O2: 문서작성일 | P2: 2025.09.25
J3: Target System | K3: APLAN | O3: 버전 | P3: 0.1
B4: 매핑정의
B5: Source Table : cdp.sf_cdpdw.D_USER_DFN_PRD_GRP_MSTR | I5: Target Table : ? | R5: Set Value | S5: 변환규칙
B6: RFC | I6: Web SVC
B7: SEQ | C7: Field | D7: PK | E7: Type | F7: Size | G7: Desc | H7: Desc(ENG) | I7: SEQ | J7: Field | K7: PK | L7: Type | M7: Size | N7: Desc | O7: Desc(ENG) | P7: Req No | Q7: Res No
B8: 1 | C8: BU_NM | E8: CHAR | G8: 부문명 | I8: 1 | J8: BU_NM | L8: nvarchar2 | M8: 1000 | N8: 부문명
B9: 2 | C9: SLS_TEAM_NM | E9: CHAR | G9: 팀명 | I9: 2 | J9: SLS_TEAM_NM | L9: nvarchar2 | M9: 1000 | N9: 팀명
B10: 3 | C10: PRD_CD | E10: CHAR | G10: 상품코드 | I10: 3 | J10: PRD_CD | L10: nvarchar2 | M10: 1000 | N10: 상품코드
B11: 4 | C11: PRD_GRP_0 | E11: CHAR | G11: 상품그룹0 | I11: 4 | J11: PRD_GRP_0 | L11: nvarchar2 | M11: 1000 | N11: 상품그룹0
B12: 5 | C12: PRD_GRP_1 | E12: CHAR | G12: 상품그룹1 | I12: 5 | J12: PRD_GRP_1 | L12: nvarchar2 | M12: 1000 | N12: 상품그룹1
B13: 6 | C13: PRD_GRP_2 | E13: CHAR | G13: 상품그룹2 | I13: 6 | J13: PRD_GRP_2 | L13: nvarchar2 | M13: 1000 | N13: 상품그룹2
B14: 7 | C14: PRD_GRP_3 | E14: CHAR | G14: 상품그룹3 | I14: 7 | J14: PRD_GRP_3 | L14: nvarchar2 | M14: 1000 | N14: 상품그룹3
B15: 8 | C15: PRD_GRP_4 | E15: CHAR | G15: 상품그룹4 | I15: 8 | J15: PRD_GRP_4 | L15: nvarchar2 | M15: 1000 | N15: 상품그룹4
B16: 9 | C16: PRD_GRP_5 | E16: CHAR | G16: 상품그룹5 | I16: 9 | J16: PRD_GRP_5 | L16: nvarchar2 | M16: 1000 | N16: 상품그룹5
B17: 10 | C17: PRD_GRP_6 | E17: CHAR | G17: 상품그룹6 | I17: 10 | J17: PRD_GRP_6 | L17: nvarchar2 | M17: 1000 | N17: 상품그룹6
B18: 11 | C18: PRD_GRP_7 | E18: CHAR | G18: 상품그룹7 | I18: 11 | J18: PRD_GRP_7 | L18: nvarchar2 | M18: 1000 | N18: 상품그룹7
B19: 12 | C19: PRD_GRP_8 | E19: CHAR | G19: 상품그룹8 | I19: 12 | J19: PRD_GRP_8 | L19: nvarchar2 | M19: 1000 | N19: 상품그룹8
... B21: 14 | C21: ETL_PROC_DTTM TIMESTAMP | E21: CHAR | G21: ETL처리일시 | I21: 14 | J21: ETL_PROC_DTTM TIMESTAMP | L21: nvarchar2 | M21: 1000 | N21: ETL처리일시
B22: 15 | I22: 15
B23: 16 | I23: 16
B24: 17 | I24: 17
B25: 18 | I25: 18
B26: 19 | I26: 19
B27: 20 | I27: 20
B28: 21 | I28: 21
B29: 22 | I29: 22
B30: 23 | I30: 23
B31: 24 | I31: 24
B32: 25 | I32: 25
B33: 26 | I33: 26
... B38: 31 | I38: 31
B41: 변환규칙정의
B42: 변환규칙 | D42: 내용
B43: R1
B44: R2
B46: 기타정보
B47: 이벤트 발생조건 (DB Trigger)
B48: 연계데이터 추출조건
B49: 데이터 반영방법
B50: 기타
B52: ID#AAAAwkmaw3M
B53: AC800097 (2023-05-11 05:12:59)
B54: A001 회사코드
B55: A002 국가코드
B56: A003 영업조직코드
... B60: A007 PG유형코드로 정의하고 코드키를 보내드릴 것입니다. SAP기준으로 맵핑 부탁드립니다.

Sheet DP-42-1.자재정보추가_BW
A1: Top
B2: 매핑정의서 -DP-42-1.자재정보추가_BW | J2: Source System | K2: BW | O2: 문서작성일 | P2: 2025.09.25
J3: Target System | K3: APLAN | O3: 버전 | P3: 0.1
B4: 매핑정의
B5: Source Table : ? | I5: Target Table : ? | R5: Set Value | S5: 변환규칙 | Z5: CDP 자재 마스터 테이블 명세서 (D_PRD_MSTR)
B6: RFC | I6: Web SVC
B7: SEQ | C7: Field | D7: PK | E7: Type | F7: Size | G7: Desc | H7: Desc(ENG) | I7: SEQ | J7: Field | K7: PK | L7: Type | M7: Size | N7: Desc | O7: Desc(ENG) | P7: Req No | Q7: Res No | Z7: 컬럼명 | AA7: 데이터타입 | AB7: 한글명 | AC7: 영문명
B8: 1 | C8: 0MATERIAL | D8: O | E8: CHAR | F8: 40 | G8: 자재코드 | I8: 1 | J8: ITEM | K8: O | L8: NVARCHAR2 | M8: 1000 | N8: 자재코드 | Z8: PRD_CD | AA8: VARCHAR(12) | AB8: 상품코드 | AC8: Product Code.
B9: 2 | C9: ZDBSBIG | E9: CHAR | F9: 10 | G9: DBS 제품대유형 | I9: 2 | J9: ZDBSBIG | L9: NVARCHAR2 | M9: 1000 | N9: DBS 제품대유형 | Z9: PRD_NM | AA9: VARCHAR(100) | AB9: 상품명 | AC9: Product Name.
B10: 3 | C10: ZDBSMID | E10: CHAR | F10: 10 | G10: DBS 제품중유형 | I10: 3 | J10: ZDBSMID | L10: NVARCHAR2 | M10: 1000 | N10: DBS 제품중유형 | Z10: PRD_ENGL_NM | AA10: VARCHAR(200) | AB10: 상품영어명 | AC10: Product English Name.
B11: 4 | C11: ZDBSSML | E11: CHAR | F11: 10 | G11: DBS 제품소유형 | I11: 4 | J11: ZDBSSML | L11: NVARCHAR2 | M11: 1000 | N11: DBS 제품소유형 | Z11: ENGL_PRD_NM | AA11: VARCHAR(100) | AB11: 영어상품명(비표준) | AC11: English Product Name (Non-Standard).
B12: 5 | C12: ZDBSBRLNB | E12: CHAR | F12: 20 | G12: DBS 브랜드라인1 | I12: 5 | J12: ZDBSBRLNB | L12: NVARCHAR2 | M12: 1000 | N12: DBS 브랜드라인1 | Z12: BRND_CD | AA12: VARCHAR(5) | AB12: 브랜드코드 | AC12: Brand Code.
B13: 6 | C13: ZDBSBRLNC | E13: CHAR | F13: 20 | G13: DBS 브랜드라인2 | I13: 6 | J13: ZDBSBRLNC | L13: NVARCHAR2 | M13: 1000 | N13: DBS 브랜드라인2 | Z13: BRND_DTL_CD | AA13: VARCHAR(6) | AB13: 브랜드상세코드 | AC13: Brand Detail Code.
B14: 7 | C14: ZMAGRV | E14: CHAR | F14: 4 | G14: 포장재그룹 | I14: 7 | J14: ZMAGRV | L14: NVARCHAR2 | M14: 1000 | N14: 포장재그룹 | Z14: RPRS_PRD_CD | AA14: VARCHAR(12) | AB14: 대표상품코드 | AC14: Representative Product Code.
B15: 8 | C15: ZPGENDCUS | E15: CHAR | F15: 10 | G15: 포장재 계층구조 | I15: 8 | J15: ZPGENDCUS | L15: NVARCHAR2 | M15: 1000 | N15: 포장재 계층구조 | Z15: RPRS_PRD_NM | AA15: VARCHAR(100) | AB15: 대표상품명 | AC15: Product Name.
B16: 9 | C16: ZPRO_HLV1 | E16: CHAR | F16: 18 | G16: 제품유형 1레벨 | I16: 9 | J16: ZPRO_HLV1 | L16: NVARCHAR2 | M16: 1000 | N16: 제품유형 1레벨 | Z16: RPRS_PRD_ENGL_NM | AA16: VARCHAR(100) | AB16: 대표상품영어명 | AC16: Representative Product English Name.
B17: 10 | C17: ZPRO_HLV2 | E17: CHAR | F17: 18 | G17: 제품유형 2레벨 | I17: 10 | J17: ZPRO_HLV2 | L17: NVARCHAR2 | M17: 1000 | N17: 제품유형 2레벨 | Z17: RPLC_PRD_CD | AA17: VARCHAR(12) | AB17: 대체상품코드 | AC17: Alternative Product Code.
B18: 11 | C18: ZPRO_HLV3 | E18: CHAR | F18: 18 | G18: 제품유형 3레벨 | I18: 11 | J18: ZPRO_HLV3 | L18: NVARCHAR2 | M18: 1000 | N18: 제품유형 3레벨 | Z18: PRD_MKT_CAT_CD | AA18: VARCHAR(2) | AB18: 상품마케팅분류코드 | AC18: Product Marketing Classification Code.
B19: 12 | C19: ZRPFUT | E19: CHAR | F19: 10 | G19: 대표기능 | I19: 12 | J19: ZRPFUT | L19: NVARCHAR2 | M19: 1000 | N19: 대표기능 | Z19: SET_PRD_YN | AA19: VARCHAR(1) | AB19: 세트상품여부 | AC19: Set product or not.
B20: 13 | C20: ZSDCOLOR | E20: CHAR | F20: 3 | G20: 색상 | I20: 13 | J20: ZSDCOLOR | L20: NVARCHAR2 | M20: 1000 | N20: 색상 | Z20: SET_DSMN_YN | AA20: VARCHAR(1) | AB20: 세트해체여부 | AC20: Set disassembly.
... B25: 18 | C25: ZBLAMOS | E25: CHAR | F25: 4 | G25: 브랜드라인(아모스) | I25: 18 | J25: ZBLAMOS | L25: NVARCHAR2 | M25: 1000 | N25: 브랜드라인(아모스) | Z25: PRD_CAT_CD | AA25: VARCHAR(10) | AB25: 상품분류코드 | AC25: Product Classification Code.
B26: 19 | I26: 19 | Z26: MAIN_FUNC_CD | AA26: VARCHAR(4) | AB26: 주요기능코드 | AC26: Main Function Code.
B27: 20 | I27: 20 | Z27: USER_TP_CD | AA27: VARCHAR(1) | AB27: 사용자유형코드 | AC27: User Type Code.
B28: 21 | I28: 21 | Z28: FRSH_CSMT_YN | AA28: VARCHAR(1) | AB28: 신선화장품여부 | AC28: Fresh Cosmetics.
B29: 22 | I29: 22 | Z29: PRD_CL_CD | AA29: VARCHAR(2) | AB29: 상품구분코드 | AC29: Product Classification Code.
B30: 23 | I30: 23 | Z30: SLS_TP_CD | AA30: VARCHAR(3) | AB30: 영업유형코드 | AC30: Sales Type Code.
B31: 24 | I31: 24 | Z31: SAP_PRD_LN_CD | AA31: VARCHAR(4) | AB31: SAP상품라인코드 | AC31: SAP Product Line Code.
B32: 25 | I32: 25 | Z32: PRD_CLR_CD | AA32: VARCHAR(4) | AB32: 상품색상코드 | AC32: Product Color Code.
B33: 26 | I33: 26 | Z33: NEW_PRD_CL_CD | AA33: VARCHAR(3) | AB33: 신상품구분코드 | AC33: New Product Code.
B34: 27 | I34: 27 | Z34: STRO_PRD_YN | AA34: VARCHAR(1) | AB34: 강한상품여부 | AC34: Strong product or not.
B35: 28 | I35: 28 | Z35: INNO_PRD_YN | AA35: VARCHAR(1) | AB35: 혁신상품여부 | AC35: Innovative Product Status.
B36: 29 | I36: 29 | Z36: CUSH_PRD_YN | AA36: VARCHAR(1) | AB36: 쿠션상품여부 | AC36: Cushion product status.
B37: 30 | I37: 30 | Z37: PRD_GRD_CD | AA37: VARCHAR(3) | AB37: 상품등급코드 | AC37: Product Grade Code.
B38: 31 | I38: 31 | Z38: BRND_LN_CD | AA38: VARCHAR(4) | AB38: 브랜드라인코드 | AC38: Brand Line Code.
Z39: MFG_PLNT_CD | AA39: VARCHAR(4) | AB39: 생산플랜트코드 | AC39: Production Plant Code.
Z40: NITM_APLY_YN | AA40: VARCHAR(1) | AB40: 품목수적용여부 | AC40: Item Application.
B41: 변환규칙정의 | Z41: FST_MFG_DT | AA41: VARCHAR(10) | AB41: 최초생산일자 | AC41: Initial Production Date.
B42: 변환규칙 | D42: 내용 | Z42: LST_MFG_DT | AA42: VARCHAR(10) | AB42: 최종생산일자 | AC42: Final production date.
B43: R1 | Z43: PRD_BRCD_CD | AA43: VARCHAR(15) | AB43: 상품바코드코드 | AC43: Product barcode code.
B44: R2 | Z44: REG_APPL_CL_CD | AA44: VARCHAR(10) | AB44: 등록어플리케이션구분코드 | AC44: Registration Application Type Code.
Z45: CP_PRD_YN | AA45: VARCHAR(1) | AB45: 자사상품여부 | AC45: Is it a company product?.
B46: 기타정보 | Z46: INSD_MGNT_AMT | AA46: NUMBER(20,3) | AB46: 내부관리금액 | AC46: Internal Management Amount.
B47: 이벤트 발생조건 (DB Trigger) | Z47: WKPL_CL_CD | AA47: VARCHAR(10) | AB47: 사업장구분코드 | AC47: Business Site Classification Code.
B48: 연계데이터 추출조건 | Z48: ASRC_PRD_MKT_CAT_CD | AA48: VARCHAR(2) | AB48: 소스상품마케팅분류코드 | AC48: Source Product Marketing Classification Code.
B49: 데이터 반영방법 | Z49: ASRC_PRD_CAT_CD | AA49: VARCHAR(10) | AB49: 소스상품분류코드 | AC49: Source Product Classification Code.
B50: 기타 | Z50: PRD_TP_CD | AA50: VARCHAR(4) | AB50: 상품유형코드 | AC50: Product Type Code.

Sheet DP-42-2.자재정보추가_BW
A1: Top
B2: 매핑정의서 -DP-42-2.자재정보추가_BW | J2: Source System | K2: BW | O2: 문서작성일 | P2: 2025.09.25
J3: Target System | K3: APLAN | O3: 버전 | P3: 0.1
B4: 매핑정의
B5: Source Table : ? | I5: Target Table : ? | R5: Set Value | S5: 변환규칙 | Z5: CDP 자재 마스터 테이블 명세서 (D_PRD_MSTR)
B6: RFC | I6: Web SVC
B7: SEQ | C7: Field | D7: PK | E7: Type | F7: Size | G7: Desc | H7: Desc(ENG) | I7: SEQ | J7: Field | K7: PK | L7: Type | M7: Size | N7: Desc | O7: Desc(ENG) | P7: Req No | Q7: Res No | Z7: 컬럼명 | AA7: 데이터타입 | AB7: 한글명 | AC7: 영문명
B8: 1 | C8: 0MAT_SALES | D8: O | E8: CHAR | F8: 40 | G8: 자재코드 | I8: 1 | J8: ITEM | K8: O | L8: NVARCHAR2 | M8: 1000 | N8: 자재코드 | Z8: PRD_CD | AA8: VARCHAR(12) | AB8: 상품코드 | AC8: Product Code.
B9: 2 | C9: 0salesorg | D9: O | E9: CHAR | F9: 4 | G9: 영업조직 | I9: 2 | J9: SALESORG | K9: O | L9: NVARCHAR2 | M9: 1000 | N9: 영업조직 | Z9: PRD_NM | AA9: VARCHAR(100) | AB9: 상품명 | AC9: Product Name.
B10: 3 | C10: 0distr_chan | D10: O | E10: CHAR | F10: 2 | G10: 유통경로 | I10: 3 | J10: DIST_CHANN | K10: O | L10: NVARCHAR2 | M10: 1000 | N10: 유통경로 | Z10: PRD_ENGL_NM | AA10: VARCHAR(200) | AB10: 상품영어명 | AC10: Product English Name.
B11: 4 | C11: ZFRDAT | E11: DATS | F11: 8 | G11: 최초입고일 | I11: 4 | J11: ZFRDAT | L11: NVARCHAR2 | M11: 1000 | N11: 최초입고일 | Z11: ENGL_PRD_NM | AA11: VARCHAR(100) | AB11: 영어상품명(비표준) | AC11: English Product Name (Non-Standard).
B12: 5 | C12: ZLRDAT | E12: DATS | F12: 8 | G12: 최종입고일 | I12: 5 | J12: ZLRDAT | L12: NVARCHAR2 | M12: 1000 | N12: 최종입고일 | Z12: BRND_CD | AA12: VARCHAR(5) | AB12: 브랜드코드 | AC12: Brand Code.
B13: 6 | C13: ZSKURG | E13: CHAR | F13: 1 | G13: 제품매출등급 | I13: 6 | J13: ZSKURG | L13: NVARCHAR2 | M13: 1000 | N13: 제품매출등급 | Z13: BRND_DTL_CD | AA13: VARCHAR(6) | AB13: 브랜드상세코드 | AC13: Brand Detail Code.
B14: 7 | C14: ZSLMV | E14: CHAR | F14: 1 | G14: 부동재고 구분자-현시점(N) | I14: 7 | J14: ZSLMV | L14: NVARCHAR2 | M14: 1000 | N14: 부동재고 구분자-현시점(N) | Z14: RPRS_PRD_CD | AA14: VARCHAR(12) | AB14: 대표상품코드 | AC14: Representative Product Code.
B15: 8 | C15: ZSLOWFALG | E15: CHAR | F15: 1 | G15: 부진진고 구분자-현시점(N) | I15: 8 | J15: ZSLOWFALG | L15: NVARCHAR2 | M15: 1000 | N15: 부진진고 구분자-현시점(N) | Z15: RPRS_PRD_NM | AA15: VARCHAR(100) | AB15: 대표상품명 | AC15: Product Name.
B16: 9 | I16: 9 | Z16: RPRS_PRD_ENGL_NM | AA16: VARCHAR(100) | AB16: 대표상품영어명 | AC16: Representative Product English Name.
B17: 10 | I17: 10 | Z17: RPLC_PRD_CD | AA17: VARCHAR(12) | AB17: 대체상품코드 | AC17: Alternative Product Code.
B18: 11 | I18: 11 | Z18: PRD_MKT_CAT_CD | AA18: VARCHAR(2) | AB18: 상품마케팅분류코드 | AC18: Product Marketing Classification Code.
B19: 12 | I19: 12 | Z19: SET_PRD_YN | AA19: VARCHAR(1) | AB19: 세트상품여부 | AC19: Set product or not.
B20: 13 | I20: 13 | Z20: SET_DSMN_YN | AA20: VARCHAR(1) | AB20: 세트해체여부 | AC20: Set disassembly.
B21: 14 | I21: 14 | Z21: CNSM_UTPR_AMT | AA21: NUMBER(20,3) | AB21: 소비자단가금액 | AC21: Consumer Unit Price.
B22: 15 | I22: 15 | Z22: PRD_CPT | AA22: NUMBER(38,0) | AB22: 상품용량 | AC22: Product Capacity.
B23: 16 | I23: 16 | Z23: PRD_CPT_UNIT_CD | AA23: VARCHAR(3) | AB23: 상품용량단위코드 | AC23: Product Unit Code.
B24: 17 | I24: 17 | Z24: PRD_USE_CD | AA24: VARCHAR(3) | AB24: 상품용도코드 | AC24: Product Use Code.
B25: 18 | I25: 18 | Z25: PRD_CAT_CD | AA25: VARCHAR(10) | AB25: 상품분류코드 | AC25: Product Classification Code.
B26: 19 | I26: 19 | Z26: MAIN_FUNC_CD | AA26: VARCHAR(4) | AB26: 주요기능코드 | AC26: Main Function Code.
B27: 20 | I27: 20 | Z27: USER_TP_CD | AA27: VARCHAR(1) | AB27: 사용자유형코드 | AC27: User Type Code.
... B38: 31 | I38: 31 | Z38: BRND_LN_CD | AA38: VARCHAR(4) | AB38: 브랜드라인코드 | AC38: Brand Line Code.
Z39: MFG_PLNT_CD | AA39: VARCHAR(4) | AB39: 생산플랜트코드 | AC39: Production Plant Code.
Z40: NITM_APLY_YN | AA40: VARCHAR(1) | AB40: 품목수적용여부 | AC40: Item Application.
B41: 변환규칙정의 | Z41: FST_MFG_DT | AA41: VARCHAR(10) | AB41: 최초생산일자 | AC41: Initial Production Date.
B42: 변환규칙 | D42: 내용 | Z42: LST_MFG_DT | AA42: VARCHAR(10) | AB42: 최종생산일자 | AC42: Final production date.
B43: R1 | Z43: PRD_BRCD_CD | AA43: VARCHAR(15) | AB43: 상품바코드코드 | AC43: Product barcode code.
B44: R2 | Z44: REG_APPL_CL_CD | AA44: VARCHAR(10) | AB44: 등록어플리케이션구분코드 | AC44: Registration Application Type Code.
